Workbook

Sheet Tableau_de_bord
B2: DealPME : tableau de bord du projet
B3: Toutes les valeurs de cette page sont calculées. Pour mettre à jour le projet, modifier uniquement l'onglet Taches (statuts, % saisi, dates) et les onglets Jalons, Risques, Decisions.
B4: Date du jour | C4: =TODAY() | E4: Jours avant la démonstration V1 | G4: =Versions!E6-TODAY() | I4: Périmètre cible | J4: Cahier des charges v0 + Référentiel P04-P25
B6: Avancement global | D6: Charge totale (j/p) | F6: Charge réalisée (j/p) | H6: Charge totale (sem.-pers.) | J6: Tâches | L6: Faites
B7: =Modules!I26 | D7: =Modules!G26 | F7: =Modules!H26 | H7: =Modules!G26/5 | J7: =Modules!J26 | L7: =Modules!K26
B9: En cours | D9: Bloquées | F9: En retard | H9: Risques critiques ou élevés ouverts | J9: Décisions ouvertes | L9: Jalons dépassés
B10: =Modules!L26 | D10: =Modules!M26 | F10: =Modules!N26 | H10: =COUNTIFS(Risques!$H$6:$H$68,"Critique",Risques!$L$6:$L$68,"<>Clos")+COUNTIFS(Risques!$H$6:$H$68,"Élevé",Risques!$L$6:$L$68,"<>Clos") | J10: =COUNTIF(Decisions!$F$6:$F$67,"Ouvert")+COUNTIF(Decisions!$F$6:$F$67,"En discussion") | L10: =COUNTIF(Jalons!$I$6:$I$22,"Dépassé")
B12: Tâches sans responsable | D12: Charge non assignée (j/p) | F12: Personnes actives dans l'équipe | H12: Charge restante (j/p) | J12: Semaines-personne restantes | L12: Risques ouverts (tous niveaux)
B13: =Equipe!$C$48 | D13: =Equipe!$C$49 | F13: =COUNTIF(Equipe!$H$6:$H$45,"Oui") | H13: =Modules!G26-Modules!H26 | J13: =(Modules!G26-Modules!H26)/5 | L13: =COUNTIF(Risques!$L$6:$L$68,"Ouvert")
B16: Avancement par version
B17: Version | C17: Objet | D17: Fin prévue | E17: Jours restants | F17: Charge (sem.) | G17: Avancement | H17: Tâches | I17: Faites | J17: Bloquées | K17: En retard | L17: État
B18: =Versions!B6 | C18: =Versions!C6 | D18: =Versions!E6 | E18: =Versions!F6 | F18: =Versions!H6 | G18: =Versions!J6 | H18: =Versions!K6 | I18: =Versions!L6 | J18: =Versions!N6 | K18: =Versions!O6 | L18: =Versions!P6
B19: =Versions!B7 | C19: =Versions!C7 | D19: =Versions!E7 | E19: =Versions!F7 | F19: =Versions!H7 | G19: =Versions!J7 | H19: =Versions!K7 | I19: =Versions!L7 | J19: =Versions!N7 | K19: =Versions!O7 | L19: =Versions!P7
B20: =Versions!B8 | C20: =Versions!C8 | D20: =Versions!E8 | E20: =Versions!F8 | F20: =Versions!H8 | G20: =Versions!J8 | H20: =Versions!K8 | I20: =Versions!L8 | J20: =Versions!N8 | K20: =Versions!O8 | L20: =Versions!P8
B21: =Versions!B9 | C21: =Versions!C9 | D21: =Versions!E9 | E21: =Versions!F9 | F21: =Versions!H9 | G21: =Versions!J9 | H21: =Versions!K9 | I21: =Versions!L9 | J21: =Versions!N9 | K21: =Versions!O9 | L21: =Versions!P9
B22: =Versions!B10 | C22: =Versions!C10 | D22: =Versions!E10 | E22: =Versions!F10 | F22: =Versions!H10 | G22: =Versions!J10 | H22: =Versions!K10 | I22: =Versions!L10 | J22: =Versions!N10 | K22: =Versions!O10 | L22: =Versions!P10
B25: Avancement par module
B26: Code | C26: Module | D26: Version cible | E26: Charge (j/p) | F26: Avancement | G26: Tâches | H26: Faites | I26: En cours | J26: Bloquées | K26: En retard | L26: État
B27: =Modules!B6 | C27: =Modules!C6 | D27: =Modules!F6 | E27: =Modules!G6 | F27: =Modules!I6 | G27: =Modules!J6 | H27: =Modules!K6 | I27: =Modules!L6 | J27: =Modules!M6 | K27: =Modules!N6 | L27: =Modules!O6
B28: =Modules!B7 | C28: =Modules!C7 | D28: =Modules!F7 | E28: =Modules!G7 | F28: =Modules!I7 | G28: =Modules!J7 | H28: =Modules!K7 | I28: =Modules!L7 | J28: =Modules!M7 | K28: =Modules!N7 | L28: =Modules!O7
B29: =Modules!B8 | C29: =Modules!C8 | D29: =Modules!F8 | E29: =Modules!G8 | F29: =Modules!I8 | G29: =Modules!J8 | H29: =Modules!K8 | I29: =Modules!L8 | J29: =Modules!M8 | K29: =Modules!N8 | L29: =Modules!O8
B30: =Modules!B9 | C30: =Modules!C9 | D30: =Modules!F9 | E30: =Modules!G9 | F30: =Modules!I9 | G30: =Modules!J9 | H30: =Modules!K9 | I30: =Modules!L9 | J30: =Modules!M9 | K30: =Modules!N9 | L30: =Modules!O9
B31: =Modules!B10 | C31: =Modules!C10 | D31: =Modules!F10 | E31: =Modules!G10 | F31: =Modules!I10 | G31: =Modules!J10 | H31: =Modules!K10 | I31: =Modules!L10 | J31: =Modules!M10 | K31: =Modules!N10 | L31: =Modules!O10
B32: =Modules!B11 | C32: =Modules!C11 | D32: =Modules!F11 | E32: =Modules!G11 | F32: =Modules!I11 | G32: =Modules!J11 | H32: =Modules!K11 | I32: =Modules!L11 | J32: =Modules!M11 | K32: =Modules!N11 | L32: =Modules!O11
B33: =Modules!B12 | C33: =Modules!C12 | D33: =Modules!F12 | E33: =Modules!G12 | F33: =Modules!I12 | G33: =Modules!J12 | H33: =Modules!K12 | I33: =Modules!L12 | J33: =Modules!M12 | K33: =Modules!N12 | L33: =Modules!O12
B34: =Modules!B13 | C34: =Modules!C13 | D34: =Modules!F13 | E34: =Modules!G13 | F34: =Modules!I13 | G34: =Modules!J13 | H34: =Modules!K13 | I34: =Modules!L13 | J34: =Modules!M13 | K34: =Modules!N13 | L34: =Modules!O13
B35: =Modules!B14 | C35: =Modules!C14 | D35: =Modules!F14 | E35: =Modules!G14 | F35: =Modules!I14 | G35: =Modules!J14 | H35: =Modules!K14 | I35: =Modules!L14 | J35: =Modules!M14 | K35: =Modules!N14 | L35: =Modules!O14
B36: =Modules!B15 | C36: =Modules!C15 | D36: =Modules!F15 | E36: =Modules!G15 | F36: =Modules!I15 | G36: =Modules!J15 | H36: =Modules!K15 | I36: =Modules!L15 | J36: =Modules!M15 | K36: =Modules!N15 | L36: =Modules!O15
B37: =Modules!B16 | C37: =Modules!C16 | D37: =Modules!F16 | E37: =Modules!G16 | F37: =Modules!I16 | G37: =Modules!J16 | H37: =Modules!K16 | I37: =Modules!L16 | J37: =Modules!M16 | K37: =Modules!N16 | L37: =Modules!O16
B38: =Modules!B17 | C38: =Modules!C17 | D38: =Modules!F17 | E38: =Modules!G17 | F38: =Modules!I17 | G38: =Modules!J17 | H38: =Modules!K17 | I38: =Modules!L17 | J38: =Modules!M17 | K38: =Modules!N17 | L38: =Modules!O17
... B46: =Modules!B25 | C46: =Modules!C25 | D46: =Modules!F25 | E46: =Modules!G25 | F46: =Modules!I25 | G46: =Modules!J25 | H46: =Modules!K25 | I46: =Modules!L25 | J46: =Modules!M25 | K46: =Modules!N25 | L46: =Modules!O25
B49: Prochain jalon | D49: =IFERROR(INDEX(Jalons!$C$6:$C$22,MATCH(MIN(Jalons!$J$6:$J$22),Jalons!$J$6:$J$22,0)),"Aucun") | J49: =IFERROR(MIN(Jalons!$J$6:$J$22),"")
B50: Jalons des 30 prochains jours | D50: =COUNTIFS(Jalons!$E$6:$E$22,">="&TODAY(),Jalons!$E$6:$E$22,"<="&(TODAY()+30),Jalons!$F$6:$F$22,"<>Atteint")
B53: Charge par personne (équipe inscrite)
B54: Nom | C54: Rôle | D54: Actif | E54: Tâches | F54: Charge (j/p) | G54: Réalisé (j/p) | H54: Avancement | I54: En cours | J54: Bloquées | K54: En retard | L54: Restant (j/p)
B55: =IF(Equipe!B6="","",Equipe!B6) | C55: =IF(Equipe!B6="","",Equipe!C6) | D55: =IF(Equipe!B6="","",Equipe!H6) | E55: =IF(Equipe!B6="","",Equipe!I6) | F55: =IF(Equipe!B6="","",Equipe!J6) | G55: =IF(Equipe!B6="","",Equipe!K6) | H55: =IF(Equipe!B6="","",Equipe!L6) | I55: =IF(Equipe!B6="","",Equipe!M6) | J55: =IF(Equipe!B6="","",Equipe!N6) | K55: =IF(Equipe!B6="","",Equipe!O6) | L55: =IF(Equipe!B6="","",Equipe!Q6)
B56: =IF(Equipe!B7="","",Equipe!B7) | C56: =IF(Equipe!B7="","",Equipe!C7) | D56: =IF(Equipe!B7="","",Equipe!H7) | E56: =IF(Equipe!B7="","",Equipe!I7) | F56: =IF(Equipe!B7="","",Equipe!J7) | G56: =IF(Equipe!B7="","",Equipe!K7) | H56: =IF(Equipe!B7="","",Equipe!L7) | I56: =IF(Equipe!B7="","",Equipe!M7) | J56: =IF(Equipe!B7="","",Equipe!N7) | K56: =IF(Equipe!B7="","",Equipe!O7) | L56: =IF(Equipe!B7="","",Equipe!Q7)
B57: =IF(Equipe!B8="","",Equipe!B8) | C57: =IF(Equipe!B8="","",Equipe!C8) | D57: =IF(Equipe!B8="","",Equipe!H8) | E57: =IF(Equipe!B8="","",Equipe!I8) | F57: =IF(Equipe!B8="","",Equipe!J8) | G57: =IF(Equipe!B8="","",Equipe!K8) | H57: =IF(Equipe!B8="","",Equipe!L8) | I57: =IF(Equipe!B8="","",Equipe!M8) | J57: =IF(Equipe!B8="","",Equipe!N8) | K57: =IF(Equipe!B8="","",Equipe!O8) | L57: =IF(Equipe!B8="","",Equipe!Q8)
B58: =IF(Equipe!B9="","",Equipe!B9) | C58: =IF(Equipe!B9="","",Equipe!C9) | D58: =IF(Equipe!B9="","",Equipe!H9) | E58: =IF(Equipe!B9="","",Equipe!I9) | F58: =IF(Equipe!B9="","",Equipe!J9) | G58: =IF(Equipe!B9="","",Equipe!K9) | H58: =IF(Equipe!B9="","",Equipe!L9) | I58: =IF(Equipe!B9="","",Equipe!M9) | J58: =IF(Equipe!B9="","",Equipe!N9) | K58: =IF(Equipe!B9="","",Equipe!O9) | L58: =IF(Equipe!B9="","",Equipe!Q9)
B59: =IF(Equipe!B10="","",Equipe!B10) | C59: =IF(Equipe!B10="","",Equipe!C10) | D59: =IF(Equipe!B10="","",Equipe!H10) | E59: =IF(Equipe!B10="","",Equipe!I10) | F59: =IF(Equipe!B10="","",Equipe!J10) | G59: =IF(Equipe!B10="","",Equipe!K10) | H59: =IF(Equipe!B10="","",Equipe!L10) | I59: =IF(Equipe!B10="","",Equipe!M10) | J59: =IF(Equipe!B10="","",Equipe!N10) | K59: =IF(Equipe!B10="","",Equipe!O10) | L59: =IF(Equipe!B10="","",Equipe!Q10)
B60: =IF(Equipe!B11="","",Equipe!B11) | C60: =IF(Equipe!B11="","",Equipe!C11) | D60: =IF(Equipe!B11="","",Equipe!H11) | E60: =IF(Equipe!B11="","",Equipe!I11) | F60: =IF(Equipe!B11="","",Equipe!J11) | G60: =IF(Equipe!B11="","",Equipe!K11) | H60: =IF(Equipe!B11="","",Equipe!L11) | I60: =IF(Equipe!B11="","",Equipe!M11) | J60: =IF(Equipe!B11="","",Equipe!N11) | K60: =IF(Equipe!B11="","",Equipe!O11) | L60: =IF(Equipe!B11="","",Equipe!Q11)
B61: =IF(Equipe!B12="","",Equipe!B12) | C61: =IF(Equipe!B12="","",Equipe!C12) | D61: =IF(Equipe!B12="","",Equipe!H12) | E61: =IF(Equipe!B12="","",Equipe!I12) | F61: =IF(Equipe!B12="","",Equipe!J12) | G61: =IF(Equipe!B12="","",Equipe!K12) | H61: =IF(Equipe!B12="","",Equipe!L12) | I61: =IF(Equipe!B12="","",Equipe!M12) | J61: =IF(Equipe!B12="","",Equipe!N12) | K61: =IF(Equipe!B12="","",Equipe!O12) | L61: =IF(Equipe!B12="","",Equipe!Q12)
B62: =IF(Equipe!B13="","",Equipe!B13) | C62: =IF(Equipe!B13="","",Equipe!C13) | D62: =IF(Equipe!B13="","",Equipe!H13) | E62: =IF(Equipe!B13="","",Equipe!I13) | F62: =IF(Equipe!B13="","",Equipe!J13) | G62: =IF(Equipe!B13="","",Equipe!K13) | H62: =IF(Equipe!B13="","",Equipe!L13) | I62: =IF(Equipe!B13="","",Equipe!M13) | J62: =IF(Equipe!B13="","",Equipe!N13) | K62: =IF(Equipe!B13="","",Equipe!O13) | L62: =IF(Equipe!B13="","",Equipe!Q13)
B63: =IF(Equipe!B14="","",Equipe!B14) | C63: =IF(Equipe!B14="","",Equipe!C14) | D63: =IF(Equipe!B14="","",Equipe!H14) | E63: =IF(Equipe!B14="","",Equipe!I14) | F63: =IF(Equipe!B14="","",Equipe!J14) | G63: =IF(Equipe!B14="","",Equipe!K14) | H63: =IF(Equipe!B14="","",Equipe!L14) | I63: =IF(Equipe!B14="","",Equipe!M14) | J63: =IF(Equipe!B14="","",Equipe!N14) | K63: =IF(Equipe!B14="","",Equipe!O14) | L63: =IF(Equipe!B14="","",Equipe!Q14)
B64: =IF(Equipe!B15="","",Equipe!B15) | C64: =IF(Equipe!B15="","",Equipe!C15) | D64: =IF(Equipe!B15="","",Equipe!H15) | E64: =IF(Equipe!B15="","",Equipe!I15) | F64: =IF(Equipe!B15="","",Equipe!J15) | G64: =IF(Equipe!B15="","",Equipe!K15) | H64: =IF(Equipe!B15="","",Equipe!L15) | I64: =IF(Equipe!B15="","",Equipe!M15) | J64: =IF(Equipe!B15="","",Equipe!N15) | K64: =IF(Equipe!B15="","",Equipe!O15) | L64: =IF(Equipe!B15="","",Equipe!Q15)
B65: =IF(Equipe!B16="","",Equipe!B16) | C65: =IF(Equipe!B16="","",Equipe!C16) | D65: =IF(Equipe!B16="","",Equipe!H16) | E65: =IF(Equipe!B16="","",Equipe!I16) | F65: =IF(Equipe!B16="","",Equipe!J16) | G65: =IF(Equipe!B16="","",Equipe!K16) | H65: =IF(Equipe!B16="","",Equipe!L16) | I65: =IF(Equipe!B16="","",Equipe!M16) | J65: =IF(Equipe!B16="","",Equipe!N16) | K65: =IF(Equipe!B16="","",Equipe!O16) | L65: =IF(Equipe!B16="","",Equipe!Q16)
B66: =IF(Equipe!B17="","",Equipe!B17) | C66: =IF(Equipe!B17="","",Equipe!C17) | D66: =IF(Equipe!B17="","",Equipe!H17) | E66: =IF(Equipe!B17="","",Equipe!I17) | F66: =IF(Equipe!B17="","",Equipe!J17) | G66: =IF(Equipe!B17="","",Equipe!K17) | H66: =IF(Equipe!B17="","",Equipe!L17) | I66: =IF(Equipe!B17="","",Equipe!M17) | J66: =IF(Equipe!B17="","",Equipe!N17) | K66: =IF(Equipe!B17="","",Equipe!O17) | L66: =IF(Equipe!B17="","",Equipe!Q17)

Sheet Presentation
B2: DealPME : présentation du projet
B3: Place de marché de transmission et reprise de PME en Afrique francophone (zone OHADA), pilote Togo, en partenariat avec la CCI-Togo.
B5: 1. Le projet en quelques lignes
B6: DealPME est une infrastructure de confiance pour la transmission et la reprise de PME : elle vérifie les acteurs, prépare les dossiers, met en relation sous confidentialité contrôlée, sécurise la divulgation d'information et orchestre la transaction avec des professionnels. DealPME est un fournisseur logiciel : elle ne valorise pas, ne certifie pas, ne détient pas de fonds et n'est jamais partie à la transaction. La certification Deal-Ready est une décision souveraine et nominative de la CCI-Togo.
B7: Signature de marque : « Là où les entreprises changent de mains. »
B9: 2. Documents de référence et autorité
B10: Document | C10: Rôle | D10: Statut retenu
B11: Cahier des charges v0 approuvé (54 p., 25/06/2026) | C11: Spécification technique et juridique, ancrée AUSCGIE / AUDCG / AUPCAP, vendeurs locaux réels | D11: Autorité principale
B12: Référentiel de processus P04 à P25 (50 p., v1.0, contractuel CCI-Togo) | C12: 22 processus opposables, RACI, contrôles, indicateurs ; dérive directement du v0 | D12: Autorité opérationnelle
B13: Note investisseurs et partenaires (28 p., 26/06/2026) | C13: Thèse, marché, monétisation, feuille de route | D13: Contexte stratégique
B14: Services Blueprint v5.0 | C14: Vision générique (escrow, valorisation automatique, KYC biométrique, hub courtiers) non retrouvée dans le v0 ni le référentiel | D14: Non retenu
B15: Master Developer Handoff V3.1 (12 cas, 24 scénarios, 6 Skills) | C15: Corpus de référence exécutable : maquettes et fixtures servant d'oracle de test, pas de code de production | D15: Socle de conception à porter en production
B17: 3. Socle réglementaire qui gouverne tout le reste
B18: Bifurcation des types de cession : chaque dossier est typé dès l'origine ASSET_DEAL (fonds de commerce, librement commercialisable) ou SHARE_DEAL (titres, cercle fermé obligatoire). La forme juridique de la cible est vérifiée au RCCM.
B19: Regulatory Perimeter Service (RPS) : service indépendant qui applique trois paliers de divulgation. T0 : existence (secteur, région, taille). T1 : teaser anonymisé, jamais de prix ni d'identité. T2 : identité, prix et data room, uniquement après NDA. Compteur de divulgation par personne, plafond de cercle (défaut 50), filtre de communication, journal append-only haché. L'admission n'est jamais automatique.
B20: Dix portes de conformité (G1 à G10) doivent être fermées avant tout lancement commercial : déclaration IPDCP, transfert transfrontalier, prestataire de signature qualifié, revues juridiques, avis écrit sur le RPS, audit du texte d'interface, recalcul de la rétrocession, DPO nommé, pentest indépendant.
B21: 4. Pipeline transactionnel
B22: Compte vérifié > Qualifié > Admis (RPS) > NDA signé > T2 autorisé > Data room et Q&R > LOI et audit d'acquisition > Réalisation documentée. Chaque état est un sur-ensemble strict du précédent ; aucune étape ne peut être sautée sans règle documentée.
B23: 5. Intégrations réelles retenues par le v0
B24: Besoin | C24: Vendeurs retenus | D24: Note
B25: Mobile money | C25: CinetPay, PayDunya, Hub2, PayGate Global, Gozem Pay | D25: Rails réels : T-Money, Flooz, Gozem Money ; pas de carte bancaire par défaut
B26: Signature électronique | C26: Prestataire togolais accrédité ARCEP (PSC) | D26: Présomption légale de fiabilité, critère décisif
B27: Vérification d'identité | C27: Capture documentaire, revue humaine, OTP | D27: Aucune biométrie en v0
B28: Registre des entreprises | C28: CFE / RCCM | D28: Si aucune API : échange de fichier supervisé
B29: Archivage de preuve | C29: PSAE accrédité | D29: Valeur probante du NDA
B30: Événements et rendez-vous virtuels | C30: Remo.co | D30: Connecteur externe pour Deal-Connect et Guichet Diaspora
B31: Fiscalité | C31: Partenaire tiers à confirmer | D31: Le nom TaxeFacile n'apparaît que dans le blueprint v5
B33: 6. Exigences transverses
B34: Domaine | C34: Exigence
B35: Disponibilité | C35: 99,5 % mensuel, obligation de résultat contractuelle ; RPO 1 h, RTO 4 h ; priorités P1 à P4 avec délais
B36: Capacité pilote | C36: 2 000 comptes, 300 sessions concurrentes, 200 deals actifs, 20 000 documents ; test de charge à 2x ; ne pas sur-construire
B37: Sécurité | C37: TLS 1.3, AES-256, chiffrement applicatif des champs CONFIDENTIAL_DEAL, séparation VDR / marketplace, idempotence des webhooks, pentest
B38: Localisation | C38: Français langue source, formats FCFA sans décimale, termes OHADA jamais traduits, dates DD/MM/YYYY
B39: Ingénierie | C39: Monorepo apps/ et packages/, RPS déployé séparément, REST /v1, UUIDv7, montants en entier XOF, pagination par curseur
B41: 7. Hors périmètre v0 (à ne pas construire maintenant)
B42: Élément | C42: Statut | D42: Raison
B43: Deal-Pay et séquestre (escrow) | C43: Hors périmètre v0 | D43: Frontière d'intégration partenaire licencié désactivée ; avenant requis
B44: Valorisation algorithmique automatique | C44: Hors périmètre v0 | D44: Le v0 interdit toute fourchette présentée comme un avis DealPME
B45: Certification automatique / score de readiness | C45: Hors périmètre v0 | D45: Décision nominative CCI-Togo obligatoire
B46: KYC biométrique | C46: Différé (P2) | D46: Activable après autorisation IPDCP, sous drapeau fonctionnel
B47: Broker Agency Hub multi-tenant | C47: Hors périmètre v0 | D47: Pas de compte maître de cabinet M&A dans le v0
B48: Marques globales génériques (Stripe, DocuSign, SumSub, Ecobank) | C48: Hors périmètre v0 | D48: Remplacées par des vendeurs locaux réels
B50: 8. Décisions actées
B51: - Le cahier des charges v0 et le Référentiel P04 à P25 sont la cible finale ; le blueprint v5 n'est pas retenu.
B52: - Remo.co est retenu comme connecteur externe pour les salons et rendez-vous virtuels ; intégration dès V1, billetterie et sponsoring en V4.
B53: - V1 inclut une démonstration maquettée du blocage RPS (+20 j/p) ; le circuit réel reste en V2.

Sheet Feuille_de_route
B2: Feuille de route V1 à V5
B3: Détail de chaque version. Les charges et avancements par lot sont calculés depuis l'onglet Taches.
B5: V1 Premier produit : cessions d'actifs, espace CCI-Togo, Deal-Ready, démonstration du blocage RPS, Deal-Connect via Remo.co
B6: Début prévu | C6: Fin prévue | D6: Charge (j/p) | E6: Charge (sem.-pers.) | F6: Avancement | G6: État | H6: Semaines calendaires | I6: ETP requis à pleine cadence
B7: =Versions!D6 | C7: =Versions!E6 | D7: =Versions!G6 | E7: =Versions!H6 | F7: =Versions!J6 | G7: =Versions!P6 | H7: =ROUND((Versions!E6-Versions!D6)/7,1) | I7: =IFERROR(ROUND(Versions!H6/((Versions!E6-Versions!D6)/7),1),0)
B8: Premier produit de démonstration, à données synthétiques, pour faire comprendre le fonctionnement de DealPME. Cessions d'actifs uniquement, plus une démonstration maquettée du blocage RPS. La CCI-Togo confirme l'adhésion et décide seule de la certification.
B9: Inclus | F9: Exclu ou reporté
B10: + Authentification et rôles : cédant, investisseur, agent CCI-Togo, administrateur | F10: - Circuit RPS réel : admission humaine, compteur, plafond, journal réglementaire (V2)
B11: + Espace CCI-Togo : confirmation d'adhésion, vérification RCCM/CFE, décision de certification nominative | F11: - Data room chiffrée, filigranée, révocable et Q&R (V2)
B12: + Pass Transmission : constitution du dossier cédant | F12: - Moteur d'honoraires et rétrocession CCI (V3)
B13: + Marketplace de cessions d'actifs : recherche et mise en relation simple | F13: - Alerte & Rebond, billetterie et sponsoring Deal-Connect, rendez-vous mutuels, rapport post-événement, profil diaspora complet (V4)
B14: + Évaluation financière sommaire et indicative
B15: + Badge Deal-Ready affiché, workflow porté par la CCI-Togo
B16: + Démonstration maquettée du blocage RPS (bannière de nullité, scénario scripté)
B17: + Deal-Connect via Remo.co : événements, inscriptions avec consentement, lien d'accès unique, présence par webhook
B18: + Guichet Diaspora léger : demande de rendez-vous avec avis transfrontalier, entretien vidéo Remo après confirmation humaine
B19: + Lot Sécurité : RLS effective, anti-force-brute, MFA officiers et administrateurs, chiffrement applicatif, en-têtes, idempotence et signatures de webhooks, revue interne
B21: Lot | C21: Charge (j/p) | D21: Réalisé (j/p) | E21: Avancement | F21: Tâches | G21: Complétées | H21: Bloquées | I21: En retard
B22: Fondations | C22: =SUMIFS(Taches!$M$6:$M$325,Taches!$C$6:$C$325,"V1",Taches!$E$6:$E$325,$B22) | D22: =SUMIFS(Taches!$N$6:$N$325,Taches!$C$6:$C$325,"V1",Taches!$E$6:$E$325,$B22) | E22: =IF(C22=0,0,D22/C22) | F22: =COUNTIFS(Taches!$C$6:$C$325,"V1",Taches!$E$6:$E$325,$B22,Taches!$J$6:$J$325,"<>Abandonnée",Taches!$B$6:$B$325,"<>") | G22: =COUNTIFS(Taches!$C$6:$C$325,"V1",Taches!$E$6:$E$325,$B22,Taches!$J$6:$J$325,"Complétée") | H22: =COUNTIFS(Taches!$C$6:$C$325,"V1",Taches!$E$6:$E$325,$B22,Taches!$J$6:$J$325,"Bloquée") | I22: =COUNTIFS(Taches!$C$6:$C$325,"V1",Taches!$E$6:$E$325,$B22,Taches!$U$6:$U$325,"En retard")
B23: Auth et rôles | C23: =SUMIFS(Taches!$M$6:$M$325,Taches!$C$6:$C$325,"V1",Taches!$E$6:$E$325,$B23) | D23: =SUMIFS(Taches!$N$6:$N$325,Taches!$C$6:$C$325,"V1",Taches!$E$6:$E$325,$B23) | E23: =IF(C23=0,0,D23/C23) | F23: =COUNTIFS(Taches!$C$6:$C$325,"V1",Taches!$E$6:$E$325,$B23,Taches!$J$6:$J$325,"<>Abandonnée",Taches!$B$6:$B$325,"<>") | G23: =COUNTIFS(Taches!$C$6:$C$325,"V1",Taches!$E$6:$E$325,$B23,Taches!$J$6:$J$325,"Complétée") | H23: =COUNTIFS(Taches!$C$6:$C$325,"V1",Taches!$E$6:$E$325,$B23,Taches!$J$6:$J$325,"Bloquée") | I23: =COUNTIFS(Taches!$C$6:$C$325,"V1",Taches!$E$6:$E$325,$B23,Taches!$U$6:$U$325,"En retard")
B24: Espace CCI-Togo | C24: =SUMIFS(Taches!$M$6:$M$325,Taches!$C$6:$C$325,"V1",Taches!$E$6:$E$325,$B24) | D24: =SUMIFS(Taches!$N$6:$N$325,Taches!$C$6:$C$325,"V1",Taches!$E$6:$E$325,$B24) | E24: =IF(C24=0,0,D24/C24) | F24: =COUNTIFS(Taches!$C$6:$C$325,"V1",Taches!$E$6:$E$325,$B24,Taches!$J$6:$J$325,"<>Abandonnée",Taches!$B$6:$B$325,"<>") | G24: =COUNTIFS(Taches!$C$6:$C$325,"V1",Taches!$E$6:$E$325,$B24,Taches!$J$6:$J$325,"Complétée") | H24: =COUNTIFS(Taches!$C$6:$C$325,"V1",Taches!$E$6:$E$325,$B24,Taches!$J$6:$J$325,"Bloquée") | I24: =COUNTIFS(Taches!$C$6:$C$325,"V1",Taches!$E$6:$E$325,$B24,Taches!$U$6:$U$325,"En retard")
B25: Deal-Ready | C25: =SUMIFS(Taches!$M$6:$M$325,Taches!$C$6:$C$325,"V1",Taches!$E$6:$E$325,$B25) | D25: =SUMIFS(Taches!$N$6:$N$325,Taches!$C$6:$C$325,"V1",Taches!$E$6:$E$325,$B25) | E25: =IF(C25=0,0,D25/C25) | F25: =COUNTIFS(Taches!$C$6:$C$325,"V1",Taches!$E$6:$E$325,$B25,Taches!$J$6:$J$325,"<>Abandonnée",Taches!$B$6:$B$325,"<>") | G25: =COUNTIFS(Taches!$C$6:$C$325,"V1",Taches!$E$6:$E$325,$B25,Taches!$J$6:$J$325,"Complétée") | H25: =COUNTIFS(Taches!$C$6:$C$325,"V1",Taches!$E$6:$E$325,$B25,Taches!$J$6:$J$325,"Bloquée") | I25: =COUNTIFS(Taches!$C$6:$C$325,"V1",Taches!$E$6:$E$325,$B25,Taches!$U$6:$U$325,"En retard")
B26: Dossier cédant | C26: =SUMIFS(Taches!$M$6:$M$325,Taches!$C$6:$C$325,"V1",Taches!$E$6:$E$325,$B26) | D26: =SUMIFS(Taches!$N$6:$N$325,Taches!$C$6:$C$325,"V1",Taches!$E$6:$E$325,$B26) | E26: =IF(C26=0,0,D26/C26) | F26: =COUNTIFS(Taches!$C$6:$C$325,"V1",Taches!$E$6:$E$325,$B26,Taches!$J$6:$J$325,"<>Abandonnée",Taches!$B$6:$B$325,"<>") | G26: =COUNTIFS(Taches!$C$6:$C$325,"V1",Taches!$E$6:$E$325,$B26,Taches!$J$6:$J$325,"Complétée") | H26: =COUNTIFS(Taches!$C$6:$C$325,"V1",Taches!$E$6:$E$325,$B26,Taches!$J$6:$J$325,"Bloquée") | I26: =COUNTIFS(Taches!$C$6:$C$325,"V1",Taches!$E$6:$E$325,$B26,Taches!$U$6:$U$325,"En retard")
B27: Marketplace actifs | C27: =SUMIFS(Taches!$M$6:$M$325,Taches!$C$6:$C$325,"V1",Taches!$E$6:$E$325,$B27) | D27: =SUMIFS(Taches!$N$6:$N$325,Taches!$C$6:$C$325,"V1",Taches!$E$6:$E$325,$B27) | E27: =IF(C27=0,0,D27/C27) | F27: =COUNTIFS(Taches!$C$6:$C$325,"V1",Taches!$E$6:$E$325,$B27,Taches!$J$6:$J$325,"<>Abandonnée",Taches!$B$6:$B$325,"<>") | G27: =COUNTIFS(Taches!$C$6:$C$325,"V1",Taches!$E$6:$E$325,$B27,Taches!$J$6:$J$325,"Complétée") | H27: =COUNTIFS(Taches!$C$6:$C$325,"V1",Taches!$E$6:$E$325,$B27,Taches!$J$6:$J$325,"Bloquée") | I27: =COUNTIFS(Taches!$C$6:$C$325,"V1",Taches!$E$6:$E$325,$B27,Taches!$U$6:$U$325,"En retard")
B28: Évaluation indicative | C28: =SUMIFS(Taches!$M$6:$M$325,Taches!$C$6:$C$325,"V1",Taches!$E$6:$E$325,$B28) | D28: =SUMIFS(Taches!$N$6:$N$325,Taches!$C$6:$C$325,"V1",Taches!$E$6:$E$325,$B28) | E28: =IF(C28=0,0,D28/C28) | F28: =COUNTIFS(Taches!$C$6:$C$325,"V1",Taches!$E$6:$E$325,$B28,Taches!$J$6:$J$325,"<>Abandonnée",Taches!$B$6:$B$325,"<>") | G28: =COUNTIFS(Taches!$C$6:$C$325,"V1",Taches!$E$6:$E$325,$B28,Taches!$J$6:$J$325,"Complétée") | H28: =COUNTIFS(Taches!$C$6:$C$325,"V1",Taches!$E$6:$E$325,$B28,Taches!$J$6:$J$325,"Bloquée") | I28: =COUNTIFS(Taches!$C$6:$C$325,"V1",Taches!$E$6:$E$325,$B28,Taches!$U$6:$U$325,"En retard")
B29: Démonstration RPS | C29: =SUMIFS(Taches!$M$6:$M$325,Taches!$C$6:$C$325,"V1",Taches!$E$6:$E$325,$B29) | D29: =SUMIFS(Taches!$N$6:$N$325,Taches!$C$6:$C$325,"V1",Taches!$E$6:$E$325,$B29) | E29: =IF(C29=0,0,D29/C29) | F29: =COUNTIFS(Taches!$C$6:$C$325,"V1",Taches!$E$6:$E$325,$B29,Taches!$J$6:$J$325,"<>Abandonnée",Taches!$B$6:$B$325,"<>") | G29: =COUNTIFS(Taches!$C$6:$C$325,"V1",Taches!$E$6:$E$325,$B29,Taches!$J$6:$J$325,"Complétée") | H29: =COUNTIFS(Taches!$C$6:$C$325,"V1",Taches!$E$6:$E$325,$B29,Taches!$J$6:$J$325,"Bloquée") | I29: =COUNTIFS(Taches!$C$6:$C$325,"V1",Taches!$E$6:$E$325,$B29,Taches!$U$6:$U$325,"En retard")
B30: Deal-Connect (Remo) | C30: =SUMIFS(Taches!$M$6:$M$325,Taches!$C$6:$C$325,"V1",Taches!$E$6:$E$325,$B30) | D30: =SUMIFS(Taches!$N$6:$N$325,Taches!$C$6:$C$325,"V1",Taches!$E$6:$E$325,$B30) | E30: =IF(C30=0,0,D30/C30) | F30: =COUNTIFS(Taches!$C$6:$C$325,"V1",Taches!$E$6:$E$325,$B30,Taches!$J$6:$J$325,"<>Abandonnée",Taches!$B$6:$B$325,"<>") | G30: =COUNTIFS(Taches!$C$6:$C$325,"V1",Taches!$E$6:$E$325,$B30,Taches!$J$6:$J$325,"Complétée") | H30: =COUNTIFS(Taches!$C$6:$C$325,"V1",Taches!$E$6:$E$325,$B30,Taches!$J$6:$J$325,"Bloquée") | I30: =COUNTIFS(Taches!$C$6:$C$325,"V1",Taches!$E$6:$E$325,$B30,Taches!$U$6:$U$325,"En retard")
B31: Sécurité | C31: =SUMIFS(Taches!$M$6:$M$325,Taches!$C$6:$C$325,"V1",Taches!$E$6:$E$325,$B31) | D31: =SUMIFS(Taches!$N$6:$N$325,Taches!$C$6:$C$325,"V1",Taches!$E$6:$E$325,$B31) | E31: =IF(C31=0,0,D31/C31) | F31: =COUNTIFS(Taches!$C$6:$C$325,"V1",Taches!$E$6:$E$325,$B31,Taches!$J$6:$J$325,"<>Abandonnée",Taches!$B$6:$B$325,"<>") | G31: =COUNTIFS(Taches!$C$6:$C$325,"V1",Taches!$E$6:$E$325,$B31,Taches!$J$6:$J$325,"Complétée") | H31: =COUNTIFS(Taches!$C$6:$C$325,"V1",Taches!$E$6:$E$325,$B31,Taches!$J$6:$J$325,"Bloquée") | I31: =COUNTIFS(Taches!$C$6:$C$325,"V1",Taches!$E$6:$E$325,$B31,Taches!$U$6:$U$325,"En retard")
B32: Frontend et design | C32: =SUMIFS(Taches!$M$6:$M$325,Taches!$C$6:$C$325,"V1",Taches!$E$6:$E$325,$B32) | D32: =SUMIFS(Taches!$N$6:$N$325,Taches!$C$6:$C$325,"V1",Taches!$E$6:$E$325,$B32) | E32: =IF(C32=0,0,D32/C32) | F32: =COUNTIFS(Taches!$C$6:$C$325,"V1",Taches!$E$6:$E$325,$B32,Taches!$J$6:$J$325,"<>Abandonnée",Taches!$B$6:$B$325,"<>") | G32: =COUNTIFS(Taches!$C$6:$C$325,"V1",Taches!$E$6:$E$325,$B32,Taches!$J$6:$J$325,"Complétée") | H32: =COUNTIFS(Taches!$C$6:$C$325,"V1",Taches!$E$6:$E$325,$B32,Taches!$J$6:$J$325,"Bloquée") | I32: =COUNTIFS(Taches!$C$6:$C$325,"V1",Taches!$E$6:$E$325,$B32,Taches!$U$6:$U$325,"En retard")
B33: QA et livraison | C33: =SUMIFS(Taches!$M$6:$M$325,Taches!$C$6:$C$325,"V1",Taches!$E$6:$E$325,$B33) | D33: =SUMIFS(Taches!$N$6:$N$325,Taches!$C$6:$C$325,"V1",Taches!$E$6:$E$325,$B33) | E33: =IF(C33=0,0,D33/C33) | F33: =COUNTIFS(Taches!$C$6:$C$325,"V1",Taches!$E$6:$E$325,$B33,Taches!$J$6:$J$325,"<>Abandonnée",Taches!$B$6:$B$325,"<>") | G33: =COUNTIFS(Taches!$C$6:$C$325,"V1",Taches!$E$6:$E$325,$B33,Taches!$J$6:$J$325,"Complétée") | H33: =COUNTIFS(Taches!$C$6:$C$325,"V1",Taches!$E$6:$E$325,$B33,Taches!$J$6:$J$325,"Bloquée") | I33: =COUNTIFS(Taches!$C$6:$C$325,"V1",Taches!$E$6:$E$325,$B33,Taches!$U$6:$U$325,"En retard")
B34: Total V1 | C34: =SUM(C22:C33) | D34: =SUM(D22:D33) | E34: =IF(C34=0,0,D34/C34) | F34: =SUM(F22:F33) | G34: =SUM(G22:G33) | H34: =SUM(H22:H33) | I34: =SUM(I22:I33)
B36: Prérequis
B37: Équipe de développement confirmée (5 à 6 profils) ; réponse sur l'API CFE/RCCM ; designer UI/UX confirmé.
B38: Décision ou règle
B39: La démonstration RPS fait partie de V1. Sans équipe à 5 ou 6 profils, la démonstration RPS est le premier lot à retirer, avant le matching automatisé.
B42: V2 Cession de titres en cercle restreint (RPS réel), signature électronique, data room et Q&R
B43: Début prévu | C43: Fin prévue | D43: Charge (j/p) | E43: Charge (sem.-pers.) | F43: Avancement | G43: État | H43: Semaines calendaires | I43: ETP requis à pleine cadence
B44: =Versions!D7 | C44: =Versions!E7 | D44: =Versions!G7 | E44: =Versions!H7 | F44: =Versions!J7 | G44: =Versions!P7 | H44: =ROUND((Versions!E7-Versions!D7)/7,1) | I44: =IFERROR(ROUND(Versions!H7/((Versions!E7-Versions!D7)/7),1),0)
B45: Le cœur du différenciateur produit : le moteur RPS complet pour les cessions de titres et la data room. Prérequis à toute diligence réelle.
B46: Inclus | F46: Exclu ou reporté
B47: + Circuit RPS complet : admission humaine, plafond de cercle (défaut 50), journal réglementaire haché | F47: - Négociation, LOI, audit d'acquisition et réalisation (V3)
B48: + Signature électronique et preuve : prestataire PSC togolais, repli papier, archivage PSAE | F48: - Génération documentaire LegalTech (V3)
B49: + Data room : arborescence OHADA, rendu serveur, filigrane dynamique, téléchargement contrôlé, révocation en moins de 60 s
B50: + Fils de questions-réponses par document
B52: Lot | C52: Charge (j/p) | D52: Réalisé (j/p) | E52: Avancement | F52: Tâches | G52: Complétées | H52: Bloquées | I52: En retard
B53: Circuit RPS réel | C53: =SUMIFS(Taches!$M$6:$M$325,Taches!$C$6:$C$325,"V2",Taches!$E$6:$E$325,$B53) | D53: =SUMIFS(Taches!$N$6:$N$325,Taches!$C$6:$C$325,"V2",Taches!$E$6:$E$325,$B53) | E53: =IF(C53=0,0,D53/C53) | F53: =COUNTIFS(Taches!$C$6:$C$325,"V2",Taches!$E$6:$E$325,$B53,Taches!$J$6:$J$325,"<>Abandonnée",Taches!$B$6:$B$325,"<>") | G53: =COUNTIFS(Taches!$C$6:$C$325,"V2",Taches!$E$6:$E$325,$B53,Taches!$J$6:$J$325,"Complétée") | H53: =COUNTIFS(Taches!$C$6:$C$325,"V2",Taches!$E$6:$E$325,$B53,Taches!$J$6:$J$325,"Bloquée") | I53: =COUNTIFS(Taches!$C$6:$C$325,"V2",Taches!$E$6:$E$325,$B53,Taches!$U$6:$U$325,"En retard")
B54: Signature électronique | C54: =SUMIFS(Taches!$M$6:$M$325,Taches!$C$6:$C$325,"V2",Taches!$E$6:$E$325,$B54) | D54: =SUMIFS(Taches!$N$6:$N$325,Taches!$C$6:$C$325,"V2",Taches!$E$6:$E$325,$B54) | E54: =IF(C54=0,0,D54/C54) | F54: =COUNTIFS(Taches!$C$6:$C$325,"V2",Taches!$E$6:$E$325,$B54,Taches!$J$6:$J$325,"<>Abandonnée",Taches!$B$6:$B$325,"<>") | G54: =COUNTIFS(Taches!$C$6:$C$325,"V2",Taches!$E$6:$E$325,$B54,Taches!$J$6:$J$325,"Complétée") | H54: =COUNTIFS(Taches!$C$6:$C$325,"V2",Taches!$E$6:$E$325,$B54,Taches!$J$6:$J$325,"Bloquée") | I54: =COUNTIFS(Taches!$C$6:$C$325,"V2",Taches!$E$6:$E$325,$B54,Taches!$U$6:$U$325,"En retard")
B55: Data room | C55: =SUMIFS(Taches!$M$6:$M$325,Taches!$C$6:$C$325,"V2",Taches!$E$6:$E$325,$B55) | D55: =SUMIFS(Taches!$N$6:$N$325,Taches!$C$6:$C$325,"V2",Taches!$E$6:$E$325,$B55) | E55: =IF(C55=0,0,D55/C55) | F55: =COUNTIFS(Taches!$C$6:$C$325,"V2",Taches!$E$6:$E$325,$B55,Taches!$J$6:$J$325,"<>Abandonnée",Taches!$B$6:$B$325,"<>") | G55: =COUNTIFS(Taches!$C$6:$C$325,"V2",Taches!$E$6:$E$325,$B55,Taches!$J$6:$J$325,"Complétée") | H55: =COUNTIFS(Taches!$C$6:$C$325,"V2",Taches!$E$6:$E$325,$B55,Taches!$J$6:$J$325,"Bloquée") | I55: =COUNTIFS(Taches!$C$6:$C$325,"V2",Taches!$E$6:$E$325,$B55,Taches!$U$6:$U$325,"En retard")
B56: Questions-réponses | C56: =SUMIFS(Taches!$M$6:$M$325,Taches!$C$6:$C$325,"V2",Taches!$E$6:$E$325,$B56) | D56: =SUMIFS(Taches!$N$6:$N$325,Taches!$C$6:$C$325,"V2",Taches!$E$6:$E$325,$B56) | E56: =IF(C56=0,0,D56/C56) | F56: =COUNTIFS(Taches!$C$6:$C$325,"V2",Taches!$E$6:$E$325,$B56,Taches!$J$6:$J$325,"<>Abandonnée",Taches!$B$6:$B$325,"<>") | G56: =COUNTIFS(Taches!$C$6:$C$325,"V2",Taches!$E$6:$E$325,$B56,Taches!$J$6:$J$325,"Complétée") | H56: =COUNTIFS(Taches!$C$6:$C$325,"V2",Taches!$E$6:$E$325,$B56,Taches!$J$6:$J$325,"Bloquée") | I56: =COUNTIFS(Taches!$C$6:$C$325,"V2",Taches!$E$6:$E$325,$B56,Taches!$U$6:$U$325,"En retard")
B57: QA et sécurité | C57: =SUMIFS(Taches!$M$6:$M$325,Taches!$C$6:$C$325,"V2",Taches!$E$6:$E$325,$B57) | D57: =SUMIFS(Taches!$N$6:$N$325,Taches!$C$6:$C$325,"V2",Taches!$E$6:$E$325,$B57) | E57: =IF(C57=0,0,D57/C57) | F57: =COUNTIFS(Taches!$C$6:$C$325,"V2",Taches!$E$6:$E$325,$B57,Taches!$J$6:$J$325,"<>Abandonnée",Taches!$B$6:$B$325,"<>") | G57: =COUNTIFS(Taches!$C$6:$C$325,"V2",Taches!$E$6:$E$325,$B57,Taches!$J$6:$J$325,"Complétée") | H57: =COUNTIFS(Taches!$C$6:$C$325,"V2",Taches!$E$6:$E$325,$B57,Taches!$J$6:$J$325,"Bloquée") | I57: =COUNTIFS(Taches!$C$6:$C$325,"V2",Taches!$E$6:$E$325,$B57,Taches!$U$6:$U$325,"En retard")
B58: Total V2 | C58: =SUM(C53:C57) | D58: =SUM(D53:D57) | E58: =IF(C58=0,0,D58/C58) | F58: =SUM(F53:F57) | G58: =SUM(G53:G57) | H58: =SUM(H53:H57) | I58: =SUM(I53:I57)
B60: Prérequis
B61: Modèle de données Deal et Organisation de V1 ; contrat avec le prestataire de signature qualifiée.
B64: V3 Négociation et réalisation, LegalTech OHADA, Finance et rétrocession, support, fermeture des portes de conformité
B65: Début prévu | C65: Fin prévue | D65: Charge (j/p) | E65: Charge (sem.-pers.) | F65: Avancement | G65: État | H65: Semaines calendaires | I65: ETP requis à pleine cadence
B66: =Versions!D8 | C66: =Versions!E8 | D66: =Versions!G8 | E66: =Versions!H8 | F66: =Versions!J8 | G66: =Versions!P8 | H66: =ROUND((Versions!E8-Versions!D8)/7,1) | I66: =IFERROR(ROUND(Versions!H8/((Versions!E8-Versions!D8)/7),1),0)
B67: Ce qui rend une transaction réelle facturable et légalement défendable : négociation et réalisation, LegalTech OHADA, moteur de frais et rétrocession, support, fermeture des dix portes de conformité et durcissement de l'exploitation.
B68: Inclus | F68: Exclu ou reporté
B69: + Offre, contre-offre, LOI et registre des points ouverts d'audit d'acquisition | F69: - Deal-Experts (V4, sous réserve d'arbitrage)
B70: + Réalisation documentée sans Deal-Pay natif, création automatique du FeeEvent | F70: - Modules réseau : Alerte & Rebond, Deal-Connect, Guichet Diaspora (V4)
B71: + LegalTech OHADA : NDA, LOI, pacte simplifié, SPA, cession d'actifs, contrat de travail (droit togolais)
B72: + Finance : barème de frais sous drapeau juridique, rétrocession CCI, journal de calcul recalculable, rapport trimestriel
B73: + Support et accès privilégiés, mode break-glass journalisé
B74: + Portes de conformité G1 à G10 : IPDCP, revues juridiques, DPO, pentest indépendant
B75: + Exploitation : supervision SLA 99,5 %, sauvegardes testées, procédure d'incident
B77: Lot | C77: Charge (j/p) | D77: Réalisé (j/p) | E77: Avancement | F77: Tâches | G77: Complétées | H77: Bloquées | I77: En retard
B78: LegalTech OHADA | C78: =SUMIFS(Taches!$M$6:$M$325,Taches!$C$6:$C$325,"V3",Taches!$E$6:$E$325,$B78) | D78: =SUMIFS(Taches!$N$6:$N$325,Taches!$C$6:$C$325,"V3",Taches!$E$6:$E$325,$B78) | E78: =IF(C78=0,0,D78/C78) | F78: =COUNTIFS(Taches!$C$6:$C$325,"V3",Taches!$E$6:$E$325,$B78,Taches!$J$6:$J$325,"<>Abandonnée",Taches!$B$6:$B$325,"<>") | G78: =COUNTIFS(Taches!$C$6:$C$325,"V3",Taches!$E$6:$E$325,$B78,Taches!$J$6:$J$325,"Complétée") | H78: =COUNTIFS(Taches!$C$6:$C$325,"V3",Taches!$E$6:$E$325,$B78,Taches!$J$6:$J$325,"Bloquée") | I78: =COUNTIFS(Taches!$C$6:$C$325,"V3",Taches!$E$6:$E$325,$B78,Taches!$U$6:$U$325,"En retard")
B79: Conformité fiscale | C79: =SUMIFS(Taches!$M$6:$M$325,Taches!$C$6:$C$325,"V3",Taches!$E$6:$E$325,$B79) | D79: =SUMIFS(Taches!$N$6:$N$325,Taches!$C$6:$C$325,"V3",Taches!$E$6:$E$325,$B79) | E79: =IF(C79=0,0,D79/C79) | F79: =COUNTIFS(Taches!$C$6:$C$325,"V3",Taches!$E$6:$E$325,$B79,Taches!$J$6:$J$325,"<>Abandonnée",Taches!$B$6:$B$325,"<>") | G79: =COUNTIFS(Taches!$C$6:$C$325,"V3",Taches!$E$6:$E$325,$B79,Taches!$J$6:$J$325,"Complétée") | H79: =COUNTIFS(Taches!$C$6:$C$325,"V3",Taches!$E$6:$E$325,$B79,Taches!$J$6:$J$325,"Bloquée") | I79: =COUNTIFS(Taches!$C$6:$C$325,"V3",Taches!$E$6:$E$325,$B79,Taches!$U$6:$U$325,"En retard")
B80: Négociation | C80: =SUMIFS(Taches!$M$6:$M$325,Taches!$C$6:$C$325,"V3",Taches!$E$6:$E$325,$B80) | D80: =SUMIFS(Taches!$N$6:$N$325,Taches!$C$6:$C$325,"V3",Taches!$E$6:$E$325,$B80) | E80: =IF(C80=0,0,D80/C80) | F80: =COUNTIFS(Taches!$C$6:$C$325,"V3",Taches!$E$6:$E$325,$B80,Taches!$J$6:$J$325,"<>Abandonnée",Taches!$B$6:$B$325,"<>") | G80: =COUNTIFS(Taches!$C$6:$C$325,"V3",Taches!$E$6:$E$325,$B80,Taches!$J$6:$J$325,"Complétée") | H80: =COUNTIFS(Taches!$C$6:$C$325,"V3",Taches!$E$6:$E$325,$B80,Taches!$J$6:$J$325,"Bloquée") | I80: =COUNTIFS(Taches!$C$6:$C$325,"V3",Taches!$E$6:$E$325,$B80,Taches!$U$6:$U$325,"En retard")
B81: Audit d'acquisition | C81: =SUMIFS(Taches!$M$6:$M$325,Taches!$C$6:$C$325,"V3",Taches!$E$6:$E$325,$B81) | D81: =SUMIFS(Taches!$N$6:$N$325,Taches!$C$6:$C$325,"V3",Taches!$E$6:$E$325,$B81) | E81: =IF(C81=0,0,D81/C81) | F81: =COUNTIFS(Taches!$C$6:$C$325,"V3",Taches!$E$6:$E$325,$B81,Taches!$J$6:$J$325,"<>Abandonnée",Taches!$B$6:$B$325,"<>") | G81: =COUNTIFS(Taches!$C$6:$C$325,"V3",Taches!$E$6:$E$325,$B81,Taches!$J$6:$J$325,"Complétée") | H81: =COUNTIFS(Taches!$C$6:$C$325,"V3",Taches!$E$6:$E$325,$B81,Taches!$J$6:$J$325,"Bloquée") | I81: =COUNTIFS(Taches!$C$6:$C$325,"V3",Taches!$E$6:$E$325,$B81,Taches!$U$6:$U$325,"En retard")
B82: Réalisation | C82: =SUMIFS(Taches!$M$6:$M$325,Taches!$C$6:$C$325,"V3",Taches!$E$6:$E$325,$B82) | D82: =SUMIFS(Taches!$N$6:$N$325,Taches!$C$6:$C$325,"V3",Taches!$E$6:$E$325,$B82) | E82: =IF(C82=0,0,D82/C82) | F82: =COUNTIFS(Taches!$C$6:$C$325,"V3",Taches!$E$6:$E$325,$B82,Taches!$J$6:$J$325,"<>Abandonnée",Taches!$B$6:$B$325,"<>") | G82: =COUNTIFS(Taches!$C$6:$C$325,"V3",Taches!$E$6:$E$325,$B82,Taches!$J$6:$J$325,"Complétée") | H82: =COUNTIFS(Taches!$C$6:$C$325,"V3",Taches!$E$6:$E$325,$B82,Taches!$J$6:$J$325,"Bloquée") | I82: =COUNTIFS(Taches!$C$6:$C$325,"V3",Taches!$E$6:$E$325,$B82,Taches!$U$6:$U$325,"En retard")
B83: Finance | C83: =SUMIFS(Taches!$M$6:$M$325,Taches!$C$6:$C$325,"V3",Taches!$E$6:$E$325,$B83) | D83: =SUMIFS(Taches!$N$6:$N$325,Taches!$C$6:$C$325,"V3",Taches!$E$6:$E$325,$B83) | E83: =IF(C83=0,0,D83/C83) | F83: =COUNTIFS(Taches!$C$6:$C$325,"V3",Taches!$E$6:$E$325,$B83,Taches!$J$6:$J$325,"<>Abandonnée",Taches!$B$6:$B$325,"<>") | G83: =COUNTIFS(Taches!$C$6:$C$325,"V3",Taches!$E$6:$E$325,$B83,Taches!$J$6:$J$325,"Complétée") | H83: =COUNTIFS(Taches!$C$6:$C$325,"V3",Taches!$E$6:$E$325,$B83,Taches!$J$6:$J$325,"Bloquée") | I83: =COUNTIFS(Taches!$C$6:$C$325,"V3",Taches!$E$6:$E$325,$B83,Taches!$U$6:$U$325,"En retard")
B84: Support | C84: =SUMIFS(Taches!$M$6:$M$325,Taches!$C$6:$C$325,"V3",Taches!$E$6:$E$325,$B84) | D84: =SUMIFS(Taches!$N$6:$N$325,Taches!$C$6:$C$325,"V3",Taches!$E$6:$E$325,$B84) | E84: =IF(C84=0,0,D84/C84) | F84: =COUNTIFS(Taches!$C$6:$C$325,"V3",Taches!$E$6:$E$325,$B84,Taches!$J$6:$J$325,"<>Abandonnée",Taches!$B$6:$B$325,"<>") | G84: =COUNTIFS(Taches!$C$6:$C$325,"V3",Taches!$E$6:$E$325,$B84,Taches!$J$6:$J$325,"Complétée") | H84: =COUNTIFS(Taches!$C$6:$C$325,"V3",Taches!$E$6:$E$325,$B84,Taches!$J$6:$J$325,"Bloquée") | I84: =COUNTIFS(Taches!$C$6:$C$325,"V3",Taches!$E$6:$E$325,$B84,Taches!$U$6:$U$325,"En retard")
B85: Portes de conformité | C85: =SUMIFS(Taches!$M$6:$M$325,Taches!$C$6:$C$325,"V3",Taches!$E$6:$E$325,$B85) | D85: =SUMIFS(Taches!$N$6:$N$325,Taches!$C$6:$C$325,"V3",Taches!$E$6:$E$325,$B85) | E85: =IF(C85=0,0,D85/C85) | F85: =COUNTIFS(Taches!$C$6:$C$325,"V3",Taches!$E$6:$E$325,$B85,Taches!$J$6:$J$325,"<>Abandonnée",Taches!$B$6:$B$325,"<>") | G85: =COUNTIFS(Taches!$C$6:$C$325,"V3",Taches!$E$6:$E$325,$B85,Taches!$J$6:$J$325,"Complétée") | H85: =COUNTIFS(Taches!$C$6:$C$325,"V3",Taches!$E$6:$E$325,$B85,Taches!$J$6:$J$325,"Bloquée") | I85: =COUNTIFS(Taches!$C$6:$C$325,"V3",Taches!$E$6:$E$325,$B85,Taches!$U$6:$U$325,"En retard")
B86: Exploitation | C86: =SUMIFS(Taches!$M$6:$M$325,Taches!$C$6:$C$325,"V3",Taches!$E$6:$E$325,$B86) | D86: =SUMIFS(Taches!$N$6:$N$325,Taches!$C$6:$C$325,"V3",Taches!$E$6:$E$325,$B86) | E86: =IF(C86=0,0,D86/C86) | F86: =COUNTIFS(Taches!$C$6:$C$325,"V3",Taches!$E$6:$E$325,$B86,Taches!$J$6:$J$325,"<>Abandonnée",Taches!$B$6:$B$325,"<>") | G86: =COUNTIFS(Taches!$C$6:$C$325,"V3",Taches!$E$6:$E$325,$B86,Taches!$J$6:$J$325,"Complétée") | H86: =COUNTIFS(Taches!$C$6:$C$325,"V3",Taches!$E$6:$E$325,$B86,Taches!$J$6:$J$325,"Bloquée") | I86: =COUNTIFS(Taches!$C$6:$C$325,"V3",Taches!$E$6:$E$325,$B86,Taches!$U$6:$U$325,"En retard")
B87: Total V3 | C87: =SUM(C78:C86) | D87: =SUM(D78:D86) | E87: =IF(C87=0,0,D87/C87) | F87: =SUM(F78:F86) | G87: =SUM(G78:G86) | H87: =SUM(H78:H86) | I87: =SUM(I78:I86)
B89: Prérequis
B90: Des transactions peuvent atteindre CLOSED_REPORTED (V2) ; avis juridique écrit sur le barème de frais.
B91: Décision ou règle
B92: Le barème de frais et la rétrocession ne s'activent qu'après avis juridique écrit, jamais par simple décision produit.
B95: V4 Alerte & Rebond, Deal-Connect (Remo.co), Guichet Diaspora, Deal-Experts
B96: Début prévu | C96: Fin prévue | D96: Charge (j/p) | E96: Charge (sem.-pers.) | F96: Avancement | G96: État | H96: Semaines calendaires | I96: ETP requis à pleine cadence
B97: =Versions!D9 | C97: =Versions!E9 | D97: =Versions!G9 | E97: =Versions!H9 | F97: =Versions!J9 | G97: =Versions!P9 | H97: =ROUND((Versions!E9-Versions!D9)/7,1) | I97: =IFERROR(ROUND(Versions!H9/((Versions!E9-Versions!D9)/7),1),0)
B98: Les modules réseau. Seul changement d'architecture notable : la brique de salons et rendez-vous virtuels est externalisée vers Remo.co plutôt que construite en propre.
B99: Inclus | F99: Exclu ou reporté
B100: + Alerte & Rebond : auto-diagnostic, cellule de crise confidentielle, listings d'actifs en difficulté, coupe-circuit | F100: - Mécanismes d'enchère en temps réel (non présumés contractuels)
B101: + Deal-Connect : événements B2B via connecteur Remo.co ; DealPME gère inscriptions, billetterie, attribution et reporting | F101: - Tout conseil de change ou d'investissement fourni par la plateforme
B102: + Guichet Diaspora : liste de suivi, rendez-vous sécurisé via Remo.co, contraintes transfrontalières, renvoi vers banque et conseil
B103: + Deal-Experts : registre d'experts, routage, accès temporaire scopé (sous réserve de l'arbitrage P13)
B105: Lot | C105: Charge (j/p) | D105: Réalisé (j/p) | E105: Avancement | F105: Tâches | G105: Complétées | H105: Bloquées | I105: En retard
B106: Alerte & Rebond | C106: =SUMIFS(Taches!$M$6:$M$325,Taches!$C$6:$C$325,"V4",Taches!$E$6:$E$325,$B106) | D106: =SUMIFS(Taches!$N$6:$N$325,Taches!$C$6:$C$325,"V4",Taches!$E$6:$E$325,$B106) | E106: =IF(C106=0,0,D106/C106) | F106: =COUNTIFS(Taches!$C$6:$C$325,"V4",Taches!$E$6:$E$325,$B106,Taches!$J$6:$J$325,"<>Abandonnée",Taches!$B$6:$B$325,"<>") | G106: =COUNTIFS(Taches!$C$6:$C$325,"V4",Taches!$E$6:$E$325,$B106,Taches!$J$6:$J$325,"Complétée") | H106: =COUNTIFS(Taches!$C$6:$C$325,"V4",Taches!$E$6:$E$325,$B106,Taches!$J$6:$J$325,"Bloquée") | I106: =COUNTIFS(Taches!$C$6:$C$325,"V4",Taches!$E$6:$E$325,$B106,Taches!$U$6:$U$325,"En retard")
B107: Actifs en difficulté | C107: =SUMIFS(Taches!$M$6:$M$325,Taches!$C$6:$C$325,"V4",Taches!$E$6:$E$325,$B107) | D107: =SUMIFS(Taches!$N$6:$N$325,Taches!$C$6:$C$325,"V4",Taches!$E$6:$E$325,$B107) | E107: =IF(C107=0,0,D107/C107) | F107: =COUNTIFS(Taches!$C$6:$C$325,"V4",Taches!$E$6:$E$325,$B107,Taches!$J$6:$J$325,"<>Abandonnée",Taches!$B$6:$B$325,"<>") | G107: =COUNTIFS(Taches!$C$6:$C$325,"V4",Taches!$E$6:$E$325,$B107,Taches!$J$6:$J$325,"Complétée") | H107: =COUNTIFS(Taches!$C$6:$C$325,"V4",Taches!$E$6:$E$325,$B107,Taches!$J$6:$J$325,"Bloquée") | I107: =COUNTIFS(Taches!$C$6:$C$325,"V4",Taches!$E$6:$E$325,$B107,Taches!$U$6:$U$325,"En retard")
B108: Deal-Connect | C108: =SUMIFS(Taches!$M$6:$M$325,Taches!$C$6:$C$325,"V4",Taches!$E$6:$E$325,$B108) | D108: =SUMIFS(Taches!$N$6:$N$325,Taches!$C$6:$C$325,"V4",Taches!$E$6:$E$325,$B108) | E108: =IF(C108=0,0,D108/C108) | F108: =COUNTIFS(Taches!$C$6:$C$325,"V4",Taches!$E$6:$E$325,$B108,Taches!$J$6:$J$325,"<>Abandonnée",Taches!$B$6:$B$325,"<>") | G108: =COUNTIFS(Taches!$C$6:$C$325,"V4",Taches!$E$6:$E$325,$B108,Taches!$J$6:$J$325,"Complétée") | H108: =COUNTIFS(Taches!$C$6:$C$325,"V4",Taches!$E$6:$E$325,$B108,Taches!$J$6:$J$325,"Bloquée") | I108: =COUNTIFS(Taches!$C$6:$C$325,"V4",Taches!$E$6:$E$325,$B108,Taches!$U$6:$U$325,"En retard")
B109: Guichet Diaspora | C109: =SUMIFS(Taches!$M$6:$M$325,Taches!$C$6:$C$325,"V4",Taches!$E$6:$E$325,$B109) | D109: =SUMIFS(Taches!$N$6:$N$325,Taches!$C$6:$C$325,"V4",Taches!$E$6:$E$325,$B109) | E109: =IF(C109=0,0,D109/C109) | F109: =COUNTIFS(Taches!$C$6:$C$325,"V4",Taches!$E$6:$E$325,$B109,Taches!$J$6:$J$325,"<>Abandonnée",Taches!$B$6:$B$325,"<>") | G109: =COUNTIFS(Taches!$C$6:$C$325,"V4",Taches!$E$6:$E$325,$B109,Taches!$J$6:$J$325,"Complétée") | H109: =COUNTIFS(Taches!$C$6:$C$325,"V4",Taches!$E$6:$E$325,$B109,Taches!$J$6:$J$325,"Bloquée") | I109: =COUNTIFS(Taches!$C$6:$C$325,"V4",Taches!$E$6:$E$325,$B109,Taches!$U$6:$U$325,"En retard")
B110: Deal-Experts | C110: =SUMIFS(Taches!$M$6:$M$325,Taches!$C$6:$C$325,"V4",Taches!$E$6:$E$325,$B110) | D110: =SUMIFS(Taches!$N$6:$N$325,Taches!$C$6:$C$325,"V4",Taches!$E$6:$E$325,$B110) | E110: =IF(C110=0,0,D110/C110) | F110: =COUNTIFS(Taches!$C$6:$C$325,"V4",Taches!$E$6:$E$325,$B110,Taches!$J$6:$J$325,"<>Abandonnée",Taches!$B$6:$B$325,"<>") | G110: =COUNTIFS(Taches!$C$6:$C$325,"V4",Taches!$E$6:$E$325,$B110,Taches!$J$6:$J$325,"Complétée") | H110: =COUNTIFS(Taches!$C$6:$C$325,"V4",Taches!$E$6:$E$325,$B110,Taches!$J$6:$J$325,"Bloquée") | I110: =COUNTIFS(Taches!$C$6:$C$325,"V4",Taches!$E$6:$E$325,$B110,Taches!$U$6:$U$325,"En retard")
B111: Total V4 | C111: =SUM(C106:C110) | D111: =SUM(D106:D110) | E111: =IF(C111=0,0,D111/C111) | F111: =SUM(F106:F110) | G111: =SUM(G106:G110) | H111: =SUM(H106:H110) | I111: =SUM(I106:I110)
B113: Prérequis
B114: Portes de conformité fermées (V3) ; cadrage écrit de l'intégration Remo.co.
B115: Décision ou règle
B116: Remo.co est retenu. Le périmètre exact (SSO natif, webhooks de présence, marque blanche) dépend du plan Remo.co choisi.
...

Sheet Guide
B2: Mode d'emploi du classeur
B5: Principe | C5: L'onglet Taches est la seule source de vérité. Tout le reste (Modules, Versions, Processus, Jalons, Tableau de bord, Gantt) se recalcule automatiquement à partir des tâches.
B6: Mettre à jour une tâche | C6: Changer le Statut (liste déroulante). 'Complétée' = 100 %. Choisir le Responsable dans la liste des personnes inscrites dans l'onglet Equipe. Pour une tâche 'En cours', saisir un pourcentage dans '% saisi' si l'on veut être précis ; sinon 25 % s'applique par défaut (90 % pour 'En revue').
B7: Ajouter une tâche | C7: Écrire sur la première ligne vide de l'onglet Taches en renseignant au minimum ID, Version, Module, Tâche, Charge et Statut. Les formules des colonnes grises sont déjà en place jusqu'à la ligne 325. Le Gantt et tous les totaux la prennent en compte immédiatement.
B8: Abandonner une tâche | C8: Mettre le statut 'Abandonnée' : la tâche sort des totaux de charge sans être supprimée (traçabilité).
B9: Codes couleur | C9: Cellules jaune pâle : à saisir. Cellules grises : calculées, ne pas modifier. Statuts colorés automatiquement (vert complétée, ambre en cours, rouge bloquée).
B10: Modules | C10: Avancement pondéré par la charge des tâches du module. Colonnes Responsable et Commentaire à saisir. Les éléments hors périmètre v0 sont listés pour mémoire, sans tâche.
B11: Versions | C11: Les dates de début et de fin se saisissent ici. L'état passe automatiquement à 'En dépassement' si la date de fin est passée sans 100 %.
B12: Jalons | C12: Saisir la date cible et le statut. La colonne Alerte signale 'Dépassé' ou 'Cette semaine'. Le tableau de bord affiche le prochain jalon non atteint.
B13: Risques | C13: Saisir probabilité et impact de 1 à 5. Le score et le niveau se calculent. Passer le statut à 'Clos' quand le risque est levé.
B14: Securite | C14: Registre des constats de sécurité : chaque ligne renvoie à la tâche qui la traite ; le statut et l'avancement se lisent automatiquement. Un report vers une version ultérieure doit être justifié et accompagné d'une mitigation.
B15: Decisions | C15: Toute demande de changement de périmètre s'inscrit ici avant d'être traduite en tâches. Statut : Ouvert, En discussion, Tranché.
B16: Gantt | C16: Barres hebdomadaires calculées depuis 'Début prévu' et 'Fin prévue' de chaque tâche. Modifier les dates dans Taches, pas dans le Gantt. La colonne de la semaine courante est surlignée.
... B19: Partage | C19: Ce classeur est conçu pour être le point de rencontre de tous les acteurs : les développeurs mettent à jour Taches, la CCI-Togo et M. Bruno lisent le Tableau de bord, les Jalons et les Decisions.

Sheet Taches
B2: Tâches détaillées
B3: Source unique de vérité. Colonnes jaunes : à saisir. Colonnes grises : calculées, ne pas modifier. Filtrer avec les en-têtes.
B5: ID | C5: Version | D5: Module | E5: Lot | F5: Tâche | G5: Critère de fin | H5: Charge (j/p) | I5: Priorité | J5: Statut | K5: % saisi (optionnel) | L5: Avancement | M5: Charge retenue | N5: Charge réalisée | O5: Responsable | P5: Début prévu | Q5: Fin prévue | R5: Fin réelle | S5: Dépendances | T5: Bloquant | U5: Retard | V5: Commentaire
B6: V1-001 | C6: V1 | D6: TRV | E6: Fondations | F6: Dépôt monorepo (apps/, packages/), conventions de code, CI de base | G6: Pipeline CI vert sur une branche vide, lint et tests exécutés | H6: 3 | I6: Haute | J6: Complétée | L6: =IF($B6="","",IF(J6="Complétée",1,IF(J6="Abandonnée",0,IF(K6<>"",K6,IFERROR(VLOOKUP(J6,Parametres!$B$6:$C$12,2,FALSE),0))))) | M6: =IF($B6="","",IF(J6="Abandonnée",0,H6)) | N6: =IF($B6="","",M6*L6) | O6: Abdou-Raouf | P6: 46268 | Q6: 46273 | R6: 46274 | T6: Non | U6: =IF($B6="","",IF(AND(J6<>"Complétée",J6<>"Abandonnée",Q6<>"",TODAY()>Q6),"En retard",""))
B7: V1-002 | C7: V1 | D7: TRV | E7: Fondations | F7: Environnements dev / staging, gestion des secrets, déploiement de base | G7: Déploiement automatique de staging depuis la branche principale | H7: 4 | I7: Haute | J7: En cours | K7: 0.7 | L7: =IF($B7="","",IF(J7="Complétée",1,IF(J7="Abandonnée",0,IF(K7<>"",K7,IFERROR(VLOOKUP(J7,Parametres!$B$6:$C$12,2,FALSE),0))))) | M7: =IF($B7="","",IF(J7="Abandonnée",0,H7)) | N7: =IF($B7="","",M7*L7) | O7: Abdou-Raouf | P7: 46268 | Q7: 46274 | T7: Non | U7: =IF($B7="","",IF(AND(J7<>"Complétée",J7<>"Abandonnée",Q7<>"",TODAY()>Q7),"En retard",""))
B8: V1-003 | C8: V1 | D8: FOND | E8: Fondations | F8: Modèle de données socle : Organisation, User, Person, Company | G8: Migrations appliquées, classification de chaque champ renseignée | H8: 4 | I8: Haute | J8: Complétée | L8: =IF($B8="","",IF(J8="Complétée",1,IF(J8="Abandonnée",0,IF(K8<>"",K8,IFERROR(VLOOKUP(J8,Parametres!$B$6:$C$12,2,FALSE),0))))) | M8: =IF($B8="","",IF(J8="Abandonnée",0,H8)) | N8: =IF($B8="","",M8*L8) | O8: Abdou-Raouf | P8: 46269 | Q8: 46275 | R8: 46274 | T8: Non | U8: =IF($B8="","",IF(AND(J8<>"Complétée",J8<>"Abandonnée",Q8<>"",TODAY()>Q8),"En retard",""))
B9: V1-004 | C9: V1 | D9: FOND | E9: Fondations | F9: Modèle Deal et AssetDealDetail, typage ASSET_DEAL / SHARE_DEAL immuable | G9: Impossible de modifier dealType après création (test négatif) | H9: 4 | I9: Haute | J9: Complétée | L9: =IF($B9="","",IF(J9="Complétée",1,IF(J9="Abandonnée",0,IF(K9<>"",K9,IFERROR(VLOOKUP(J9,Parametres!$B$6:$C$12,2,FALSE),0))))) | M9: =IF($B9="","",IF(J9="Abandonnée",0,H9)) | N9: =IF($B9="","",M9*L9) | O9: Abdou-Raouf | P9: 46270 | Q9: 46276 | R9: 46275 | T9: Non | U9: =IF($B9="","",IF(AND(J9<>"Complétée",J9<>"Abandonnée",Q9<>"",TODAY()>Q9),"En retard",""))
B10: V1-005 | C10: V1 | D10: FOND | E10: Fondations | F10: Classification des champs (PUBLIC, INTERNAL, PERSONAL, CONFIDENTIAL_DEAL) dans les migrations | G10: Chaque colonne porte sa classification en commentaire de migration | H10: 2 | I10: Haute | J10: En cours | K10: 0.7 | L10: =IF($B10="","",IF(J10="Complétée",1,IF(J10="Abandonnée",0,IF(K10<>"",K10,IFERROR(VLOOKUP(J10,Parametres!$B$6:$C$12,2,FALSE),0))))) | M10: =IF($B10="","",IF(J10="Abandonnée",0,H10)) | N10: =IF($B10="","",M10*L10) | O10: Abdou-Raouf | P10: 46270 | Q10: 46273 | T10: Non | U10: =IF($B10="","",IF(AND(J10<>"Complétée",J10<>"Abandonnée",Q10<>"",TODAY()>Q10),"En retard",""))
B11: V1-006 | C11: V1 | D11: FOND | E11: Fondations | F11: Enregistrement d'attribution immuable à la création de compte (canal, campagne, référence CCI) | G11: Attribution non modifiable après création (test négatif) | H11: 2 | I11: Haute | J11: Complétée | L11: =IF($B11="","",IF(J11="Complétée",1,IF(J11="Abandonnée",0,IF(K11<>"",K11,IFERROR(VLOOKUP(J11,Parametres!$B$6:$C$12,2,FALSE),0))))) | M11: =IF($B11="","",IF(J11="Abandonnée",0,H11)) | N11: =IF($B11="","",M11*L11) | O11: Abdou-Raouf | P11: 46270 | Q11: 46273 | R11: 46275 | T11: Non | U11: =IF($B11="","",IF(AND(J11<>"Complétée",J11<>"Abandonnée",Q11<>"",TODAY()>Q11),"En retard",""))
B12: V1-007 | C12: V1 | D12: FOND | E12: Fondations | F12: Journal DealEvent et machine à états du deal (version réduite V1) | G12: Transition invalide renvoie 409, chaque transition journalisée | H12: 4 | I12: Haute | J12: Complétée | L12: =IF($B12="","",IF(J12="Complétée",1,IF(J12="Abandonnée",0,IF(K12<>"",K12,IFERROR(VLOOKUP(J12,Parametres!$B$6:$C$12,2,FALSE),0))))) | M12: =IF($B12="","",IF(J12="Abandonnée",0,H12)) | N12: =IF($B12="","",M12*L12) | O12: Abdou-Raouf | P12: 46271 | Q12: 46277 | R12: 46274 | T12: Non | U12: =IF($B12="","",IF(AND(J12<>"Complétée",J12<>"Abandonnée",Q12<>"",TODAY()>Q12),"En retard",""))
B13: V1-008 | C13: V1 | D13: TRV | E13: Fondations | F13: Socle i18n français-source, formats FCFA (entier, sans décimale), dates, typographie | G13: Aucune chaîne anglaise dans l'interface, montants en XOF entiers | H13: 3 | I13: Moyenne | J13: En cours | K13: 0.6 | L13: =IF($B13="","",IF(J13="Complétée",1,IF(J13="Abandonnée",0,IF(K13<>"",K13,IFERROR(VLOOKUP(J13,Parametres!$B$6:$C$12,2,FALSE),0))))) | M13: =IF($B13="","",IF(J13="Abandonnée",0,H13)) | N13: =IF($B13="","",M13*L13) | O13: Abdou-Raouf | P13: 46271 | Q13: 46276 | T13: Non | U13: =IF($B13="","",IF(AND(J13<>"Complétée",J13<>"Abandonnée",Q13<>"",TODAY()>Q13),"En retard",""))
B14: V1-009 | C14: V1 | D14: OPS | E14: Fondations | F14: Supervision et journaux applicatifs de base | G14: Journaux centralisés, alerte sur erreur 5xx | H14: 3 | I14: Moyenne | J14: À faire | L14: =IF($B14="","",IF(J14="Complétée",1,IF(J14="Abandonnée",0,IF(K14<>"",K14,IFERROR(VLOOKUP(J14,Parametres!$B$6:$C$12,2,FALSE),0))))) | M14: =IF($B14="","",IF(J14="Abandonnée",0,H14)) | N14: =IF($B14="","",M14*L14) | P14: 46272 | Q14: 46277 | T14: Non | U14: =IF($B14="","",IF(AND(J14<>"Complétée",J14<>"Abandonnée",Q14<>"",TODAY()>Q14),"En retard",""))
B15: V1-010 | C15: V1 | D15: OPS | E15: Fondations | F15: Sauvegardes de base de la base de données | G15: Sauvegarde quotidienne, restauration testée une fois | H15: 2 | I15: Moyenne | J15: À faire | L15: =IF($B15="","",IF(J15="Complétée",1,IF(J15="Abandonnée",0,IF(K15<>"",K15,IFERROR(VLOOKUP(J15,Parametres!$B$6:$C$12,2,FALSE),0))))) | M15: =IF($B15="","",IF(J15="Abandonnée",0,H15)) | N15: =IF($B15="","",M15*L15) | P15: 46272 | Q15: 46275 | T15: Non | U15: =IF($B15="","",IF(AND(J15<>"Complétée",J15<>"Abandonnée",Q15<>"",TODAY()>Q15),"En retard",""))
B16: V1-011 | C16: V1 | D16: OPS | E16: Sécurité | F16: RLS effective : rôle applicatif sans contournement, contexte app.organisation_id et app.roles par transaction | G16: Test négatif : un cédant ne lit pas le dossier d'un autre cédant | H16: 4 | I16: Haute | J16: Complétée | L16: =IF($B16="","",IF(J16="Complétée",1,IF(J16="Abandonnée",0,IF(K16<>"",K16,IFERROR(VLOOKUP(J16,Parametres!$B$6:$C$12,2,FALSE),0))))) | M16: =IF($B16="","",IF(J16="Abandonnée",0,H16)) | N16: =IF($B16="","",M16*L16) | O16: Abdou-Raouf | P16: 46272 | Q16: 46278 | R16: 46275 | T16: Oui | U16: =IF($B16="","",IF(AND(J16<>"Complétée",J16<>"Abandonnée",Q16<>"",TODAY()>Q16),"En retard",""))
B17: V1-012 | C17: V1 | D17: OPS | E17: Sécurité | F17: Anti-force-brute : limitation de débit par IP et par compte, verrouillage progressif, journal des échecs | G17: Cinquième échec en une minute renvoie 429 et laisse une trace | H17: 2 | I17: Haute | J17: Complétée | L17: =IF($B17="","",IF(J17="Complétée",1,IF(J17="Abandonnée",0,IF(K17<>"",K17,IFERROR(VLOOKUP(J17,Parametres!$B$6:$C$12,2,FALSE),0))))) | M17: =IF($B17="","",IF(J17="Abandonnée",0,H17)) | N17: =IF($B17="","",M17*L17) | O17: Abdou-Raouf | P17: 46273 | Q17: 46276 | R17: 46275 | T17: Non | U17: =IF($B17="","",IF(AND(J17<>"Complétée",J17<>"Abandonnée",Q17<>"",TODAY()>Q17),"En retard",""))
B18: V1-013 | C18: V1 | D18: OPS | E18: Sécurité | F18: Vérification email, MFA obligatoire pour les officiers CCI-Togo et les administrateurs, liaison OTP | G18: Officier sans second facteur ne peut pas certifier | H18: 3 | I18: Haute | J18: Complétée | L18: =IF($B18="","",IF(J18="Complétée",1,IF(J18="Abandonnée",0,IF(K18<>"",K18,IFERROR(VLOOKUP(J18,Parametres!$B$6:$C$12,2,FALSE),0))))) | M18: =IF($B18="","",IF(J18="Abandonnée",0,H18)) | N18: =IF($B18="","",M18*L18) | O18: Abdou-Raouf | P18: 46273 | Q18: 46278 | R18: 46275 | S18: OTP SMS | T18: Non | U18: =IF($B18="","",IF(AND(J18<>"Complétée",J18<>"Abandonnée",Q18<>"",TODAY()>Q18),"En retard",""))
B19: V1-014 | C19: V1 | D19: OPS | E19: Sécurité | F19: Chiffrement applicatif des champs CONFIDENTIAL_DEAL, clé gérée hors base, rotation documentée | G19: Prix illisible dans un dump de la base | H19: 3 | I19: Haute | J19: Complétée | L19: =IF($B19="","",IF(J19="Complétée",1,IF(J19="Abandonnée",0,IF(K19<>"",K19,IFERROR(VLOOKUP(J19,Parametres!$B$6:$C$12,2,FALSE),0))))) | M19: =IF($B19="","",IF(J19="Abandonnée",0,H19)) | N19: =IF($B19="","",M19*L19) | O19: Abdou-Raouf | P19: 46274 | Q19: 46279 | R19: 46275 | T19: Non | U19: =IF($B19="","",IF(AND(J19<>"Complétée",J19<>"Abandonnée",Q19<>"",TODAY()>Q19),"En retard",""))
B20: V1-015 | C20: V1 | D20: OPS | E20: Sécurité | F20: En-têtes de sécurité HTTP, CORS strict, cookies sécurisés, taille maximale des corps de requête | G20: Scan d'en-têtes sans constat, origine inconnue refusée | H20: 1 | I20: Moyenne | J20: Complétée | L20: =IF($B20="","",IF(J20="Complétée",1,IF(J20="Abandonnée",0,IF(K20<>"",K20,IFERROR(VLOOKUP(J20,Parametres!$B$6:$C$12,2,FALSE),0))))) | M20: =IF($B20="","",IF(J20="Abandonnée",0,H20)) | N20: =IF($B20="","",M20*L20) | O20: Abdou-Raouf | P20: 46274 | Q20: 46276 | R20: 46275 | T20: Non | U20: =IF($B20="","",IF(AND(J20<>"Complétée",J20<>"Abandonnée",Q20<>"",TODAY()>Q20),"En retard",""))
B21: V1-016 | C21: V1 | D21: OPS | E21: Sécurité | F21: Idempotence persistée en base et vérification de signature HMAC sur tous les webhooks | G21: Rejeu d'un webhook sans double effet ; signature invalide rejetée | H21: 2 | I21: Haute | J21: Complétée | L21: =IF($B21="","",IF(J21="Complétée",1,IF(J21="Abandonnée",0,IF(K21<>"",K21,IFERROR(VLOOKUP(J21,Parametres!$B$6:$C$12,2,FALSE),0))))) | M21: =IF($B21="","",IF(J21="Abandonnée",0,H21)) | N21: =IF($B21="","",M21*L21) | O21: Abdou-Raouf | P21: 46274 | Q21: 46277 | R21: 46275 | T21: Non | U21: =IF($B21="","",IF(AND(J21<>"Complétée",J21<>"Abandonnée",Q21<>"",TODAY()>Q21),"En retard",""))
B22: V1-017 | C22: V1 | D22: OPS | E22: Sécurité | F22: Revue de sécurité interne (liste de contrôle v0 : paliers, URL pré-signées, compteur RPS) et scan de dépendances bloquant en CI | G22: Rapport de revue archivé, CI rouge sur vulnérabilité critique | H22: 3 | I22: Haute | J22: À faire | L22: =IF($B22="","",IF(J22="Complétée",1,IF(J22="Abandonnée",0,IF(K22<>"",K22,IFERROR(VLOOKUP(J22,Parametres!$B$6:$C$12,2,FALSE),0))))) | M22: =IF($B22="","",IF(J22="Abandonnée",0,H22)) | N22: =IF($B22="","",M22*L22) | P22: 46274 | Q22: 46279 | T22: Non | U22: =IF($B22="","",IF(AND(J22<>"Complétée",J22<>"Abandonnée",Q22<>"",TODAY()>Q22),"En retard",""))
B23: V1-018 | C23: V1 | D23: OPS | E23: Sécurité | F23: Mots de passe de démonstration uniques par compte, jeu de démonstration interdit hors environnement local | G23: Le chargement refuse de s'exécuter si NODE_ENV n'est pas development | H23: 1 | I23: Moyenne | J23: Complétée | L23: =IF($B23="","",IF(J23="Complétée",1,IF(J23="Abandonnée",0,IF(K23<>"",K23,IFERROR(VLOOKUP(J23,Parametres!$B$6:$C$12,2,FALSE),0))))) | M23: =IF($B23="","",IF(J23="Abandonnée",0,H23)) | N23: =IF($B23="","",M23*L23) | O23: Abdou-Raouf | P23: 46275 | Q23: 46277 | R23: 46275 | T23: Non | U23: =IF($B23="","",IF(AND(J23<>"Complétée",J23<>"Abandonnée",Q23<>"",TODAY()>Q23),"En retard",""))
B24: V1-019 | C24: V1 | D24: IDN | E24: Auth et rôles | F24: Inscription email + mot de passe (Argon2id), vérification email | G24: Compte créé, email vérifié, mot de passe jamais en clair | H24: 3 | I24: Haute | J24: En cours | K24: 0.7 | L24: =IF($B24="","",IF(J24="Complétée",1,IF(J24="Abandonnée",0,IF(K24<>"",K24,IFERROR(VLOOKUP(J24,Parametres!$B$6:$C$12,2,FALSE),0))))) | M24: =IF($B24="","",IF(J24="Abandonnée",0,H24)) | N24: =IF($B24="","",M24*L24) | O24: Abdou-Raouf | P24: 46275 | Q24: 46280 | T24: Non | U24: =IF($B24="","",IF(AND(J24<>"Complétée",J24<>"Abandonnée",Q24<>"",TODAY()>Q24),"En retard",""))
B25: V1-020 | C25: V1 | D25: IDN | E25: Auth et rôles | F25: OTP SMS (intégration fournisseur SMS) | G25: Code reçu et validé en moins de 60 s en test | H25: 3 | I25: Haute | J25: En cours | K25: 0.6 | L25: =IF($B25="","",IF(J25="Complétée",1,IF(J25="Abandonnée",0,IF(K25<>"",K25,IFERROR(VLOOKUP(J25,Parametres!$B$6:$C$12,2,FALSE),0))))) | M25: =IF($B25="","",IF(J25="Abandonnée",0,H25)) | N25: =IF($B25="","",M25*L25) | O25: Abdou-Raouf | P25: 46275 | Q25: 46280 | T25: Non | U25: =IF($B25="","",IF(AND(J25<>"Complétée",J25<>"Abandonnée",Q25<>"",TODAY()>Q25),"En retard",""))
B26: V1-021 | C26: V1 | D26: IDN | E26: Auth et rôles | F26: Rôles et permissions évalués côté serveur (cédant, investisseur, agent CCI-Togo, admin) | G26: Chaque endpoint refuse un rôle non autorisé (tests négatifs) | H26: 4 | I26: Haute | J26: Complétée | L26: =IF($B26="","",IF(J26="Complétée",1,IF(J26="Abandonnée",0,IF(K26<>"",K26,IFERROR(VLOOKUP(J26,Parametres!$B$6:$C$12,2,FALSE),0))))) | M26: =IF($B26="","",IF(J26="Abandonnée",0,H26)) | N26: =IF($B26="","",M26*L26) | O26: Abdou-Raouf | P26: 46276 | Q26: 46282 | R26: 46275 | T26: Non | U26: =IF($B26="","",IF(AND(J26<>"Complétée",J26<>"Abandonnée",Q26<>"",TODAY()>Q26),"En retard",""))
B27: V1-022 | C27: V1 | D27: IDN | E27: Auth et rôles | F27: Gestion de session : expiration, liste des appareils, révocation à distance | G27: Session révoquée inutilisable immédiatement | H27: 2 | I27: Moyenne | J27: En cours | K27: 0.7 | L27: =IF($B27="","",IF(J27="Complétée",1,IF(J27="Abandonnée",0,IF(K27<>"",K27,IFERROR(VLOOKUP(J27,Parametres!$B$6:$C$12,2,FALSE),0))))) | M27: =IF($B27="","",IF(J27="Abandonnée",0,H27)) | N27: =IF($B27="","",M27*L27) | O27: Abdou-Raouf | P27: 46276 | Q27: 46279 | T27: Non | U27: =IF($B27="","",IF(AND(J27<>"Complétée",J27<>"Abandonnée",Q27<>"",TODAY()>Q27),"En retard",""))
B28: V1-023 | C28: V1 | D28: IDN | E28: Auth et rôles | F28: Consentements séparés (CGU, confidentialité, marketing) | G28: Trois cases distinctes, marketing non pré-coché | H28: 2 | I28: Moyenne | J28: Complétée | L28: =IF($B28="","",IF(J28="Complétée",1,IF(J28="Abandonnée",0,IF(K28<>"",K28,IFERROR(VLOOKUP(J28,Parametres!$B$6:$C$12,2,FALSE),0))))) | M28: =IF($B28="","",IF(J28="Abandonnée",0,H28)) | N28: =IF($B28="","",M28*L28) | O28: Abdou-Raouf | P28: 46277 | Q28: 46280 | R28: 46274 | T28: Non | U28: =IF($B28="","",IF(AND(J28<>"Complétée",J28<>"Abandonnée",Q28<>"",TODAY()>Q28),"En retard",""))
B29: V1-024 | C29: V1 | D29: IDN | E29: Auth et rôles | F29: Paliers d'abonnement : modèle et entitlements (sans paiement en V1) | G29: Entitlement résolu depuis un service unique versionné | H29: 4 | I29: Moyenne | J29: En cours | K29: 0.5 | L29: =IF($B29="","",IF(J29="Complétée",1,IF(J29="Abandonnée",0,IF(K29<>"",K29,IFERROR(VLOOKUP(J29,Parametres!$B$6:$C$12,2,FALSE),0))))) | M29: =IF($B29="","",IF(J29="Abandonnée",0,H29)) | N29: =IF($B29="","",M29*L29) | O29: Abdou-Raouf | P29: 46277 | Q29: 46283 | T29: Non | U29: =IF($B29="","",IF(AND(J29<>"Complétée",J29<>"Abandonnée",Q29<>"",TODAY()>Q29),"En retard",""))
B30: V1-025 | C30: V1 | D30: IDN | E30: Auth et rôles | F30: Écrans authentification (connexion, inscription, OTP, profil) | G30: Parcours complet sur mobile et desktop | H30: 4 | I30: Haute | J30: À faire | L30: =IF($B30="","",IF(J30="Complétée",1,IF(J30="Abandonnée",0,IF(K30<>"",K30,IFERROR(VLOOKUP(J30,Parametres!$B$6:$C$12,2,FALSE),0))))) | M30: =IF($B30="","",IF(J30="Abandonnée",0,H30)) | N30: =IF($B30="","",M30*L30) | P30: 46278 | Q30: 46284 | T30: Non | U30: =IF($B30="","",IF(AND(J30<>"Complétée",J30<>"Abandonnée",Q30<>"",TODAY()>Q30),"En retard",""))
B31: V1-026 | C31: V1 | D31: GOV | E31: Espace CCI-Togo | F31: Workflow de confirmation d'adhésion (demande, décision, référence stockée) | G31: Seule la référence de confirmation est stockée, jamais la base des membres | H31: 4 | I31: Haute | J31: En cours | K31: 0.8 | L31: =IF($B31="","",IF(J31="Complétée",1,IF(J31="Abandonnée",0,IF(K31<>"",K31,IFERROR(VLOOKUP(J31,Parametres!$B$6:$C$12,2,FALSE),0))))) | M31: =IF($B31="","",IF(J31="Abandonnée",0,H31)) | N31: =IF($B31="","",M31*L31) | O31: Abdou-Raouf | P31: 46278 | Q31: 46284 | T31: Non | U31: =IF($B31="","",IF(AND(J31<>"Complétée",J31<>"Abandonnée",Q31<>"",TODAY()>Q31),"En retard",""))
B32: V1-027 | C32: V1 | D32: GOV | E32: Espace CCI-Togo | F32: Vérification RCCM / CFE : adaptateur (API si disponible, sinon saisie manuelle supervisée) | G32: Source et horodatage de vérification stockés | H32: 5 | I32: Haute | J32: En cours | K32: 0.7 | L32: =IF($B32="","",IF(J32="Complétée",1,IF(J32="Abandonnée",0,IF(K32<>"",K32,IFERROR(VLOOKUP(J32,Parametres!$B$6:$C$12,2,FALSE),0))))) | M32: =IF($B32="","",IF(J32="Abandonnée",0,H32)) | N32: =IF($B32="","",M32*L32) | O32: Abdou-Raouf | P32: 46279 | Q32: 46286 | S32: Réponse sur l'API CFE/RCCM | T32: Oui | U32: =IF($B32="","",IF(AND(J32<>"Complétée",J32<>"Abandonnée",Q32<>"",TODAY()>Q32),"En retard",""))
B33: V1-028 | C33: V1 | D33: GOV | E33: Espace CCI-Togo | F33: RegistryRecord stocké séparément des données déclarées par le cédant | G33: Deux tables distinctes, aucune fusion à l'affichage | H33: 2 | I33: Haute | J33: Complétée | L33: =IF($B33="","",IF(J33="Complétée",1,IF(J33="Abandonnée",0,IF(K33<>"",K33,IFERROR(VLOOKUP(J33,Parametres!$B$6:$C$12,2,FALSE),0))))) | M33: =IF($B33="","",IF(J33="Abandonnée",0,H33)) | N33: =IF($B33="","",M33*L33) | O33: Abdou-Raouf | P33: 46279 | Q33: 46282 | R33: 46274 | T33: Non | U33: =IF($B33="","",IF(AND(J33<>"Complétée",J33<>"Abandonnée",Q33<>"",TODAY()>Q33),"En retard",""))
B34: V1-029 | C34: V1 | D34: GOV | E34: Espace CCI-Togo | F34: Tableau de bord institutionnel agrégé (version minimale) | G34: Aucune vue sur le contenu confidentiel d'un dossier | H34: 3 | I34: Moyenne | J34: À faire | L34: =IF($B34="","",IF(J34="Complétée",1,IF(J34="Abandonnée",0,IF(K34<>"",K34,IFERROR(VLOOKUP(J34,Parametres!$B$6:$C$12,2,FALSE),0))))) | M34: =IF($B34="","",IF(J34="Abandonnée",0,H34)) | N34: =IF($B34="","",M34*L34) | P34: 46280 | Q34: 46285 | T34: Non | U34: =IF($B34="","",IF(AND(J34<>"Complétée",J34<>"Abandonnée",Q34<>"",TODAY()>Q34),"En retard",""))
B35: V1-030 | C35: V1 | D35: GOV | E35: Espace CCI-Togo | F35: Écrans console CCI-Togo | G35: Rôles et journal d'audit séparés du back-office plateforme | H35: 5 | I35: Haute | J35: À faire | L35: =IF($B35="","",IF(J35="Complétée",1,IF(J35="Abandonnée",0,IF(K35<>"",K35,IFERROR(VLOOKUP(J35,Parametres!$B$6:$C$12,2,FALSE),0))))) | M35: =IF($B35="","",IF(J35="Abandonnée",0,H35)) | N35: =IF($B35="","",M35*L35) | P35: 46280 | Q35: 46287 | T35: Non | U35: =IF($B35="","",IF(AND(J35<>"Complétée",J35<>"Abandonnée",Q35<>"",TODAY()>Q35),"En retard",""))
B36: V1-031 | C36: V1 | D36: CCI | E36: Deal-Ready | F36: Modèle Certification : portée, décision, officier, expiration, révocation | G36: Chaque décision porte un officier nommé | H36: 2 | I36: Haute | J36: Complétée | L36: =IF($B36="","",IF(J36="Complétée",1,IF(J36="Abandonnée",0,IF(K36<>"",K36,IFERROR(VLOOKUP(J36,Parametres!$B$6:$C$12,2,FALSE),0))))) | M36: =IF($B36="","",IF(J36="Abandonnée",0,H36)) | N36: =IF($B36="","",M36*L36) | O36: Abdou-Raouf | P36: 46281 | Q36: 46284 | R36: 46274 | T36: Non | U36: =IF($B36="","",IF(AND(J36<>"Complétée",J36<>"Abandonnée",Q36<>"",TODAY()>Q36),"En retard",""))
B37: V1-032 | C37: V1 | D37: CCI | E37: Deal-Ready | F37: Workflow de décision nominative (octroi, refus, retrait) et déclaration de conflit d'intérêts | G37: Octroi automatique impossible par construction (test négatif) | H37: 4 | I37: Haute | J37: Complétée | L37: =IF($B37="","",IF(J37="Complétée",1,IF(J37="Abandonnée",0,IF(K37<>"",K37,IFERROR(VLOOKUP(J37,Parametres!$B$6:$C$12,2,FALSE),0))))) | M37: =IF($B37="","",IF(J37="Abandonnée",0,H37)) | N37: =IF($B37="","",M37*L37) | O37: Abdou-Raouf | P37: 46281 | Q37: 46287 | R37: 46275 | T37: Non | U37: =IF($B37="","",IF(AND(J37<>"Complétée",J37<>"Abandonnée",Q37<>"",TODAY()>Q37),"En retard",""))
B38: V1-033 | C38: V1 | D38: CCI | E38: Deal-Ready | F38: Checklist Deal-Ready et pièces attendues | G38: Liste des manques visible par l'entreprise | H38: 3 | I38: Moyenne | J38: À faire | L38: =IF($B38="","",IF(J38="Complétée",1,IF(J38="Abandonnée",0,IF(K38<>"",K38,IFERROR(VLOOKUP(J38,Parametres!$B$6:$C$12,2,FALSE),0))))) | M38: =IF($B38="","",IF(J38="Abandonnée",0,H38)) | N38: =IF($B38="","",M38*L38) | P38: 46282 | Q38: 46287 | T38: Non | U38: =IF($B38="","",IF(AND(J38<>"Complétée",J38<>"Abandonnée",Q38<>"",TODAY()>Q38),"En retard",""))
B39: V1-034 | C39: V1 | D39: CCI | E39: Deal-Ready | F39: Écrans côté entreprise : demande, suivi de remédiation | G39: Statut et pièces manquantes visibles | H39: 4 | I39: Moyenne | J39: À faire | L39: =IF($B39="","",IF(J39="Complétée",1,IF(J39="Abandonnée",0,IF(K39<>"",K39,IFERROR(VLOOKUP(J39,Parametres!$B$6:$C$12,2,FALSE),0))))) | M39: =IF($B39="","",IF(J39="Abandonnée",0,H39)) | N39: =IF($B39="","",M39*L39) | P39: 46282 | Q39: 46288 | T39: Non | U39: =IF($B39="","",IF(AND(J39<>"Complétée",J39<>"Abandonnée",Q39<>"",TODAY()>Q39),"En retard",""))
B40: V1-035 | C40: V1 | D40: CCI | E40: Deal-Ready | F40: Badge Deal-Ready : affichage avec périmètre et limites explicites | G40: Texte du badge précise ce qui est vérifié et ce qui ne l'est pas | H40: 2 | I40: Haute | J40: En cours | K40: 0.6 | L40: =IF($B40="","",IF(J40="Complétée",1,IF(J40="Abandonnée",0,IF(K40<>"",K40,IFERROR(VLOOKUP(J40,Parametres!$B$6:$C$12,2,FALSE),0))))) | M40: =IF($B40="","",IF(J40="Abandonnée",0,H40)) | N40: =IF($B40="","",M40*L40) | O40: Abdou-Raouf | P40: 46283 | Q40: 46286 | T40: Non | U40: =IF($B40="","",IF(AND(J40<>"Complétée",J40<>"Abandonnée",Q40<>"",TODAY()>Q40),"En retard",""))
B41: V1-036 | C41: V1 | D41: CCI | E41: Deal-Ready | F41: Journal d'audit des décisions de certification | G41: Chaque décision exportable avec horodatage et officier | H41: 2 | I41: Moyenne | J41: En cours | K41: 0.6 | L41: =IF($B41="","",IF(J41="Complétée",1,IF(J41="Abandonnée",0,IF(K41<>"",K41,IFERROR(VLOOKUP(J41,Parametres!$B$6:$C$12,2,FALSE),0))))) | M41: =IF($B41="","",IF(J41="Abandonnée",0,H41)) | N41: =IF($B41="","",M41*L41) | O41: Abdou-Raouf | P41: 46283 | Q41: 46286 | T41: Non | U41: =IF($B41="","",IF(AND(J41<>"Complétée",J41<>"Abandonnée",Q41<>"",TODAY()>Q41),"En retard",""))
B42: V1-037 | C42: V1 | D42: MKT | E42: Dossier cédant | F42: Assistant de constitution de dossier : étapes, branchement par type de cession dès l'étape 1 | G42: Parcours actif complet, branche titres présente mais bloquée en V1 | H42: 6 | I42: Haute | J42: En cours | K42: 0.15 | L42: =IF($B42="","",IF(J42="Complétée",1,IF(J42="Abandonnée",0,IF(K42<>"",K42,IFERROR(VLOOKUP(J42,Parametres!$B$6:$C$12,2,FALSE),0))))) | M42: =IF($B42="","",IF(J42="Abandonnée",0,H42)) | N42: =IF($B42="","",M42*L42) | O42: Abdou-Raouf | P42: 46283 | Q42: 46292 | T42: Non | U42: =IF($B42="","",IF(AND(J42<>"Complétée",J42<>"Abandonnée",Q42<>"",TODAY()>Q42),"En retard",""))
B43: V1-038 | C43: V1 | D43: MKT | E43: Dossier cédant | F43: Upload de documents : scan antivirus, stockage chiffré, jamais d'URL publique | G43: Fichier infecté rejeté, URL directe inaccessible (test négatif) | H43: 4 | I43: Haute | J43: À faire | L43: =IF($B43="","",IF(J43="Complétée",1,IF(J43="Abandonnée",0,IF(K43<>"",K43,IFERROR(VLOOKUP(J43,Parametres!$B$6:$C$12,2,FALSE),0))))) | M43: =IF($B43="","",IF(J43="Abandonnée",0,H43)) | N43: =IF($B43="","",M43*L43) | P43: 46284 | Q43: 46290 | T43: Non | U43: =IF($B43="","",IF(AND(J43<>"Complétée",J43<>"Abandonnée",Q43<>"",TODAY()>Q43),"En retard",""))
B44: V1-039 | C44: V1 | D44: MKT | E44: Dossier cédant | F44: Provenance et versionnage des données déclarées | G44: Chaque valeur porte source et date, mention 'déclaré, non audité' | H44: 3 | I44: Haute | J44: À faire | L44: =IF($B44="","",IF(J44="Complétée",1,IF(J44="Abandonnée",0,IF(K44<>"",K44,IFERROR(VLOOKUP(J44,Parametres!$B$6:$C$12,2,FALSE),0))))) | M44: =IF($B44="","",IF(J44="Abandonnée",0,H44)) | N44: =IF($B44="","",M44*L44) | P44: 46285 | Q44: 46290 | T44: Non | U44: =IF($B44="","",IF(AND(J44<>"Complétée",J44<>"Abandonnée",Q44<>"",TODAY()>Q44),"En retard",""))
B45: V1-040 | C45: V1 | D45: MKT | E45: Dossier cédant | F45: Contrôle de complétude et liste des manques | G45: Dossier incomplet reste en DRAFT | H45: 3 | I45: Moyenne | J45: À faire | L45: =IF($B45="","",IF(J45="Complétée",1,IF(J45="Abandonnée",0,IF(K45<>"",K45,IFERROR(VLOOKUP(J45,Parametres!$B$6:$C$12,2,FALSE),0))))) | M45: =IF($B45="","",IF(J45="Abandonnée",0,H45)) | N45: =IF($B45="","",M45*L45) | P45: 46285 | Q45: 46290 | T45: Non | U45: =IF($B45="","",IF(AND(J45<>"Complétée",J45<>"Abandonnée",Q45<>"",TODAY()>Q45),"En retard",""))
B46: V1-041 | C46: V1 | D46: MKT | E46: Dossier cédant | F46: Écrans Pass Transmission (assistant, récapitulatif) | G46: Récapitulatif fidèle aux données saisies | H46: 5 | I46: Haute | J46: À faire | L46: =IF($B46="","",IF(J46="Complétée",1,IF(J46="Abandonnée",0,IF(K46<>"",K46,IFERROR(VLOOKUP(J46,Parametres!$B$6:$C$12,2,FALSE),0))))) | M46: =IF($B46="","",IF(J46="Abandonnée",0,H46)) | N46: =IF($B46="","",M46*L46) | P46: 46285 | Q46: 46292 | T46: Non | U46: =IF($B46="","",IF(AND(J46<>"Complétée",J46<>"Abandonnée",Q46<>"",TODAY()>Q46),"En retard",""))
B47: V1-042 | C47: V1 | D47: MKT | E47: Marketplace actifs | F47: Fiche opportunité T0 (secteur, région, tranche de CA) et publication | G47: Aucun champ au-delà de T0 sérialisé (allow-list serveur) | H47: 4 | I47: Haute | J47: En cours | K47: 0.85 | L47: =IF($B47="","",IF(J47="Complétée",1,IF(J47="Abandonnée",0,IF(K47<>"",K47,IFERROR(VLOOKUP(J47,Parametres!$B$6:$C$12,2,FALSE),0))))) | M47: =IF($B47="","",IF(J47="Abandonnée",0,H47)) | N47: =IF($B47="","",M47*L47) | O47: Abdou-Raouf | P47: 46286 | Q47: 46292 | T47: Non | U47: =IF($B47="","",IF(AND(J47<>"Complétée",J47<>"Abandonnée",Q47<>"",TODAY()>Q47),"En retard",""))
B48: V1-043 | C48: V1 | D48: MKT | E48: Marketplace actifs | F48: Recherche et filtres (secteur, région, tranche, statut de certification) | G48: Résultats limités aux champs T0 | H48: 4 | I48: Haute | J48: En cours | K48: 0.8 | L48: =IF($B48="","",IF(J48="Complétée",1,IF(J48="Abandonnée",0,IF(K48<>"",K48,IFERROR(VLOOKUP(J48,Parametres!$B$6:$C$12,2,FALSE),0))))) | M48: =IF($B48="","",IF(J48="Abandonnée",0,H48)) | N48: =IF($B48="","",M48*L48) | O48: Abdou-Raouf | P48: 46287 | Q48: 46293 | T48: Non | U48: =IF($B48="","",IF(AND(J48<>"Complétée",J48<>"Abandonnée",Q48<>"",TODAY()>Q48),"En retard",""))
B49: V1-044 | C49: V1 | D49: MKT | E49: Marketplace actifs | F49: Mise en relation : manifestation d'intérêt et messagerie simple (pièces jointes bloquées) | G49: Intérêt tracé, message reçu, pièce jointe refusée | H49: 5 | I49: Haute | J49: En cours | K49: 0.6 | L49: =IF($B49="","",IF(J49="Complétée",1,IF(J49="Abandonnée",0,IF(K49<>"",K49,IFERROR(VLOOKUP(J49,Parametres!$B$6:$C$12,2,FALSE),0))))) | M49: =IF($B49="","",IF(J49="Abandonnée",0,H49)) | N49: =IF($B49="","",M49*L49) | O49: Abdou-Raouf | P49: 46287 | Q49: 46294 | T49: Non | U49: =IF($B49="","",IF(AND(J49<>"Complétée",J49<>"Abandonnée",Q49<>"",TODAY()>Q49),"En retard",""))
B50: V1-045 | C50: V1 | D50: MKT | E50: Marketplace actifs | F50: Alertes sauvegardées opt-in (version simple) | G50: Aucune alerte sans opt-in explicite | H50: 3 | I50: Basse | J50: À faire | L50: =IF($B50="","",IF(J50="Complétée",1,IF(J50="Abandonnée",0,IF(K50<>"",K50,IFERROR(VLOOKUP(J50,Parametres!$B$6:$C$12,2,FALSE),0))))) | M50: =IF($B50="","",IF(J50="Abandonnée",0,H50)) | N50: =IF($B50="","",M50*L50) | P50: 46288 | Q50: 46293 | T50: Non | U50: =IF($B50="","",IF(AND(J50<>"Complétée",J50<>"Abandonnée",Q50<>"",TODAY()>Q50),"En retard",""))
B51: V1-046 | C51: V1 | D51: MKT | E51: Marketplace actifs | F51: Tableau de bord cédant (vues, intérêts reçus) | G51: Compteurs cohérents avec le journal | H51: 3 | I51: Moyenne | J51: À faire | L51: =IF($B51="","",IF(J51="Complétée",1,IF(J51="Abandonnée",0,IF(K51<>"",K51,IFERROR(VLOOKUP(J51,Parametres!$B$6:$C$12,2,FALSE),0))))) | M51: =IF($B51="","",IF(J51="Abandonnée",0,H51)) | N51: =IF($B51="","",M51*L51) | P51: 46288 | Q51: 46293 | T51: Non | U51: =IF($B51="","",IF(AND(J51<>"Complétée",J51<>"Abandonnée",Q51<>"",TODAY()>Q51),"En retard",""))
B52: V1-047 | C52: V1 | D52: MKT | E52: Marketplace actifs | F52: Écrans marketplace (liste, détail, recherche) | G52: Six onglets de la fiche opportunité conformes à la Tranche 3 | H52: 5 | I52: Haute | J52: À faire | L52: =IF($B52="","",IF(J52="Complétée",1,IF(J52="Abandonnée",0,IF(K52<>"",K52,IFERROR(VLOOKUP(J52,Parametres!$B$6:$C$12,2,FALSE),0))))) | M52: =IF($B52="","",IF(J52="Abandonnée",0,H52)) | N52: =IF($B52="","",M52*L52) | P52: 46289 | Q52: 46296 | T52: Non | U52: =IF($B52="","",IF(AND(J52<>"Complétée",J52<>"Abandonnée",Q52<>"",TODAY()>Q52),"En retard",""))
B53: V1-048 | C53: V1 | D53: MKT | E53: Évaluation indicative | F53: Saisie des données financières minimales et retraitements documentés | G53: Retraitement tracé avec justification | H53: 3 | I53: Moyenne | J53: En cours | K53: 0.4 | L53: =IF($B53="","",IF(J53="Complétée",1,IF(J53="Abandonnée",0,IF(K53<>"",K53,IFERROR(VLOOKUP(J53,Parametres!$B$6:$C$12,2,FALSE),0))))) | M53: =IF($B53="","",IF(J53="Abandonnée",0,H53)) | N53: =IF($B53="","",M53*L53) | O53: Abdou-Raouf | P53: 46289 | Q53: 46294 | T53: Non | U53: =IF($B53="","",IF(AND(J53<>"Complétée",J53<>"Abandonnée",Q53<>"",TODAY()>Q53),"En retard",""))
B54: V1-049 | C54: V1 | D54: MKT | E54: Évaluation indicative | F54: Calcul de fourchette indicative, méthode et sources affichées | G54: Méthode, date et sources visibles à côté du résultat | H54: 3 | I54: Moyenne | J54: Complétée | L54: =IF($B54="","",IF(J54="Complétée",1,IF(J54="Abandonnée",0,IF(K54<>"",K54,IFERROR(VLOOKUP(J54,Parametres!$B$6:$C$12,2,FALSE),0))))) | M54: =IF($B54="","",IF(J54="Abandonnée",0,H54)) | N54: =IF($B54="","",M54*L54) | O54: Abdou-Raouf | P54: 46290 | Q54: 46295 | R54: 46274 | T54: Non | U54: =IF($B54="","",IF(AND(J54<>"Complétée",J54<>"Abandonnée",Q54<>"",TODAY()>Q54),"En retard",""))
B55: V1-050 | C55: V1 | D55: MKT | E55: Évaluation indicative | F55: Mentions 'indicative, non opposable' et journal de calcul versionné | G55: Mention non masquable, calcul rejouable | H55: 2 | I55: Haute | J55: Complétée | L55: =IF($B55="","",IF(J55="Complétée",1,IF(J55="Abandonnée",0,IF(K55<>"",K55,IFERROR(VLOOKUP(J55,Parametres!$B$6:$C$12,2,FALSE),0))))) | M55: =IF($B55="","",IF(J55="Abandonnée",0,H55)) | N55: =IF($B55="","",M55*L55) | O55: Abdou-Raouf | P55: 46290 | Q55: 46293 | R55: 46274 | T55: Non | U55: =IF($B55="","",IF(AND(J55<>"Complétée",J55<>"Abandonnée",Q55<>"",TODAY()>Q55),"En retard",""))
B56: V1-051 | C56: V1 | D56: RPS | E56: Démonstration RPS | F56: Scénario scripté : dossier titres, tentative de publication trop large | G56: Scénario rejouable en moins de 3 minutes | H56: 4 | I56: Moyenne | J56: En cours | K56: 0.3 | L56: =IF($B56="","",IF(J56="Complétée",1,IF(J56="Abandonnée",0,IF(K56<>"",K56,IFERROR(VLOOKUP(J56,Parametres!$B$6:$C$12,2,FALSE),0))))) | M56: =IF($B56="","",IF(J56="Abandonnée",0,H56)) | N56: =IF($B56="","",M56*L56) | O56: Abdou-Raouf | P56: 46291 | Q56: 46297 | T56: Non | U56: =IF($B56="","",IF(AND(J56<>"Complétée",J56<>"Abandonnée",Q56<>"",TODAY()>Q56),"En retard",""))
B57: V1-052 | C57: V1 | D57: RPS | E57: Démonstration RPS | F57: Bannière de blocage et texte explicatif (risque de nullité, paliers T0/T1) | G57: Texte validé par M. Bruno | H57: 3 | I57: Moyenne | J57: À faire | L57: =IF($B57="","",IF(J57="Complétée",1,IF(J57="Abandonnée",0,IF(K57<>"",K57,IFERROR(VLOOKUP(J57,Parametres!$B$6:$C$12,2,FALSE),0))))) | M57: =IF($B57="","",IF(J57="Abandonnée",0,H57)) | N57: =IF($B57="","",M57*L57) | P57: 46291 | Q57: 46296 | T57: Non | U57: =IF($B57="","",IF(AND(J57<>"Complétée",J57<>"Abandonnée",Q57<>"",TODAY()>Q57),"En retard",""))
B58: V1-053 | C58: V1 | D58: RPS | E58: Démonstration RPS | F58: Fixture synthétique dédiée, étiquetée 'démonstration' | G58: Étiquette visible sur chaque écran du scénario | H58: 2 | I58: Moyenne | J58: À faire | L58: =IF($B58="","",IF(J58="Complétée",1,IF(J58="Abandonnée",0,IF(K58<>"",K58,IFERROR(VLOOKUP(J58,Parametres!$B$6:$C$12,2,FALSE),0))))) | M58: =IF($B58="","",IF(J58="Abandonnée",0,H58)) | N58: =IF($B58="","",M58*L58) | P58: 46292 | Q58: 46295 | T58: Non | U58: =IF($B58="","",IF(AND(J58<>"Complétée",J58<>"Abandonnée",Q58<>"",TODAY()>Q58),"En retard",""))
B59: V1-054 | C59: V1 | D59: RPS | E59: Démonstration RPS | F59: Écran T1 anonymisé de démonstration | G59: Aucune identité, prix ni conditions affichés | H59: 5 | I59: Moyenne | J59: À faire | L59: =IF($B59="","",IF(J59="Complétée",1,IF(J59="Abandonnée",0,IF(K59<>"",K59,IFERROR(VLOOKUP(J59,Parametres!$B$6:$C$12,2,FALSE),0))))) | M59: =IF($B59="","",IF(J59="Abandonnée",0,H59)) | N59: =IF($B59="","",M59*L59) | P59: 46292 | Q59: 46299 | T59: Non | U59: =IF($B59="","",IF(AND(J59<>"Complétée",J59<>"Abandonnée",Q59<>"",TODAY()>Q59),"En retard",""))
B60: V1-055 | C60: V1 | D60: RPS | E60: Démonstration RPS | F60: Journal de démonstration : trace lisible des décisions simulées | G60: Journal consultable pendant la démo | H60: 3 | I60: Basse | J60: À faire | L60: =IF($B60="","",IF(J60="Complétée",1,IF(J60="Abandonnée",0,IF(K60<>"",K60,IFERROR(VLOOKUP(J60,Parametres!$B$6:$C$12,2,FALSE),0))))) | M60: =IF($B60="","",IF(J60="Abandonnée",0,H60)) | N60: =IF($B60="","",M60*L60) | P60: 46293 | Q60: 46298 | T60: Non | U60: =IF($B60="","",IF(AND(J60<>"Complétée",J60<>"Abandonnée",Q60<>"",TODAY()>Q60),"En retard",""))
B61: V1-056 | C61: V1 | D61: RPS | E61: Démonstration RPS | F61: Recette du scénario avec M. Bruno | G61: Validation écrite du déroulé | H61: 1 | I61: Haute | J61: À faire | L61: =IF($B61="","",IF(J61="Complétée",1,IF(J61="Abandonnée",0,IF(K61<>"",K61,IFERROR(VLOOKUP(J61,Parametres!$B$6:$C$12,2,FALSE),0))))) | M61: =IF($B61="","",IF(J61="Abandonnée",0,H61)) | N61: =IF($B61="","",M61*L61) | P61: 46293 | Q61: 46295 | T61: Non | U61: =IF($B61="","",IF(AND(J61<>"Complétée",J61<>"Abandonnée",Q61<>"",TODAY()>Q61),"En retard",""))
B62: V1-057 | C62: V1 | D62: CNX | E62: Deal-Connect (Remo) | F62: Cadrage de l'intégration Remo.co : plan retenu, API, SSO, webhooks, marque blanche | G62: Périmètre d'intégration validé par M. Bruno sur la documentation Remo | H62: 3 | I62: Haute | J62: À faire | L62: =IF($B62="","",IF(J62="Complétée",1,IF(J62="Abandonnée",0,IF(K62<>"",K62,IFERROR(VLOOKUP(J62,Parametres!$B$6:$C$12,2,FALSE),0))))) | M62: =IF($B62="","",IF(J62="Abandonnée",0,H62)) | N62: =IF($B62="","",M62*L62) | P62: 46293 | Q62: 46298 | T62: Oui | U62: =IF($B62="","",IF(AND(J62<>"Complétée",J62<>"Abandonnée",Q62<>"",TODAY()>Q62),"En retard",""))
B63: V1-058 | C63: V1 | D63: CNX | E63: Deal-Connect (Remo) | F63: Connecteur Remo.co : création d'événements, lien d'accès unique, webhooks de présence | G63: Présence remontée et rattachée à l'inscription DealPME | H63: 8 | I63: Haute | J63: En cours | K63: 0.4 | L63: =IF($B63="","",IF(J63="Complétée",1,IF(J63="Abandonnée",0,IF(K63<>"",K63,IFERROR(VLOOKUP(J63,Parametres!$B$6:$C$12,2,FALSE),0))))) | M63: =IF($B63="","",IF(J63="Abandonnée",0,H63)) | N63: =IF($B63="","",M63*L63) | O63: Abdou-Raouf | P63: 46294 | Q63: 46306 | S63: Cadrage Remo.co | T63: Non | U63: =IF($B63="","",IF(AND(J63<>"Complétée",J63<>"Abandonnée",Q63<>"",TODAY()>Q63),"En retard",""))
B64: V1-059 | C64: V1 | D64: CNX | E64: Deal-Connect (Remo) | F64: Inscriptions DEALPME_FIRST : consentement d'échange de contacts, attribution de campagne | G64: Aucun contact échangé sans consentement explicite | H64: 3 | I64: Haute | J64: En cours | K64: 0.5 | L64: =IF($B64="","",IF(J64="Complétée",1,IF(J64="Abandonnée",0,IF(K64<>"",K64,IFERROR(VLOOKUP(J64,Parametres!$B$6:$C$12,2,FALSE),0))))) | M64: =IF($B64="","",IF(J64="Abandonnée",0,H64)) | N64: =IF($B64="","",M64*L64) | O64: Abdou-Raouf | P64: 46295 | Q64: 46300 | T64: Non | U64: =IF($B64="","",IF(AND(J64<>"Complétée",J64<>"Abandonnée",Q64<>"",TODAY()>Q64),"En retard",""))
B65: V1-060 | C65: V1 | D65: CNX | E65: Deal-Connect (Remo) | F65: Écran Deal-Connect V1 : liste des événements, inscription, bouton d'accès Remo | G65: Parcours inscription puis accès en moins de trois clics | H65: 4 | I65: Moyenne | J65: À faire | L65: =IF($B65="","",IF(J65="Complétée",1,IF(J65="Abandonnée",0,IF(K65<>"",K65,IFERROR(VLOOKUP(J65,Parametres!$B$6:$C$12,2,FALSE),0))))) | M65: =IF($B65="","",IF(J65="Abandonnée",0,H65)) | N65: =IF($B65="","",M65*L65) | P65: 46295 | Q65: 46301 | T65: Non | U65: =IF($B65="","",IF(AND(J65<>"Complétée",J65<>"Abandonnée",Q65<>"",TODAY()>Q65),"En retard",""))
B66: V1-061 | C66: V1 | D66: DIA | E66: Deal-Connect (Remo) | F66: Demande de rendez-vous diaspora avec avis transfrontalier, entretien vidéo via Remo après confirmation humaine | G66: Aucune demande sans reconnaissance de l'avis transfrontalier | H66: 4 | I66: Moyenne | J66: En cours | K66: 0.3 | L66: =IF($B66="","",IF(J66="Complétée",1,IF(J66="Abandonnée",0,IF(K66<>"",K66,IFERROR(VLOOKUP(J66,Parametres!$B$6:$C$12,2,FALSE),0))))) | M66: =IF($B66="","",IF(J66="Abandonnée",0,H66)) | N66: =IF($B66="","",M66*L66) | O66: Abdou-Raouf | P66: 46296 | Q66: 46302 | S66: Connecteur Remo.co | T66: Non | U66: =IF($B66="","",IF(AND(J66<>"Complétée",J66<>"Abandonnée",Q66<>"",TODAY()>Q66),"En retard",""))
B67: V1-062 | C67: V1 | D67: TRV | E67: Frontend et design | F67: Intégration du design system (tokens et composants de base issus de la Tranche 3) | G67: Tokens couleurs et typographie conformes à la charte | H67: 5 | I67: Haute | J67: En cours | K67: 0.5 | L67: =IF($B67="","",IF(J67="Complétée",1,IF(J67="Abandonnée",0,IF(K67<>"",K67,IFERROR(VLOOKUP(J67,Parametres!$B$6:$C$12,2,FALSE),0))))) | M67: =IF($B67="","",IF(J67="Abandonnée",0,H67)) | N67: =IF($B67="","",M67*L67) | O67: Abdou-Raouf | P67: 46296 | Q67: 46303 | T67: Non | U67: =IF($B67="","",IF(AND(J67<>"Complétée",J67<>"Abandonnée",Q67<>"",TODAY()>Q67),"En retard",""))
B68: V1-063 | C68: V1 | D68: TRV | E68: Frontend et design | F68: Gabarit applicatif : AppShell, navigation, états vide / chargement / erreur | G68: Chaque écran possède ses trois états | H68: 4 | I68: Haute | J68: En cours | K68: 0.5 | L68: =IF($B68="","",IF(J68="Complétée",1,IF(J68="Abandonnée",0,IF(K68<>"",K68,IFERROR(VLOOKUP(J68,Parametres!$B$6:$C$12,2,FALSE),0))))) | M68: =IF($B68="","",IF(J68="Abandonnée",0,H68)) | N68: =IF($B68="","",M68*L68) | O68: Abdou-Raouf | P68: 46297 | Q68: 46303 | T68: Non | U68: =IF($B68="","",IF(AND(J68<>"Complétée",J68<>"Abandonnée",Q68<>"",TODAY()>Q68),"En retard",""))
B69: V1-064 | C69: V1 | D69: TRV | E69: Frontend et design | F69: Responsive mobile sur les parcours V1 | G69: Aucune casse de mise en page entre 360 et 1920 px | H69: 4 | I69: Moyenne | J69: À faire | L69: =IF($B69="","",IF(J69="Complétée",1,IF(J69="Abandonnée",0,IF(K69<>"",K69,IFERROR(VLOOKUP(J69,Parametres!$B$6:$C$12,2,FALSE),0))))) | M69: =IF($B69="","",IF(J69="Abandonnée",0,H69)) | N69: =IF($B69="","",M69*L69) | P69: 46297 | Q69: 46303 | T69: Non | U69: =IF($B69="","",IF(AND(J69<>"Complétée",J69<>"Abandonnée",Q69<>"",TODAY()>Q69),"En retard",""))
B70: V1-065 | C70: V1 | D70: TRV | E70: Frontend et design | F70: Revue visuelle avec le designer UI/UX | G70: Liste des écarts traitée | H70: 2 | I70: Moyenne | J70: À faire | L70: =IF($B70="","",IF(J70="Complétée",1,IF(J70="Abandonnée",0,IF(K70<>"",K70,IFERROR(VLOOKUP(J70,Parametres!$B$6:$C$12,2,FALSE),0))))) | M70: =IF($B70="","",IF(J70="Abandonnée",0,H70)) | N70: =IF($B70="","",M70*L70) | P70: 46298 | Q70: 46301 | S70: Designer UI/UX confirmé | T70: Non | U70: =IF($B70="","",IF(AND(J70<>"Complétée",J70<>"Abandonnée",Q70<>"",TODAY()>Q70),"En retard",""))
B71: V1-066 | C71: V1 | D71: TRV | E71: QA et livraison | F71: Tests automatisés : unitaires et bout en bout sur les parcours critiques | G71: Couverture des parcours inscription, dossier, publication, certification | H71: 5 | I71: Haute | J71: En cours | K71: 0.35 | L71: =IF($B71="","",IF(J71="Complétée",1,IF(J71="Abandonnée",0,IF(K71<>"",K71,IFERROR(VLOOKUP(J71,Parametres!$B$6:$C$12,2,FALSE),0))))) | M71: =IF($B71="","",IF(J71="Abandonnée",0,H71)) | N71: =IF($B71="","",M71*L71) | O71: Abdou-Raouf | P71: 46308 | Q71: 46310 | T71: Non | U71: =IF($B71="","",IF(AND(J71<>"Complétée",J71<>"Abandonnée",Q71<>"",TODAY()>Q71),"En retard",""))
B72: V1-067 | C72: V1 | D72: TRV | E72: QA et livraison | F72: Tests négatifs : permissions serveur, accès non autorisés, contrôles morts | G72: Aucun contrôle visible sans réaction définie | H72: 3 | I72: Haute | J72: À faire | L72: =IF($B72="","",IF(J72="Complétée",1,IF(J72="Abandonnée",0,IF(K72<>"",K72,IFERROR(VLOOKUP(J72,Parametres!$B$6:$C$12,2,FALSE),0))))) | M72: =IF($B72="","",IF(J72="Abandonnée",0,H72)) | N72: =IF($B72="","",M72*L72) | P72: 46308 | Q72: 46310 | T72: Non | U72: =IF($B72="","",IF(AND(J72<>"Complétée",J72<>"Abandonnée",Q72<>"",TODAY()>Q72),"En retard",""))
B73: V1-068 | C73: V1 | D73: TRV | E73: QA et livraison | F73: Jeu de données de démonstration complet (synthétique, étiqueté) | G73: Aucune donnée réelle, étiquette visible | H73: 3 | I73: Haute | J73: En cours | K73: 0.6 | L73: =IF($B73="","",IF(J73="Complétée",1,IF(J73="Abandonnée",0,IF(K73<>"",K73,IFERROR(VLOOKUP(J73,Parametres!$B$6:$C$12,2,FALSE),0))))) | M73: =IF($B73="","",IF(J73="Abandonnée",0,H73)) | N73: =IF($B73="","",M73*L73) | O73: Abdou-Raouf | P73: 46308 | Q73: 46310 | T73: Non | U73: =IF($B73="","",IF(AND(J73<>"Complétée",J73<>"Abandonnée",Q73<>"",TODAY()>Q73),"En retard",""))
B74: V1-069 | C74: V1 | D74: TRV | E74: QA et livraison | F74: Recette interne et corrections | G74: Zéro anomalie bloquante ouverte | H74: 4 | I74: Haute | J74: À faire | L74: =IF($B74="","",IF(J74="Complétée",1,IF(J74="Abandonnée",0,IF(K74<>"",K74,IFERROR(VLOOKUP(J74,Parametres!$B$6:$C$12,2,FALSE),0))))) | M74: =IF($B74="","",IF(J74="Abandonnée",0,H74)) | N74: =IF($B74="","",M74*L74) | P74: 46308 | Q74: 46310 | T74: Non | U74: =IF($B74="","",IF(AND(J74<>"Complétée",J74<>"Abandonnée",Q74<>"",TODAY()>Q74),"En retard",""))
B75: V1-070 | C75: V1 | D75: TRV | E75: QA et livraison | F75: Documentation développeur et guide de démonstration | G75: Nouvel arrivant opérationnel en une journée | H75: 3 | I75: Moyenne | J75: En cours | K75: 0.6 | L75: =IF($B75="","",IF(J75="Complétée",1,IF(J75="Abandonnée",0,IF(K75<>"",K75,IFERROR(VLOOKUP(J75,Parametres!$B$6:$C$12,2,FALSE),0))))) | M75: =IF($B75="","",IF(J75="Abandonnée",0,H75)) | N75: =IF($B75="","",M75*L75) | O75: Abdou-Raouf | P75: 46308 | Q75: 46310 | T75: Non | U75: =IF($B75="","",IF(AND(J75<>"Complétée",J75<>"Abandonnée",Q75<>"",TODAY()>Q75),"En retard",""))
B76: V1-071 | C76: V1 | D76: TRV | E76: QA et livraison | F76: Préparation de la démonstration du 15/10 (script, environnement, données) | G76: Répétition générale réalisée | H76: 2 | I76: Haute | J76: À faire | L76: =IF($B76="","",IF(J76="Complétée",1,IF(J76="Abandonnée",0,IF(K76<>"",K76,IFERROR(VLOOKUP(J76,Parametres!$B$6:$C$12,2,FALSE),0))))) | M76: =IF($B76="","",IF(J76="Abandonnée",0,H76)) | N76: =IF($B76="","",M76*L76) | P76: 46308 | Q76: 46310 | T76: Non | U76: =IF($B76="","",IF(AND(J76<>"Complétée",J76<>"Abandonnée",Q76<>"",TODAY()>Q76),"En retard",""))
B77: V2-001 | C77: V2 | D77: RPS | E77: Circuit RPS réel | F77: Micro-service RPS indépendant : datastore, API, déploiement séparé | G77: Déployable indépendamment du reste de la plateforme | H77: 6 | I77: Haute | J77: Backlog | L77: =IF($B77="","",IF(J77="Complétée",1,IF(J77="Abandonnée",0,IF(K77<>"",K77,IFERROR(VLOOKUP(J77,Parametres!$B$6:$C$12,2,FALSE),0))))) | M77: =IF($B77="","",IF(J77="Abandonnée",0,H77)) | N77: =IF($B77="","",M77*L77) | P77: 46311 | Q77: 46320 | T77: Non | U77: =IF($B77="","",IF(AND(J77<>"Complétée",J77<>"Abandonnée",Q77<>"",TODAY()>Q77),"En retard",""))
B78: V2-002 | C78: V2 | D78: RPS | E78: Circuit RPS réel | F78: Table Disclosure append-only et compteur par personne (pas par session) | G78: Révocation crée une ligne, ne supprime jamais | H78: 5 | I78: Haute | J78: Backlog | L78: =IF($B78="","",IF(J78="Complétée",1,IF(J78="Abandonnée",0,IF(K78<>"",K78,IFERROR(VLOOKUP(J78,Parametres!$B$6:$C$12,2,FALSE),0))))) | M78: =IF($B78="","",IF(J78="Abandonnée",0,H78)) | N78: =IF($B78="","",M78*L78) | P78: 46313 | Q78: 46320 | T78: Non | U78: =IF($B78="","",IF(AND(J78<>"Complétée",J78<>"Abandonnée",Q78<>"",TODAY()>Q78),"En retard",""))
B79: V2-003 | C79: V2 | D79: RPS | E79: Circuit RPS réel | F79: Graphe de personnes liées (comptées une seule fois) | G79: Deux comptes liés comptent pour une personne | H79: 4 | I79: Haute | J79: Backlog | L79: =IF($B79="","",IF(J79="Complétée",1,IF(J79="Abandonnée",0,IF(K79<>"",K79,IFERROR(VLOOKUP(J79,Parametres!$B$6:$C$12,2,FALSE),0))))) | M79: =IF($B79="","",IF(J79="Abandonnée",0,H79)) | N79: =IF($B79="","",M79*L79) | P79: 46314 | Q79: 46320 | T79: Non | U79: =IF($B79="","",IF(AND(J79<>"Complétée",J79<>"Abandonnée",Q79<>"",TODAY()>Q79),"En retard",""))
B80: V2-004 | C80: V2 | D80: RPS | E80: Circuit RPS réel | F80: Plafond de cercle (défaut 50), seuils 80 % et 100 %, bascule en admission manuelle | G80: Blocage effectif à 100 % (test négatif) | H80: 4 | I80: Haute | J80: Backlog | L80: =IF($B80="","",IF(J80="Complétée",1,IF(J80="Abandonnée",0,IF(K80<>"",K80,IFERROR(VLOOKUP(J80,Parametres!$B$6:$C$12,2,FALSE),0))))) | M80: =IF($B80="","",IF(J80="Abandonnée",0,H80)) | N80: =IF($B80="","",M80*L80) | P80: 46316 | Q80: 46322 | T80: Non | U80: =IF($B80="","",IF(AND(J80<>"Complétée",J80<>"Abandonnée",Q80<>"",TODAY()>Q80),"En retard",""))
B81: V2-005 | C81: V2 | D81: RPS | E81: Circuit RPS réel | F81: Workflow d'admission humaine : file, décision, justification enregistrée | G81: Admission automatique impossible par construction | H81: 6 | I81: Haute | J81: Backlog | L81: =IF($B81="","",IF(J81="Complétée",1,IF(J81="Abandonnée",0,IF(K81<>"",K81,IFERROR(VLOOKUP(J81,Parametres!$B$6:$C$12,2,FALSE),0))))) | M81: =IF($B81="","",IF(J81="Abandonnée",0,H81)) | N81: =IF($B81="","",M81*L81) | P81: 46317 | Q81: 46326 | T81: Non | U81: =IF($B81="","",IF(AND(J81<>"Complétée",J81<>"Abandonnée",Q81<>"",TODAY()>Q81),"En retard",""))
B82: V2-006 | C82: V2 | D82: RPS | E82: Circuit RPS réel | F82: Filtre de communication sortante (permettre, caviarder, bloquer) | G82: Tout message sur un dossier titres passe par le filtre | H82: 5 | I82: Haute | J82: Backlog | L82: =IF($B82="","",IF(J82="Complétée",1,IF(J82="Abandonnée",0,IF(K82<>"",K82,IFERROR(VLOOKUP(J82,Parametres!$B$6:$C$12,2,FALSE),0))))) | M82: =IF($B82="","",IF(J82="Abandonnée",0,H82)) | N82: =IF($B82="","",M82*L82) | P82: 46319 | Q82: 46326 | T82: Non | U82: =IF($B82="","",IF(AND(J82<>"Complétée",J82<>"Abandonnée",Q82<>"",TODAY()>Q82),"En retard",""))
B83: V2-007 | C83: V2 | D83: RPS | E83: Circuit RPS réel | F83: Journal réglementaire haché et export du pack de preuves par dossier | G83: Chaîne de hachage vérifiable, archive signée | H83: 5 | I83: Haute | J83: Backlog | L83: =IF($B83="","",IF(J83="Complétée",1,IF(J83="Abandonnée",0,IF(K83<>"",K83,IFERROR(VLOOKUP(J83,Parametres!$B$6:$C$12,2,FALSE),0))))) | M83: =IF($B83="","",IF(J83="Abandonnée",0,H83)) | N83: =IF($B83="","",M83*L83) | P83: 46320 | Q83: 46327 | T83: Non | U83: =IF($B83="","",IF(AND(J83<>"Complétée",J83<>"Abandonnée",Q83<>"",TODAY()>Q83),"En retard",""))
B84: V2-008 | C84: V2 | D84: RPS | E84: Circuit RPS réel | F84: Allow-list serveur des champs par palier T0 / T1 / T2 | G84: Prix jamais sérialisé sous T2 (test négatif) | H84: 3 | I84: Haute | J84: Backlog | L84: =IF($B84="","",IF(J84="Complétée",1,IF(J84="Abandonnée",0,IF(K84<>"",K84,IFERROR(VLOOKUP(J84,Parametres!$B$6:$C$12,2,FALSE),0))))) | M84: =IF($B84="","",IF(J84="Abandonnée",0,H84)) | N84: =IF($B84="","",M84*L84) | P84: 46322 | Q84: 46327 | T84: Non | U84: =IF($B84="","",IF(AND(J84<>"Complétée",J84<>"Abandonnée",Q84<>"",TODAY()>Q84),"En retard",""))
B85: V2-009 | C85: V2 | D85: RPS | E85: Circuit RPS réel | F85: Écrans admission et cercle (conformité) | G85: Compteur et capacité restante visibles | H85: 2 | I85: Moyenne | J85: Backlog | L85: =IF($B85="","",IF(J85="Complétée",1,IF(J85="Abandonnée",0,IF(K85<>"",K85,IFERROR(VLOOKUP(J85,Parametres!$B$6:$C$12,2,FALSE),0))))) | M85: =IF($B85="","",IF(J85="Abandonnée",0,H85)) | N85: =IF($B85="","",M85*L85) | P85: 46323 | Q85: 46326 | T85: Non | U85: =IF($B85="","",IF(AND(J85<>"Complétée",J85<>"Abandonnée",Q85<>"",TODAY()>Q85),"En retard",""))
B86: V2-010 | C86: V2 | D86: SIG | E86: Signature électronique | F86: Sélection et contractualisation du prestataire PSC accrédité (coordination) | G86: Contrat signé, attestation d'accréditation archivée | H86: 3 | I86: Haute | J86: Backlog | L86: =IF($B86="","",IF(J86="Complétée",1,IF(J86="Abandonnée",0,IF(K86<>"",K86,IFERROR(VLOOKUP(J86,Parametres!$B$6:$C$12,2,FALSE),0))))) | M86: =IF($B86="","",IF(J86="Abandonnée",0,H86)) | N86: =IF($B86="","",M86*L86) | P86: 46323 | Q86: 46328 | T86: Oui | U86: =IF($B86="","",IF(AND(J86<>"Complétée",J86<>"Abandonnée",Q86<>"",TODAY()>Q86),"En retard",""))
B87: V2-011 | C87: V2 | D87: SIG | E87: Signature électronique | F87: Intégration API de signature qualifiée, webhooks à signature vérifiée | G87: Webhook non signé rejeté (test négatif) | H87: 7 | I87: Haute | J87: Backlog | L87: =IF($B87="","",IF(J87="Complétée",1,IF(J87="Abandonnée",0,IF(K87<>"",K87,IFERROR(VLOOKUP(J87,Parametres!$B$6:$C$12,2,FALSE),0))))) | M87: =IF($B87="","",IF(J87="Abandonnée",0,H87)) | N87: =IF($B87="","",M87*L87) | P87: 46324 | Q87: 46334 | S87: Contrat PSC | T87: Non | U87: =IF($B87="","",IF(AND(J87<>"Complétée",J87<>"Abandonnée",Q87<>"",TODAY()>Q87),"En retard",""))
B88: V2-012 | C88: V2 | D88: SIG | E88: Signature électronique | F88: Parcours de repli papier : PDF, contre-signature, vérification CCIT | G88: Un utilisateur refusant la signature électronique n'est pas bloqué | H88: 4 | I88: Haute | J88: Backlog | L88: =IF($B88="","",IF(J88="Complétée",1,IF(J88="Abandonnée",0,IF(K88<>"",K88,IFERROR(VLOOKUP(J88,Parametres!$B$6:$C$12,2,FALSE),0))))) | M88: =IF($B88="","",IF(J88="Abandonnée",0,H88)) | N88: =IF($B88="","",M88*L88) | P88: 46327 | Q88: 46333 | T88: Non | U88: =IF($B88="","",IF(AND(J88<>"Complétée",J88<>"Abandonnée",Q88<>"",TODAY()>Q88),"En retard",""))
B89: V2-013 | C89: V2 | D89: SIG | E89: Signature électronique | F89: SignatureEvidence : hash SHA-256, chaîne de certificats, jeton d'horodatage | G89: Preuve complète stockée pour chaque NDA | H89: 4 | I89: Haute | J89: Backlog | L89: =IF($B89="","",IF(J89="Complétée",1,IF(J89="Abandonnée",0,IF(K89<>"",K89,IFERROR(VLOOKUP(J89,Parametres!$B$6:$C$12,2,FALSE),0))))) | M89: =IF($B89="","",IF(J89="Abandonnée",0,H89)) | N89: =IF($B89="","",M89*L89) | P89: 46328 | Q89: 46334 | T89: Non | U89: =IF($B89="","",IF(AND(J89<>"Complétée",J89<>"Abandonnée",Q89<>"",TODAY()>Q89),"En retard",""))
B90: V2-014 | C90: V2 | D90: SIG | E90: Signature électronique | F90: Intégration archivage électronique accrédité (PSAE) | G90: Référence d'archive stockée sur chaque preuve | H90: 5 | I90: Haute | J90: Backlog | L90: =IF($B90="","",IF(J90="Complétée",1,IF(J90="Abandonnée",0,IF(K90<>"",K90,IFERROR(VLOOKUP(J90,Parametres!$B$6:$C$12,2,FALSE),0))))) | M90: =IF($B90="","",IF(J90="Abandonnée",0,H90)) | N90: =IF($B90="","",M90*L90) | P90: 46329 | Q90: 46336 | T90: Non | U90: =IF($B90="","",IF(AND(J90<>"Complétée",J90<>"Abandonnée",Q90<>"",TODAY()>Q90),"En retard",""))
B91: V2-015 | C91: V2 | D91: SIG | E91: Signature électronique | F91: Écrans NDA : génération, signature, statut | G91: Statut NDA visible côté cédant et investisseur | H91: 2 | I91: Moyenne | J91: Backlog | L91: =IF($B91="","",IF(J91="Complétée",1,IF(J91="Abandonnée",0,IF(K91<>"",K91,IFERROR(VLOOKUP(J91,Parametres!$B$6:$C$12,2,FALSE),0))))) | M91: =IF($B91="","",IF(J91="Abandonnée",0,H91)) | N91: =IF($B91="","",M91*L91) | P91: 46331 | Q91: 46334 | T91: Non | U91: =IF($B91="","",IF(AND(J91<>"Complétée",J91<>"Abandonnée",Q91<>"",TODAY()>Q91),"En retard",""))
B92: V2-016 | C92: V2 | D92: VDR | E92: Data room | F92: Stockage objet chiffré, URLs pré-signées courtes liées à la session | G92: Accès direct hors session refusé | H92: 5 | I92: Haute | J92: Backlog | L92: =IF($B92="","",IF(J92="Complétée",1,IF(J92="Abandonnée",0,IF(K92<>"",K92,IFERROR(VLOOKUP(J92,Parametres!$B$6:$C$12,2,FALSE),0))))) | M92: =IF($B92="","",IF(J92="Abandonnée",0,H92)) | N92: =IF($B92="","",M92*L92) | P92: 46331 | Q92: 46338 | T92: Non | U92: =IF($B92="","",IF(AND(J92<>"Complétée",J92<>"Abandonnée",Q92<>"",TODAY()>Q92),"En retard",""))
B93: V2-017 | C93: V2 | D93: VDR | E93: Data room | F93: Visualiseur rendu serveur, page à page, chargement progressif (3G) | G93: Première page en moins de 6 s sur réseau de référence | H93: 8 | I93: Haute | J93: Backlog | L93: =IF($B93="","",IF(J93="Complétée",1,IF(J93="Abandonnée",0,IF(K93<>"",K93,IFERROR(VLOOKUP(J93,Parametres!$B$6:$C$12,2,FALSE),0))))) | M93: =IF($B93="","",IF(J93="Abandonnée",0,H93)) | N93: =IF($B93="","",M93*L93) | P93: 46333 | Q93: 46345 | T93: Non | U93: =IF($B93="","",IF(AND(J93<>"Complétée",J93<>"Abandonnée",Q93<>"",TODAY()>Q93),"En retard",""))
B94: V2-018 | C94: V2 | D94: VDR | E94: Data room | F94: Filigrane dynamique par page (identité, compte, horodatage, référence du deal) | G94: Chaque page rendue porte le filigrane (test DOC-02) | H94: 5 | I94: Haute | J94: Backlog | L94: =IF($B94="","",IF(J94="Complétée",1,IF(J94="Abandonnée",0,IF(K94<>"",K94,IFERROR(VLOOKUP(J94,Parametres!$B$6:$C$12,2,FALSE),0))))) | M94: =IF($B94="","",IF(J94="Abandonnée",0,H94)) | N94: =IF($B94="","",M94*L94) | P94: 46335 | Q94: 46342 | T94: Non | U94: =IF($B94="","",IF(AND(J94<>"Complétée",J94<>"Abandonnée",Q94<>"",TODAY()>Q94),"En retard",""))
B95: V2-019 | C95: V2 | D95: VDR | E95: Data room | F95: Arborescence OHADA par défaut et gestion des dossiers | G95: Squelette créé automatiquement à l'ouverture | H95: 4 | I95: Moyenne | J95: Backlog | L95: =IF($B95="","",IF(J95="Complétée",1,IF(J95="Abandonnée",0,IF(K95<>"",K95,IFERROR(VLOOKUP(J95,Parametres!$B$6:$C$12,2,FALSE),0))))) | M95: =IF($B95="","",IF(J95="Abandonnée",0,H95)) | N95: =IF($B95="","",M95*L95) | P95: 46337 | Q95: 46343 | T95: Non | U95: =IF($B95="","",IF(AND(J95<>"Complétée",J95<>"Abandonnée",Q95<>"",TODAY()>Q95),"En retard",""))
B96: V2-020 | C96: V2 | D96: VDR | E96: Data room | F96: Permissions par document, téléchargement désactivé par défaut | G96: Téléchargement refusé sans droit explicite (test DOC-01) | H96: 5 | I96: Haute | J96: Backlog | L96: =IF($B96="","",IF(J96="Complétée",1,IF(J96="Abandonnée",0,IF(K96<>"",K96,IFERROR(VLOOKUP(J96,Parametres!$B$6:$C$12,2,FALSE),0))))) | M96: =IF($B96="","",IF(J96="Abandonnée",0,H96)) | N96: =IF($B96="","",M96*L96) | P96: 46338 | Q96: 46345 | T96: Non | U96: =IF($B96="","",IF(AND(J96<>"Complétée",J96<>"Abandonnée",Q96<>"",TODAY()>Q96),"En retard",""))
B97: V2-021 | C97: V2 | D97: VDR | E97: Data room | F97: Grants d'accès scopés avec expiration obligatoire | G97: Accès perpétuel impossible à créer | H97: 4 | I97: Haute | J97: Backlog | L97: =IF($B97="","",IF(J97="Complétée",1,IF(J97="Abandonnée",0,IF(K97<>"",K97,IFERROR(VLOOKUP(J97,Parametres!$B$6:$C$12,2,FALSE),0))))) | M97: =IF($B97="","",IF(J97="Abandonnée",0,H97)) | N97: =IF($B97="","",M97*L97) | P97: 46340 | Q97: 46346 | T97: Non | U97: =IF($B97="","",IF(AND(J97<>"Complétée",J97<>"Abandonnée",Q97<>"",TODAY()>Q97),"En retard",""))
B98: V2-022 | C98: V2 | D98: VDR | E98: Data room | F98: Révocation effective en moins de 60 s avec invalidation des URLs | G98: Test chronométré de révocation | H98: 4 | I98: Haute | J98: Backlog | L98: =IF($B98="","",IF(J98="Complétée",1,IF(J98="Abandonnée",0,IF(K98<>"",K98,IFERROR(VLOOKUP(J98,Parametres!$B$6:$C$12,2,FALSE),0))))) | M98: =IF($B98="","",IF(J98="Abandonnée",0,H98)) | N98: =IF($B98="","",M98*L98) | P98: 46341 | Q98: 46347 | T98: Non | U98: =IF($B98="","",IF(AND(J98<>"Complétée",J98<>"Abandonnée",Q98<>"",TODAY()>Q98),"En retard",""))
B99: V2-023 | C99: V2 | D99: VDR | E99: Data room | F99: Journal DocumentView : qui, quel document, quand, durée, IP | G99: Export du journal par dossier | H99: 4 | I99: Haute | J99: Backlog | L99: =IF($B99="","",IF(J99="Complétée",1,IF(J99="Abandonnée",0,IF(K99<>"",K99,IFERROR(VLOOKUP(J99,Parametres!$B$6:$C$12,2,FALSE),0))))) | M99: =IF($B99="","",IF(J99="Abandonnée",0,H99)) | N99: =IF($B99="","",M99*L99) | P99: 46342 | Q99: 46348 | T99: Non | U99: =IF($B99="","",IF(AND(J99<>"Complétée",J99<>"Abandonnée",Q99<>"",TODAY()>Q99),"En retard",""))
... B112: V3-004 | C112: V3 | D112: LEG | E112: LegalTech OHADA | F112: Liaison avec transferRestrictions : alertes clauses d'agrément et de préemption | G112: Alerte affichée dès qu'une restriction existe | H112: 3 | I112: Moyenne | J112: Backlog | L112: =IF($B112="","",IF(J112="Complétée",1,IF(J112="Abandonnée",0,IF(K112<>"",K112,IFERROR(VLOOKUP(J112,Parametres!$B$6:$C$12,2,FALSE),0))))) | M112: =IF($B112="","",IF(J112="Abandonnée",0,H112)) | N112: =IF($B112="","",M112*L112) | P112: 46374 | Q112: 46379 | T112: Non | U112: =IF($B112="","",IF(AND(J112<>"Complétée",J112<>"Abandonnée",Q112<>"",TODAY()>Q112),"En retard",""))
B113: V3-005 | C113: V3 | D113: LEG | E113: Conformité fiscale | F113: Intégration du module fiscal partenaire (simulation, attestation) derrière drapeau | G113: Panne partenaire ne produit jamais une fausse attestation | H113: 6 | I113: Moyenne | J113: Backlog | L113: =IF($B113="","",IF(J113="Complétée",1,IF(J113="Abandonnée",0,IF(K113<>"",K113,IFERROR(VLOOKUP(J113,Parametres!$B$6:$C$12,2,FALSE),0))))) | M113: =IF($B113="","",IF(J113="Abandonnée",0,H113)) | N113: =IF($B113="","",M113*L113) | P113: 46375 | Q113: 46384 | S113: Partenaire fiscal confirmé | T113: Non | U113: =IF($B113="","",IF(AND(J113<>"Complétée",J113<>"Abandonnée",Q113<>"",TODAY()>Q113),"En retard",""))
B114: V3-006 | C114: V3 | D114: LEG | E114: LegalTech OHADA | F114: Écrans LegalTech | G114: Quota de documents par palier respecté | H114: 2 | I114: Moyenne | J114: Backlog | L114: =IF($B114="","",IF(J114="Complétée",1,IF(J114="Abandonnée",0,IF(K114<>"",K114,IFERROR(VLOOKUP(J114,Parametres!$B$6:$C$12,2,FALSE),0))))) | M114: =IF($B114="","",IF(J114="Abandonnée",0,H114)) | N114: =IF($B114="","",M114*L114) | P114: 46377 | Q114: 46380 | T114: Non | U114: =IF($B114="","",IF(AND(J114<>"Complétée",J114<>"Abandonnée",Q114<>"",TODAY()>Q114),"En retard",""))
...

Sheet Equipe
B2: Équipe projet
B3: Chaque développeur s'inscrit ici (colonnes jaunes). Son nom devient alors sélectionnable dans la colonne Responsable de l'onglet Taches. Charges et avancement calculés.
B5: Nom complet | C5: Rôle | D5: Organisation | E5: Contact | F5: Disponibilité | G5: Arrivée | H5: Actif | I5: Tâches assignées | J5: Charge assignée (j/p) | K5: Charge réalisée (j/p) | L5: Avancement | M5: En cours | N5: Bloquées | O5: En retard | P5: Complétées | Q5: Charge restante (j/p) | R5: Commentaire
B6: Abdou-Raouf | C6: Chef de projet / architecte | D6: DealPME | F6: 1 | G6: 46274 | H6: Oui | I6: =IF($B6="","",COUNTIFS(Taches!$O$6:$O$325,$B6,Taches!$J$6:$J$325,"<>Abandonnée")) | J6: =IF($B6="","",SUMIF(Taches!$O$6:$O$325,$B6,Taches!$M$6:$M$325)) | K6: =IF($B6="","",SUMIF(Taches!$O$6:$O$325,$B6,Taches!$N$6:$N$325)) | L6: =IF(OR($B6="",J6=0),"",K6/J6) | M6: =IF($B6="","",COUNTIFS(Taches!$O$6:$O$325,$B6,Taches!$J$6:$J$325,"En cours")+COUNTIFS(Taches!$O$6:$O$325,$B6,Taches!$J$6:$J$325,"En revue")) | N6: =IF($B6="","",COUNTIFS(Taches!$O$6:$O$325,$B6,Taches!$J$6:$J$325,"Bloquée")) | O6: =IF($B6="","",COUNTIFS(Taches!$O$6:$O$325,$B6,Taches!$U$6:$U$325,"En retard")) | P6: =IF($B6="","",COUNTIFS(Taches!$O$6:$O$325,$B6,Taches!$J$6:$J$325,"Complétée")) | Q6: =IF($B6="","",J6-K6) | R6: Pilotage, architecture, revue de code
I7: =IF($B7="","",COUNTIFS(Taches!$O$6:$O$325,$B7,Taches!$J$6:$J$325,"<>Abandonnée")) | J7: =IF($B7="","",SUMIF(Taches!$O$6:$O$325,$B7,Taches!$M$6:$M$325)) | K7: =IF($B7="","",SUMIF(Taches!$O$6:$O$325,$B7,Taches!$N$6:$N$325)) | L7: =IF(OR($B7="",J7=0),"",K7/J7) | M7: =IF($B7="","",COUNTIFS(Taches!$O$6:$O$325,$B7,Taches!$J$6:$J$325,"En cours")+COUNTIFS(Taches!$O$6:$O$325,$B7,Taches!$J$6:$J$325,"En revue")) | N7: =IF($B7="","",COUNTIFS(Taches!$O$6:$O$325,$B7,Taches!$J$6:$J$325,"Bloquée")) | O7: =IF($B7="","",COUNTIFS(Taches!$O$6:$O$325,$B7,Taches!$U$6:$U$325,"En retard")) | P7: =IF($B7="","",COUNTIFS(Taches!$O$6:$O$325,$B7,Taches!$J$6:$J$325,"Complétée")) | Q7: =IF($B7="","",J7-K7)
I8: =IF($B8="","",COUNTIFS(Taches!$O$6:$O$325,$B8,Taches!$J$6:$J$325,"<>Abandonnée")) | J8: =IF($B8="","",SUMIF(Taches!$O$6:$O$325,$B8,Taches!$M$6:$M$325)) | K8: =IF($B8="","",SUMIF(Taches!$O$6:$O$325,$B8,Taches!$N$6:$N$325)) | L8: =IF(OR($B8="",J8=0),"",K8/J8) | M8: =IF($B8="","",COUNTIFS(Taches!$O$6:$O$325,$B8,Taches!$J$6:$J$325,"En cours")+COUNTIFS(Taches!$O$6:$O$325,$B8,Taches!$J$6:$J$325,"En revue")) | N8: =IF($B8="","",COUNTIFS(Taches!$O$6:$O$325,$B8,Taches!$J$6:$J$325,"Bloquée")) | O8: =IF($B8="","",COUNTIFS(Taches!$O$6:$O$325,$B8,Taches!$U$6:$U$325,"En retard")) | P8: =IF($B8="","",COUNTIFS(Taches!$O$6:$O$325,$B8,Taches!$J$6:$J$325,"Complétée")) | Q8: =IF($B8="","",J8-K8)
I9: =IF($B9="","",COUNTIFS(Taches!$O$6:$O$325,$B9,Taches!$J$6:$J$325,"<>Abandonnée")) | J9: =IF($B9="","",SUMIF(Taches!$O$6:$O$325,$B9,Taches!$M$6:$M$325)) | K9: =IF($B9="","",SUMIF(Taches!$O$6:$O$325,$B9,Taches!$N$6:$N$325)) | L9: =IF(OR($B9="",J9=0),"",K9/J9) | M9: =IF($B9="","",COUNTIFS(Taches!$O$6:$O$325,$B9,Taches!$J$6:$J$325,"En cours")+COUNTIFS(Taches!$O$6:$O$325,$B9,Taches!$J$6:$J$325,"En revue")) | N9: =IF($B9="","",COUNTIFS(Taches!$O$6:$O$325,$B9,Taches!$J$6:$J$325,"Bloquée")) | O9: =IF($B9="","",COUNTIFS(Taches!$O$6:$O$325,$B9,Taches!$U$6:$U$325,"En retard")) | P9: =IF($B9="","",COUNTIFS(Taches!$O$6:$O$325,$B9,Taches!$J$6:$J$325,"Complétée")) | Q9: =IF($B9="","",J9-K9)
I10: =IF($B10="","",COUNTIFS(Taches!$O$6:$O$325,$B10,Taches!$J$6:$J$325,"<>Abandonnée")) | J10: =IF($B10="","",SUMIF(Taches!$O$6:$O$325,$B10,Taches!$M$6:$M$325)) | K10: =IF($B10="","",SUMIF(Taches!$O$6:$O$325,$B10,Taches!$N$6:$N$325)) | L10: =IF(OR($B10="",J10=0),"",K10/J10) | M10: =IF($B10="","",COUNTIFS(Taches!$O$6:$O$325,$B10,Taches!$J$6:$J$325,"En cours")+COUNTIFS(Taches!$O$6:$O$325,$B10,Taches!$J$6:$J$325,"En revue")) | N10: =IF($B10="","",COUNTIFS(Taches!$O$6:$O$325,$B10,Taches!$J$6:$J$325,"Bloquée")) | O10: =IF($B10="","",COUNTIFS(Taches!$O$6:$O$325,$B10,Taches!$U$6:$U$325,"En retard")) | P10: =IF($B10="","",COUNTIFS(Taches!$O$6:$O$325,$B10,Taches!$J$6:$J$325,"Complétée")) | Q10: =IF($B10="","",J10-K10)
I11: =IF($B11="","",COUNTIFS(Taches!$O$6:$O$325,$B11,Taches!$J$6:$J$325,"<>Abandonnée")) | J11: =IF($B11="","",SUMIF(Taches!$O$6:$O$325,$B11,Taches!$M$6:$M$325)) | K11: =IF($B11="","",SUMIF(Taches!$O$6:$O$325,$B11,Taches!$N$6:$N$325)) | L11: =IF(OR($B11="",J11=0),"",K11/J11) | M11: =IF($B11="","",COUNTIFS(Taches!$O$6:$O$325,$B11,Taches!$J$6:$J$325,"En cours")+COUNTIFS(Taches!$O$6:$O$325,$B11,Taches!$J$6:$J$325,"En revue")) | N11: =IF($B11="","",COUNTIFS(Taches!$O$6:$O$325,$B11,Taches!$J$6:$J$325,"Bloquée")) | O11: =IF($B11="","",COUNTIFS(Taches!$O$6:$O$325,$B11,Taches!$U$6:$U$325,"En retard")) | P11: =IF($B11="","",COUNTIFS(Taches!$O$6:$O$325,$B11,Taches!$J$6:$J$325,"Complétée")) | Q11: =IF($B11="","",J11-K11)
I12: =IF($B12="","",COUNTIFS(Taches!$O$6:$O$325,$B12,Taches!$J$6:$J$325,"<>Abandonnée")) | J12: =IF($B12="","",SUMIF(Taches!$O$6:$O$325,$B12,Taches!$M$6:$M$325)) | K12: =IF($B12="","",SUMIF(Taches!$O$6:$O$325,$B12,Taches!$N$6:$N$325)) | L12: =IF(OR($B12="",J12=0),"",K12/J12) | M12: =IF($B12="","",COUNTIFS(Taches!$O$6:$O$325,$B12,Taches!$J$6:$J$325,"En cours")+COUNTIFS(Taches!$O$6:$O$325,$B12,Taches!$J$6:$J$325,"En revue")) | N12: =IF($B12="","",COUNTIFS(Taches!$O$6:$O$325,$B12,Taches!$J$6:$J$325,"Bloquée")) | O12: =IF($B12="","",COUNTIFS(Taches!$O$6:$O$325,$B12,Taches!$U$6:$U$325,"En retard")) | P12: =IF($B12="","",COUNTIFS(Taches!$O$6:$O$325,$B12,Taches!$J$6:$J$325,"Complétée")) | Q12: =IF($B12="","",J12-K12)
I13: =IF($B13="","",COUNTIFS(Taches!$O$6:$O$325,$B13,Taches!$J$6:$J$325,"<>Abandonnée")) | J13: =IF($B13="","",SUMIF(Taches!$O$6:$O$325,$B13,Taches!$M$6:$M$325)) | K13: =IF($B13="","",SUMIF(Taches!$O$6:$O$325,$B13,Taches!$N$6:$N$325)) | L13: =IF(OR($B13="",J13=0),"",K13/J13) | M13: =IF($B13="","",COUNTIFS(Taches!$O$6:$O$325,$B13,Taches!$J$6:$J$325,"En cours")+COUNTIFS(Taches!$O$6:$O$325,$B13,Taches!$J$6:$J$325,"En revue")) | N13: =IF($B13="","",COUNTIFS(Taches!$O$6:$O$325,$B13,Taches!$J$6:$J$325,"Bloquée")) | O13: =IF($B13="","",COUNTIFS(Taches!$O$6:$O$325,$B13,Taches!$U$6:$U$325,"En retard")) | P13: =IF($B13="","",COUNTIFS(Taches!$O$6:$O$325,$B13,Taches!$J$6:$J$325,"Complétée")) | Q13: =IF($B13="","",J13-K13)
I14: =IF($B14="","",COUNTIFS(Taches!$O$6:$O$325,$B14,Taches!$J$6:$J$325,"<>Abandonnée")) | J14: =IF($B14="","",SUMIF(Taches!$O$6:$O$325,$B14,Taches!$M$6:$M$325)) | K14: =IF($B14="","",SUMIF(Taches!$O$6:$O$325,$B14,Taches!$N$6:$N$325)) | L14: =IF(OR($B14="",J14=0),"",K14/J14) | M14: =IF($B14="","",COUNTIFS(Taches!$O$6:$O$325,$B14,Taches!$J$6:$J$325,"En cours")+COUNTIFS(Taches!$O$6:$O$325,$B14,Taches!$J$6:$J$325,"En revue")) | N14: =IF($B14="","",COUNTIFS(Taches!$O$6:$O$325,$B14,Taches!$J$6:$J$325,"Bloquée")) | O14: =IF($B14="","",COUNTIFS(Taches!$O$6:$O$325,$B14,Taches!$U$6:$U$325,"En retard")) | P14: =IF($B14="","",COUNTIFS(Taches!$O$6:$O$325,$B14,Taches!$J$6:$J$325,"Complétée")) | Q14: =IF($B14="","",J14-K14)
I15: =IF($B15="","",COUNTIFS(Taches!$O$6:$O$325,$B15,Taches!$J$6:$J$325,"<>Abandonnée")) | J15: =IF($B15="","",SUMIF(Taches!$O$6:$O$325,$B15,Taches!$M$6:$M$325)) | K15: =IF($B15="","",SUMIF(Taches!$O$6:$O$325,$B15,Taches!$N$6:$N$325)) | L15: =IF(OR($B15="",J15=0),"",K15/J15) | M15: =IF($B15="","",COUNTIFS(Taches!$O$6:$O$325,$B15,Taches!$J$6:$J$325,"En cours")+COUNTIFS(Taches!$O$6:$O$325,$B15,Taches!$J$6:$J$325,"En revue")) | N15: =IF($B15="","",COUNTIFS(Taches!$O$6:$O$325,$B15,Taches!$J$6:$J$325,"Bloquée")) | O15: =IF($B15="","",COUNTIFS(Taches!$O$6:$O$325,$B15,Taches!$U$6:$U$325,"En retard")) | P15: =IF($B15="","",COUNTIFS(Taches!$O$6:$O$325,$B15,Taches!$J$6:$J$325,"Complétée")) | Q15: =IF($B15="","",J15-K15)
I16: =IF($B16="","",COUNTIFS(Taches!$O$6:$O$325,$B16,Taches!$J$6:$J$325,"<>Abandonnée")) | J16: =IF($B16="","",SUMIF(Taches!$O$6:$O$325,$B16,Taches!$M$6:$M$325)) | K16: =IF($B16="","",SUMIF(Taches!$O$6:$O$325,$B16,Taches!$N$6:$N$325)) | L16: =IF(OR($B16="",J16=0),"",K16/J16) | M16: =IF($B16="","",COUNTIFS(Taches!$O$6:$O$325,$B16,Taches!$J$6:$J$325,"En cours")+COUNTIFS(Taches!$O$6:$O$325,$B16,Taches!$J$6:$J$325,"En revue")) | N16: =IF($B16="","",COUNTIFS(Taches!$O$6:$O$325,$B16,Taches!$J$6:$J$325,"Bloquée")) | O16: =IF($B16="","",COUNTIFS(Taches!$O$6:$O$325,$B16,Taches!$U$6:$U$325,"En retard")) | P16: =IF($B16="","",COUNTIFS(Taches!$O$6:$O$325,$B16,Taches!$J$6:$J$325,"Complétée")) | Q16: =IF($B16="","",J16-K16)
I17: =IF($B17="","",COUNTIFS(Taches!$O$6:$O$325,$B17,Taches!$J$6:$J$325,"<>Abandonnée")) | J17: =IF($B17="","",SUMIF(Taches!$O$6:$O$325,$B17,Taches!$M$6:$M$325)) | K17: =IF($B17="","",SUMIF(Taches!$O$6:$O$325,$B17,Taches!$N$6:$N$325)) | L17: =IF(OR($B17="",J17=0),"",K17/J17) | M17: =IF($B17="","",COUNTIFS(Taches!$O$6:$O$325,$B17,Taches!$J$6:$J$325,"En cours")+COUNTIFS(Taches!$O$6:$O$325,$B17,Taches!$J$6:$J$325,"En revue")) | N17: =IF($B17="","",COUNTIFS(Taches!$O$6:$O$325,$B17,Taches!$J$6:$J$325,"Bloquée")) | O17: =IF($B17="","",COUNTIFS(Taches!$O$6:$O$325,$B17,Taches!$U$6:$U$325,"En retard")) | P17: =IF($B17="","",COUNTIFS(Taches!$O$6:$O$325,$B17,Taches!$J$6:$J$325,"Complétée")) | Q17: =IF($B17="","",J17-K17)
I18: =IF($B18="","",COUNTIFS(Taches!$O$6:$O$325,$B18,Taches!$J$6:$J$325,"<>Abandonnée")) | J18: =IF($B18="","",SUMIF(Taches!$O$6:$O$325,$B18,Taches!$M$6:$M$325)) | K18: =IF($B18="","",SUMIF(Taches!$O$6:$O$325,$B18,Taches!$N$6:$N$325)) | L18: =IF(OR($B18="",J18=0),"",K18/J18) | M18: =IF($B18="","",COUNTIFS(Taches!$O$6:$O$325,$B18,Taches!$J$6:$J$325,"En cours")+COUNTIFS(Taches!$O$6:$O$325,$B18,Taches!$J$6:$J$325,"En revue")) | N18: =IF($B18="","",COUNTIFS(Taches!$O$6:$O$325,$B18,Taches!$J$6:$J$325,"Bloquée")) | O18: =IF($B18="","",COUNTIFS(Taches!$O$6:$O$325,$B18,Taches!$U$6:$U$325,"En retard")) | P18: =IF($B18="","",COUNTIFS(Taches!$O$6:$O$325,$B18,Taches!$J$6:$J$325,"Complétée")) | Q18: =IF($B18="","",J18-K18)
... I45: =IF($B45="","",COUNTIFS(Taches!$O$6:$O$325,$B45,Taches!$J$6:$J$325,"<>Abandonnée")) | J45: =IF($B45="","",SUMIF(Taches!$O$6:$O$325,$B45,Taches!$M$6:$M$325)) | K45: =IF($B45="","",SUMIF(Taches!$O$6:$O$325,$B45,Taches!$N$6:$N$325)) | L45: =IF(OR($B45="",J45=0),"",K45/J45) | M45: =IF($B45="","",COUNTIFS(Taches!$O$6:$O$325,$B45,Taches!$J$6:$J$325,"En cours")+COUNTIFS(Taches!$O$6:$O$325,$B45,Taches!$J$6:$J$325,"En revue")) | N45: =IF($B45="","",COUNTIFS(Taches!$O$6:$O$325,$B45,Taches!$J$6:$J$325,"Bloquée")) | O45: =IF($B45="","",COUNTIFS(Taches!$O$6:$O$325,$B45,Taches!$U$6:$U$325,"En retard")) | P45: =IF($B45="","",COUNTIFS(Taches!$O$6:$O$325,$B45,Taches!$J$6:$J$325,"Complétée")) | Q45: =IF($B45="","",J45-K45)
B46: Total équipe | I46: =SUM(I6:I45) | J46: =SUM(J6:J45) | K46: =SUM(K6:K45) | L46: =IF(J46=0,0,K46/J46) | M46: =SUM(M6:M45) | N46: =SUM(N6:N45) | O46: =SUM(O6:O45) | P46: =SUM(P6:P45) | Q46: =SUM(Q6:Q45)
B48: Tâches sans responsable | C48: =COUNTIFS(Taches!$B$6:$B$325,"<>",Taches!$O$6:$O$325,"",Taches!$J$6:$J$325,"<>Abandonnée")
B49: Charge non assignée (j/p) | C49: =SUMIFS(Taches!$M$6:$M$325,Taches!$O$6:$O$325,"",Taches!$J$6:$J$325,"<>Abandonnée")

Sheet Modules
B2: Modules fonctionnels
B3: Avancement calculé automatiquement depuis les tâches (pondéré par la charge). Seules les colonnes Responsable et Commentaire se saisissent.
B5: Code | C5: Module | D5: Catégorie | E5: Processus liés | F5: Version cible | G5: Charge (j/p) | H5: Réalisé (j/p) | I5: Avancement | J5: Tâches | K5: Faites | L5: En cours | M5: Bloquées | N5: En retard | O5: État | P5: Responsable | Q5: Commentaire
B6: FOND | C6: Fondations : modèle de données et bifurcation actif / titre | D6: Socle V0 | E6: - | F6: V1 | G6: =SUMIF(Taches!$D$6:$D$325,$B6,Taches!$M$6:$M$325) | H6: =SUMIF(Taches!$D$6:$D$325,$B6,Taches!$N$6:$N$325) | I6: =IF(G6=0,0,H6/G6) | J6: =COUNTIFS(Taches!$D$6:$D$325,$B6,Taches!$J$6:$J$325,"<>Annulé",Taches!$B$6:$B$325,"<>") | K6: =COUNTIFS(Taches!$D$6:$D$325,$B6,Taches!$J$6:$J$325,"Complétée") | L6: =COUNTIFS(Taches!$D$6:$D$325,$B6,Taches!$J$6:$J$325,"En cours")+COUNTIFS(Taches!$D$6:$D$325,$B6,Taches!$J$6:$J$325,"En revue") | M6: =COUNTIFS(Taches!$D$6:$D$325,$B6,Taches!$J$6:$J$325,"Bloquée") | N6: =COUNTIFS(Taches!$D$6:$D$325,$B6,Taches!$U$6:$U$325,"En retard") | O6: =IF(J6=0,"Sans tâche",IF(I6>=0.999,"Terminé",IF(M6>0,"Bloqué (partiel)",IF(I6=0,"Non démarré","En cours")))) | Q6: Conditionne tous les autres modules
B7: TRV | C7: Transverse technique : infra, CI, design system, QA | D7: Socle V0 | E7: - | F7: V1 | G7: =SUMIF(Taches!$D$6:$D$325,$B7,Taches!$M$6:$M$325) | H7: =SUMIF(Taches!$D$6:$D$325,$B7,Taches!$N$6:$N$325) | I7: =IF(G7=0,0,H7/G7) | J7: =COUNTIFS(Taches!$D$6:$D$325,$B7,Taches!$J$6:$J$325,"<>Annulé",Taches!$B$6:$B$325,"<>") | K7: =COUNTIFS(Taches!$D$6:$D$325,$B7,Taches!$J$6:$J$325,"Complétée") | L7: =COUNTIFS(Taches!$D$6:$D$325,$B7,Taches!$J$6:$J$325,"En cours")+COUNTIFS(Taches!$D$6:$D$325,$B7,Taches!$J$6:$J$325,"En revue") | M7: =COUNTIFS(Taches!$D$6:$D$325,$B7,Taches!$J$6:$J$325,"Bloquée") | N7: =COUNTIFS(Taches!$D$6:$D$325,$B7,Taches!$U$6:$U$325,"En retard") | O7: =IF(J7=0,"Sans tâche",IF(I7>=0.999,"Terminé",IF(M7>0,"Bloqué (partiel)",IF(I7=0,"Non démarré","En cours")))) | Q7: Charge répartie sur chaque version
B8: IDN | C8: Identité, abonnement et facturation | D8: Socle V0 | E8: P08 | F8: V1 | G8: =SUMIF(Taches!$D$6:$D$325,$B8,Taches!$M$6:$M$325) | H8: =SUMIF(Taches!$D$6:$D$325,$B8,Taches!$N$6:$N$325) | I8: =IF(G8=0,0,H8/G8) | J8: =COUNTIFS(Taches!$D$6:$D$325,$B8,Taches!$J$6:$J$325,"<>Annulé",Taches!$B$6:$B$325,"<>") | K8: =COUNTIFS(Taches!$D$6:$D$325,$B8,Taches!$J$6:$J$325,"Complétée") | L8: =COUNTIFS(Taches!$D$6:$D$325,$B8,Taches!$J$6:$J$325,"En cours")+COUNTIFS(Taches!$D$6:$D$325,$B8,Taches!$J$6:$J$325,"En revue") | M8: =COUNTIFS(Taches!$D$6:$D$325,$B8,Taches!$J$6:$J$325,"Bloquée") | N8: =COUNTIFS(Taches!$D$6:$D$325,$B8,Taches!$U$6:$U$325,"En retard") | O8: =IF(J8=0,"Sans tâche",IF(I8>=0.999,"Terminé",IF(M8>0,"Bloqué (partiel)",IF(I8=0,"Non démarré","En cours")))) | Q8: KYC documentaire uniquement, pas de biométrie
B9: GOV | C9: Console institutionnelle CCI-Togo et gouvernance | D9: Socle V0 | E9: P22 | F9: V1 | G9: =SUMIF(Taches!$D$6:$D$325,$B9,Taches!$M$6:$M$325) | H9: =SUMIF(Taches!$D$6:$D$325,$B9,Taches!$N$6:$N$325) | I9: =IF(G9=0,0,H9/G9) | J9: =COUNTIFS(Taches!$D$6:$D$325,$B9,Taches!$J$6:$J$325,"<>Annulé",Taches!$B$6:$B$325,"<>") | K9: =COUNTIFS(Taches!$D$6:$D$325,$B9,Taches!$J$6:$J$325,"Complétée") | L9: =COUNTIFS(Taches!$D$6:$D$325,$B9,Taches!$J$6:$J$325,"En cours")+COUNTIFS(Taches!$D$6:$D$325,$B9,Taches!$J$6:$J$325,"En revue") | M9: =COUNTIFS(Taches!$D$6:$D$325,$B9,Taches!$J$6:$J$325,"Bloquée") | N9: =COUNTIFS(Taches!$D$6:$D$325,$B9,Taches!$U$6:$U$325,"En retard") | O9: =IF(J9=0,"Sans tâche",IF(I9>=0.999,"Terminé",IF(M9>0,"Bloqué (partiel)",IF(I9=0,"Non démarré","En cours")))) | Q9: Aucun import de la base des membres
B10: CCI | C10: Deal-Ready : certification CCI-Togo | D10: Socle V0 | E10: P06 | F10: V1 | G10: =SUMIF(Taches!$D$6:$D$325,$B10,Taches!$M$6:$M$325) | H10: =SUMIF(Taches!$D$6:$D$325,$B10,Taches!$N$6:$N$325) | I10: =IF(G10=0,0,H10/G10) | J10: =COUNTIFS(Taches!$D$6:$D$325,$B10,Taches!$J$6:$J$325,"<>Annulé",Taches!$B$6:$B$325,"<>") | K10: =COUNTIFS(Taches!$D$6:$D$325,$B10,Taches!$J$6:$J$325,"Complétée") | L10: =COUNTIFS(Taches!$D$6:$D$325,$B10,Taches!$J$6:$J$325,"En cours")+COUNTIFS(Taches!$D$6:$D$325,$B10,Taches!$J$6:$J$325,"En revue") | M10: =COUNTIFS(Taches!$D$6:$D$325,$B10,Taches!$J$6:$J$325,"Bloquée") | N10: =COUNTIFS(Taches!$D$6:$D$325,$B10,Taches!$U$6:$U$325,"En retard") | O10: =IF(J10=0,"Sans tâche",IF(I10>=0.999,"Terminé",IF(M10>0,"Bloqué (partiel)",IF(I10=0,"Non démarré","En cours")))) | Q10: Décision nominative, jamais automatique
B11: MKT | C11: Pass Transmission : dossier cédant, marketplace, évaluation indicative | D11: Socle V0 | E11: P04, P05, P09 | F11: V1 | G11: =SUMIF(Taches!$D$6:$D$325,$B11,Taches!$M$6:$M$325) | H11: =SUMIF(Taches!$D$6:$D$325,$B11,Taches!$N$6:$N$325) | I11: =IF(G11=0,0,H11/G11) | J11: =COUNTIFS(Taches!$D$6:$D$325,$B11,Taches!$J$6:$J$325,"<>Annulé",Taches!$B$6:$B$325,"<>") | K11: =COUNTIFS(Taches!$D$6:$D$325,$B11,Taches!$J$6:$J$325,"Complétée") | L11: =COUNTIFS(Taches!$D$6:$D$325,$B11,Taches!$J$6:$J$325,"En cours")+COUNTIFS(Taches!$D$6:$D$325,$B11,Taches!$J$6:$J$325,"En revue") | M11: =COUNTIFS(Taches!$D$6:$D$325,$B11,Taches!$J$6:$J$325,"Bloquée") | N11: =COUNTIFS(Taches!$D$6:$D$325,$B11,Taches!$U$6:$U$325,"En retard") | O11: =IF(J11=0,"Sans tâche",IF(I11>=0.999,"Terminé",IF(M11>0,"Bloqué (partiel)",IF(I11=0,"Non démarré","En cours")))) | Q11: V1 = actifs uniquement
B12: RPS | C12: Regulatory Perimeter Service : divulgation T0/T1/T2 | D12: Socle V0 | E12: P07, P10 | F12: V1 (démo) / V2 (réel) | G12: =SUMIF(Taches!$D$6:$D$325,$B12,Taches!$M$6:$M$325) | H12: =SUMIF(Taches!$D$6:$D$325,$B12,Taches!$N$6:$N$325) | I12: =IF(G12=0,0,H12/G12) | J12: =COUNTIFS(Taches!$D$6:$D$325,$B12,Taches!$J$6:$J$325,"<>Annulé",Taches!$B$6:$B$325,"<>") | K12: =COUNTIFS(Taches!$D$6:$D$325,$B12,Taches!$J$6:$J$325,"Complétée") | L12: =COUNTIFS(Taches!$D$6:$D$325,$B12,Taches!$J$6:$J$325,"En cours")+COUNTIFS(Taches!$D$6:$D$325,$B12,Taches!$J$6:$J$325,"En revue") | M12: =COUNTIFS(Taches!$D$6:$D$325,$B12,Taches!$J$6:$J$325,"Bloquée") | N12: =COUNTIFS(Taches!$D$6:$D$325,$B12,Taches!$U$6:$U$325,"En retard") | O12: =IF(J12=0,"Sans tâche",IF(I12>=0.999,"Terminé",IF(M12>0,"Bloqué (partiel)",IF(I12=0,"Non démarré","En cours")))) | Q12: Différenciateur central
B13: SIG | C13: Signature électronique et preuve | D13: Partenaire-dépendant | E13: P11 | F13: V2 | G13: =SUMIF(Taches!$D$6:$D$325,$B13,Taches!$M$6:$M$325) | H13: =SUMIF(Taches!$D$6:$D$325,$B13,Taches!$N$6:$N$325) | I13: =IF(G13=0,0,H13/G13) | J13: =COUNTIFS(Taches!$D$6:$D$325,$B13,Taches!$J$6:$J$325,"<>Annulé",Taches!$B$6:$B$325,"<>") | K13: =COUNTIFS(Taches!$D$6:$D$325,$B13,Taches!$J$6:$J$325,"Complétée") | L13: =COUNTIFS(Taches!$D$6:$D$325,$B13,Taches!$J$6:$J$325,"En cours")+COUNTIFS(Taches!$D$6:$D$325,$B13,Taches!$J$6:$J$325,"En revue") | M13: =COUNTIFS(Taches!$D$6:$D$325,$B13,Taches!$J$6:$J$325,"Bloquée") | N13: =COUNTIFS(Taches!$D$6:$D$325,$B13,Taches!$U$6:$U$325,"En retard") | O13: =IF(J13=0,"Sans tâche",IF(I13>=0.999,"Terminé",IF(M13>0,"Bloqué (partiel)",IF(I13=0,"Non démarré","En cours")))) | Q13: Prestataire PSC accrédité ARCEP
B14: VDR | C14: Data room et questions-réponses | D14: Socle V0 | E14: P12 | F14: V2 | G14: =SUMIF(Taches!$D$6:$D$325,$B14,Taches!$M$6:$M$325) | H14: =SUMIF(Taches!$D$6:$D$325,$B14,Taches!$N$6:$N$325) | I14: =IF(G14=0,0,H14/G14) | J14: =COUNTIFS(Taches!$D$6:$D$325,$B14,Taches!$J$6:$J$325,"<>Annulé",Taches!$B$6:$B$325,"<>") | K14: =COUNTIFS(Taches!$D$6:$D$325,$B14,Taches!$J$6:$J$325,"Complétée") | L14: =COUNTIFS(Taches!$D$6:$D$325,$B14,Taches!$J$6:$J$325,"En cours")+COUNTIFS(Taches!$D$6:$D$325,$B14,Taches!$J$6:$J$325,"En revue") | M14: =COUNTIFS(Taches!$D$6:$D$325,$B14,Taches!$J$6:$J$325,"Bloquée") | N14: =COUNTIFS(Taches!$D$6:$D$325,$B14,Taches!$U$6:$U$325,"En retard") | O14: =IF(J14=0,"Sans tâche",IF(I14>=0.999,"Terminé",IF(M14>0,"Bloqué (partiel)",IF(I14=0,"Non démarré","En cours")))) | Q14: Rendu serveur, filigrane, révocation < 60 s
B15: NEG | C15: Négociation : offre, LOI, audit d'acquisition | D15: Socle V0 | E15: P14, P15 | F15: V3 | G15: =SUMIF(Taches!$D$6:$D$325,$B15,Taches!$M$6:$M$325) | H15: =SUMIF(Taches!$D$6:$D$325,$B15,Taches!$N$6:$N$325) | I15: =IF(G15=0,0,H15/G15) | J15: =COUNTIFS(Taches!$D$6:$D$325,$B15,Taches!$J$6:$J$325,"<>Annulé",Taches!$B$6:$B$325,"<>") | K15: =COUNTIFS(Taches!$D$6:$D$325,$B15,Taches!$J$6:$J$325,"Complétée") | L15: =COUNTIFS(Taches!$D$6:$D$325,$B15,Taches!$J$6:$J$325,"En cours")+COUNTIFS(Taches!$D$6:$D$325,$B15,Taches!$J$6:$J$325,"En revue") | M15: =COUNTIFS(Taches!$D$6:$D$325,$B15,Taches!$J$6:$J$325,"Bloquée") | N15: =COUNTIFS(Taches!$D$6:$D$325,$B15,Taches!$U$6:$U$325,"En retard") | O15: =IF(J15=0,"Sans tâche",IF(I15>=0.999,"Terminé",IF(M15>0,"Bloqué (partiel)",IF(I15=0,"Non démarré","En cours"))))
B16: REA | C16: Réalisation et traçabilité de la transmission | D16: Socle V0 | E16: P16 | F16: V3 | G16: =SUMIF(Taches!$D$6:$D$325,$B16,Taches!$M$6:$M$325) | H16: =SUMIF(Taches!$D$6:$D$325,$B16,Taches!$N$6:$N$325) | I16: =IF(G16=0,0,H16/G16) | J16: =COUNTIFS(Taches!$D$6:$D$325,$B16,Taches!$J$6:$J$325,"<>Annulé",Taches!$B$6:$B$325,"<>") | K16: =COUNTIFS(Taches!$D$6:$D$325,$B16,Taches!$J$6:$J$325,"Complétée") | L16: =COUNTIFS(Taches!$D$6:$D$325,$B16,Taches!$J$6:$J$325,"En cours")+COUNTIFS(Taches!$D$6:$D$325,$B16,Taches!$J$6:$J$325,"En revue") | M16: =COUNTIFS(Taches!$D$6:$D$325,$B16,Taches!$J$6:$J$325,"Bloquée") | N16: =COUNTIFS(Taches!$D$6:$D$325,$B16,Taches!$U$6:$U$325,"En retard") | O16: =IF(J16=0,"Sans tâche",IF(I16>=0.999,"Terminé",IF(M16>0,"Bloqué (partiel)",IF(I16=0,"Non démarré","En cours")))) | Q16: Sans Deal-Pay natif
B17: LEG | C17: LegalTech OHADA et conformité fiscale | D17: Partenaire-dépendant | E17: P19 | F17: V3 | G17: =SUMIF(Taches!$D$6:$D$325,$B17,Taches!$M$6:$M$325) | H17: =SUMIF(Taches!$D$6:$D$325,$B17,Taches!$N$6:$N$325) | I17: =IF(G17=0,0,H17/G17) | J17: =COUNTIFS(Taches!$D$6:$D$325,$B17,Taches!$J$6:$J$325,"<>Annulé",Taches!$B$6:$B$325,"<>") | K17: =COUNTIFS(Taches!$D$6:$D$325,$B17,Taches!$J$6:$J$325,"Complétée") | L17: =COUNTIFS(Taches!$D$6:$D$325,$B17,Taches!$J$6:$J$325,"En cours")+COUNTIFS(Taches!$D$6:$D$325,$B17,Taches!$J$6:$J$325,"En revue") | M17: =COUNTIFS(Taches!$D$6:$D$325,$B17,Taches!$J$6:$J$325,"Bloquée") | N17: =COUNTIFS(Taches!$D$6:$D$325,$B17,Taches!$U$6:$U$325,"En retard") | O17: =IF(J17=0,"Sans tâche",IF(I17>=0.999,"Terminé",IF(M17>0,"Bloqué (partiel)",IF(I17=0,"Non démarré","En cours")))) | Q17: Partenaire fiscal à confirmer
B18: FIN | C18: Finance : frais, rétrocession CCI, reporting | D18: Socle V0 | E18: P24 | F18: V3 | G18: =SUMIF(Taches!$D$6:$D$325,$B18,Taches!$M$6:$M$325) | H18: =SUMIF(Taches!$D$6:$D$325,$B18,Taches!$N$6:$N$325) | I18: =IF(G18=0,0,H18/G18) | J18: =COUNTIFS(Taches!$D$6:$D$325,$B18,Taches!$J$6:$J$325,"<>Annulé",Taches!$B$6:$B$325,"<>") | K18: =COUNTIFS(Taches!$D$6:$D$325,$B18,Taches!$J$6:$J$325,"Complétée") | L18: =COUNTIFS(Taches!$D$6:$D$325,$B18,Taches!$J$6:$J$325,"En cours")+COUNTIFS(Taches!$D$6:$D$325,$B18,Taches!$J$6:$J$325,"En revue") | M18: =COUNTIFS(Taches!$D$6:$D$325,$B18,Taches!$J$6:$J$325,"Bloquée") | N18: =COUNTIFS(Taches!$D$6:$D$325,$B18,Taches!$U$6:$U$325,"En retard") | O18: =IF(J18=0,"Sans tâche",IF(I18>=0.999,"Terminé",IF(M18>0,"Bloqué (partiel)",IF(I18=0,"Non démarré","En cours")))) | Q18: Barème activable après avis juridique écrit
B19: SUP | C19: Support et accès privilégiés | D19: Socle V0 | E19: P23 | F19: V3 | G19: =SUMIF(Taches!$D$6:$D$325,$B19,Taches!$M$6:$M$325) | H19: =SUMIF(Taches!$D$6:$D$325,$B19,Taches!$N$6:$N$325) | I19: =IF(G19=0,0,H19/G19) | J19: =COUNTIFS(Taches!$D$6:$D$325,$B19,Taches!$J$6:$J$325,"<>Annulé",Taches!$B$6:$B$325,"<>") | K19: =COUNTIFS(Taches!$D$6:$D$325,$B19,Taches!$J$6:$J$325,"Complétée") | L19: =COUNTIFS(Taches!$D$6:$D$325,$B19,Taches!$J$6:$J$325,"En cours")+COUNTIFS(Taches!$D$6:$D$325,$B19,Taches!$J$6:$J$325,"En revue") | M19: =COUNTIFS(Taches!$D$6:$D$325,$B19,Taches!$J$6:$J$325,"Bloquée") | N19: =COUNTIFS(Taches!$D$6:$D$325,$B19,Taches!$U$6:$U$325,"En retard") | O19: =IF(J19=0,"Sans tâche",IF(I19>=0.999,"Terminé",IF(M19>0,"Bloqué (partiel)",IF(I19=0,"Non démarré","En cours")))) | Q19: Moindre privilège
B20: OPS | C20: Exploitation, sécurité, continuité (SLA 99,5 %) | D20: Socle V0 | E20: P25 | F20: V1 (base) / V3 (durci) | G20: =SUMIF(Taches!$D$6:$D$325,$B20,Taches!$M$6:$M$325) | H20: =SUMIF(Taches!$D$6:$D$325,$B20,Taches!$N$6:$N$325) | I20: =IF(G20=0,0,H20/G20) | J20: =COUNTIFS(Taches!$D$6:$D$325,$B20,Taches!$J$6:$J$325,"<>Annulé",Taches!$B$6:$B$325,"<>") | K20: =COUNTIFS(Taches!$D$6:$D$325,$B20,Taches!$J$6:$J$325,"Complétée") | L20: =COUNTIFS(Taches!$D$6:$D$325,$B20,Taches!$J$6:$J$325,"En cours")+COUNTIFS(Taches!$D$6:$D$325,$B20,Taches!$J$6:$J$325,"En revue") | M20: =COUNTIFS(Taches!$D$6:$D$325,$B20,Taches!$J$6:$J$325,"Bloquée") | N20: =COUNTIFS(Taches!$D$6:$D$325,$B20,Taches!$U$6:$U$325,"En retard") | O20: =IF(J20=0,"Sans tâche",IF(I20>=0.999,"Terminé",IF(M20>0,"Bloqué (partiel)",IF(I20=0,"Non démarré","En cours")))) | Q20: Obligation de résultat contractuelle
B21: REB | C21: Alerte & Rebond : entreprises en difficulté | D21: Socle V0 | E21: P17, P18 | F21: V4 | G21: =SUMIF(Taches!$D$6:$D$325,$B21,Taches!$M$6:$M$325) | H21: =SUMIF(Taches!$D$6:$D$325,$B21,Taches!$N$6:$N$325) | I21: =IF(G21=0,0,H21/G21) | J21: =COUNTIFS(Taches!$D$6:$D$325,$B21,Taches!$J$6:$J$325,"<>Annulé",Taches!$B$6:$B$325,"<>") | K21: =COUNTIFS(Taches!$D$6:$D$325,$B21,Taches!$J$6:$J$325,"Complétée") | L21: =COUNTIFS(Taches!$D$6:$D$325,$B21,Taches!$J$6:$J$325,"En cours")+COUNTIFS(Taches!$D$6:$D$325,$B21,Taches!$J$6:$J$325,"En revue") | M21: =COUNTIFS(Taches!$D$6:$D$325,$B21,Taches!$J$6:$J$325,"Bloquée") | N21: =COUNTIFS(Taches!$D$6:$D$325,$B21,Taches!$U$6:$U$325,"En retard") | O21: =IF(J21=0,"Sans tâche",IF(I21>=0.999,"Terminé",IF(M21>0,"Bloqué (partiel)",IF(I21=0,"Non démarré","En cours")))) | Q21: Confidentialité renforcée
B22: CNX | C22: Deal-Connect : événements B2B (Remo.co) | D22: Socle V0 | E22: P20 | F22: V4 | G22: =SUMIF(Taches!$D$6:$D$325,$B22,Taches!$M$6:$M$325) | H22: =SUMIF(Taches!$D$6:$D$325,$B22,Taches!$N$6:$N$325) | I22: =IF(G22=0,0,H22/G22) | J22: =COUNTIFS(Taches!$D$6:$D$325,$B22,Taches!$J$6:$J$325,"<>Annulé",Taches!$B$6:$B$325,"<>") | K22: =COUNTIFS(Taches!$D$6:$D$325,$B22,Taches!$J$6:$J$325,"Complétée") | L22: =COUNTIFS(Taches!$D$6:$D$325,$B22,Taches!$J$6:$J$325,"En cours")+COUNTIFS(Taches!$D$6:$D$325,$B22,Taches!$J$6:$J$325,"En revue") | M22: =COUNTIFS(Taches!$D$6:$D$325,$B22,Taches!$J$6:$J$325,"Bloquée") | N22: =COUNTIFS(Taches!$D$6:$D$325,$B22,Taches!$U$6:$U$325,"En retard") | O22: =IF(J22=0,"Sans tâche",IF(I22>=0.999,"Terminé",IF(M22>0,"Bloqué (partiel)",IF(I22=0,"Non démarré","En cours")))) | Q22: Connecteur externe Remo.co
B23: DIA | C23: Guichet Diaspora et investissement | D23: Socle V0 | E23: P21 | F23: V4 | G23: =SUMIF(Taches!$D$6:$D$325,$B23,Taches!$M$6:$M$325) | H23: =SUMIF(Taches!$D$6:$D$325,$B23,Taches!$N$6:$N$325) | I23: =IF(G23=0,0,H23/G23) | J23: =COUNTIFS(Taches!$D$6:$D$325,$B23,Taches!$J$6:$J$325,"<>Annulé",Taches!$B$6:$B$325,"<>") | K23: =COUNTIFS(Taches!$D$6:$D$325,$B23,Taches!$J$6:$J$325,"Complétée") | L23: =COUNTIFS(Taches!$D$6:$D$325,$B23,Taches!$J$6:$J$325,"En cours")+COUNTIFS(Taches!$D$6:$D$325,$B23,Taches!$J$6:$J$325,"En revue") | M23: =COUNTIFS(Taches!$D$6:$D$325,$B23,Taches!$J$6:$J$325,"Bloquée") | N23: =COUNTIFS(Taches!$D$6:$D$325,$B23,Taches!$U$6:$U$325,"En retard") | O23: =IF(J23=0,"Sans tâche",IF(I23>=0.999,"Terminé",IF(M23>0,"Bloqué (partiel)",IF(I23=0,"Non démarré","En cours")))) | Q23: Rendez-vous vidéo via Remo.co
B24: EXP | C24: Deal-Experts : mobilisation d'expert indépendant | D24: Arbitrage requis | E24: P13 | F24: V4 (à confirmer) | G24: =SUMIF(Taches!$D$6:$D$325,$B24,Taches!$M$6:$M$325) | H24: =SUMIF(Taches!$D$6:$D$325,$B24,Taches!$N$6:$N$325) | I24: =IF(G24=0,0,H24/G24) | J24: =COUNTIFS(Taches!$D$6:$D$325,$B24,Taches!$J$6:$J$325,"<>Annulé",Taches!$B$6:$B$325,"<>") | K24: =COUNTIFS(Taches!$D$6:$D$325,$B24,Taches!$J$6:$J$325,"Complétée") | L24: =COUNTIFS(Taches!$D$6:$D$325,$B24,Taches!$J$6:$J$325,"En cours")+COUNTIFS(Taches!$D$6:$D$325,$B24,Taches!$J$6:$J$325,"En revue") | M24: =COUNTIFS(Taches!$D$6:$D$325,$B24,Taches!$J$6:$J$325,"Bloquée") | N24: =COUNTIFS(Taches!$D$6:$D$325,$B24,Taches!$U$6:$U$325,"En retard") | O24: =IF(J24=0,"Sans tâche",IF(I24>=0.999,"Terminé",IF(M24>0,"Bloqué (partiel)",IF(I24=0,"Non démarré","En cours")))) | Q24: Contractuel (P13) ou cible future : à trancher
B25: VDR-IA | C25: VDR Intelligence : DealLens et surfaces de diligence | D25: Extension conçue, non prod | E25: - | F25: V5 | G25: =SUMIF(Taches!$D$6:$D$325,$B25,Taches!$M$6:$M$325) | H25: =SUMIF(Taches!$D$6:$D$325,$B25,Taches!$N$6:$N$325) | I25: =IF(G25=0,0,H25/G25) | J25: =COUNTIFS(Taches!$D$6:$D$325,$B25,Taches!$J$6:$J$325,"<>Annulé",Taches!$B$6:$B$325,"<>") | K25: =COUNTIFS(Taches!$D$6:$D$325,$B25,Taches!$J$6:$J$325,"Complétée") | L25: =COUNTIFS(Taches!$D$6:$D$325,$B25,Taches!$J$6:$J$325,"En cours")+COUNTIFS(Taches!$D$6:$D$325,$B25,Taches!$J$6:$J$325,"En revue") | M25: =COUNTIFS(Taches!$D$6:$D$325,$B25,Taches!$J$6:$J$325,"Bloquée") | N25: =COUNTIFS(Taches!$D$6:$D$325,$B25,Taches!$U$6:$U$325,"En retard") | O25: =IF(J25=0,"Sans tâche",IF(I25>=0.999,"Terminé",IF(M25>0,"Bloqué (partiel)",IF(I25=0,"Non démarré","En cours")))) | Q25: Aucun fournisseur IA contracté
B26: Total | G26: =SUM(G6:G25) | H26: =SUM(H6:H25) | I26: =IF(G26=0,0,H26/G26) | J26: =SUM(J6:J25) | K26: =SUM(K6:K25) | L26: =SUM(L6:L25) | M26: =SUM(M6:M25) | N26: =SUM(N6:N25)
B29: Hors périmètre v0 et éléments en dormance (aucune tâche, pour mémoire)
C30: Deal-Pay et séquestre (escrow) | D30: Hors périmètre v0 | Q30: Frontière d'intégration partenaire licencié désactivée ; avenant requis
C31: Valorisation algorithmique automatique | D31: Hors périmètre v0 | Q31: Le v0 interdit toute fourchette présentée comme un avis DealPME
C32: Certification automatique / score de readiness | D32: Hors périmètre v0 | Q32: Décision nominative CCI-Togo obligatoire
C33: KYC biométrique | D33: Différé (P2) | Q33: Activable après autorisation IPDCP, sous drapeau fonctionnel
C34: Broker Agency Hub multi-tenant | D34: Hors périmètre v0 | Q34: Pas de compte maître de cabinet M&A dans le v0
C35: Marques globales génériques (Stripe, DocuSign, SumSub, Ecobank) | D35: Hors périmètre v0 | Q35: Remplacées par des vendeurs locaux réels

Sheet Versions
B2: Versions
B3: Avancement, charges et retards calculés depuis les tâches. Les dates de début et de fin se saisissent ici et pilotent les jalons.
B5: Version | C5: Objet | D5: Début prévu | E5: Fin prévue | F5: Jours restants | G5: Charge (j/p) | H5: Charge (sem.) | I5: Réalisé (j/p) | J5: Avancement | K5: Tâches | L5: Faites | M5: En cours | N5: Bloquées | O5: En retard | P5: État
B6: V1 | C6: Premier produit : cessions d'actifs, espace CCI-Togo, Deal-Ready, démonstration du blocage RPS, Deal-Connect via Remo.co | D6: 46268 | E6: 46310 | F6: =E6-TODAY() | G6: =SUMIF(Taches!$C$6:$C$325,$B6,Taches!$M$6:$M$325) | H6: =G6/5 | I6: =SUMIF(Taches!$C$6:$C$325,$B6,Taches!$N$6:$N$325) | J6: =IF(G6=0,0,I6/G6) | K6: =COUNTIFS(Taches!$C$6:$C$325,$B6,Taches!$J$6:$J$325,"<>Annulé",Taches!$B$6:$B$325,"<>") | L6: =COUNTIFS(Taches!$C$6:$C$325,$B6,Taches!$J$6:$J$325,"Complétée") | M6: =COUNTIFS(Taches!$C$6:$C$325,$B6,Taches!$J$6:$J$325,"En cours")+COUNTIFS(Taches!$C$6:$C$325,$B6,Taches!$J$6:$J$325,"En revue") | N6: =COUNTIFS(Taches!$C$6:$C$325,$B6,Taches!$J$6:$J$325,"Bloquée") | O6: =COUNTIFS(Taches!$C$6:$C$325,$B6,Taches!$U$6:$U$325,"En retard") | P6: =IF(J6>=0.999,"Livrée",IF(AND(TODAY()>E6,J6<0.999),"En dépassement",IF(J6=0,IF(TODAY()>=D6,"À démarrer","Planifiée"),"En cours")))
B7: V2 | C7: Cession de titres en cercle restreint (RPS réel), signature électronique, data room et Q&R | D7: 46311 | E7: 46366 | F7: =E7-TODAY() | G7: =SUMIF(Taches!$C$6:$C$325,$B7,Taches!$M$6:$M$325) | H7: =G7/5 | I7: =SUMIF(Taches!$C$6:$C$325,$B7,Taches!$N$6:$N$325) | J7: =IF(G7=0,0,I7/G7) | K7: =COUNTIFS(Taches!$C$6:$C$325,$B7,Taches!$J$6:$J$325,"<>Annulé",Taches!$B$6:$B$325,"<>") | L7: =COUNTIFS(Taches!$C$6:$C$325,$B7,Taches!$J$6:$J$325,"Complétée") | M7: =COUNTIFS(Taches!$C$6:$C$325,$B7,Taches!$J$6:$J$325,"En cours")+COUNTIFS(Taches!$C$6:$C$325,$B7,Taches!$J$6:$J$325,"En revue") | N7: =COUNTIFS(Taches!$C$6:$C$325,$B7,Taches!$J$6:$J$325,"Bloquée") | O7: =COUNTIFS(Taches!$C$6:$C$325,$B7,Taches!$U$6:$U$325,"En retard") | P7: =IF(J7>=0.999,"Livrée",IF(AND(TODAY()>E7,J7<0.999),"En dépassement",IF(J7=0,IF(TODAY()>=D7,"À démarrer","Planifiée"),"En cours")))
B8: V3 | C8: Négociation et réalisation, LegalTech OHADA, Finance et rétrocession, support, fermeture des portes de conformité | D8: 46367 | E8: 46436 | F8: =E8-TODAY() | G8: =SUMIF(Taches!$C$6:$C$325,$B8,Taches!$M$6:$M$325) | H8: =G8/5 | I8: =SUMIF(Taches!$C$6:$C$325,$B8,Taches!$N$6:$N$325) | J8: =IF(G8=0,0,I8/G8) | K8: =COUNTIFS(Taches!$C$6:$C$325,$B8,Taches!$J$6:$J$325,"<>Annulé",Taches!$B$6:$B$325,"<>") | L8: =COUNTIFS(Taches!$C$6:$C$325,$B8,Taches!$J$6:$J$325,"Complétée") | M8: =COUNTIFS(Taches!$C$6:$C$325,$B8,Taches!$J$6:$J$325,"En cours")+COUNTIFS(Taches!$C$6:$C$325,$B8,Taches!$J$6:$J$325,"En revue") | N8: =COUNTIFS(Taches!$C$6:$C$325,$B8,Taches!$J$6:$J$325,"Bloquée") | O8: =COUNTIFS(Taches!$C$6:$C$325,$B8,Taches!$U$6:$U$325,"En retard") | P8: =IF(J8>=0.999,"Livrée",IF(AND(TODAY()>E8,J8<0.999),"En dépassement",IF(J8=0,IF(TODAY()>=D8,"À démarrer","Planifiée"),"En cours")))
B9: V4 | C9: Alerte & Rebond, Deal-Connect (Remo.co), Guichet Diaspora, Deal-Experts | D9: 46437 | E9: 46478 | F9: =E9-TODAY() | G9: =SUMIF(Taches!$C$6:$C$325,$B9,Taches!$M$6:$M$325) | H9: =G9/5 | I9: =SUMIF(Taches!$C$6:$C$325,$B9,Taches!$N$6:$N$325) | J9: =IF(G9=0,0,I9/G9) | K9: =COUNTIFS(Taches!$C$6:$C$325,$B9,Taches!$J$6:$J$325,"<>Annulé",Taches!$B$6:$B$325,"<>") | L9: =COUNTIFS(Taches!$C$6:$C$325,$B9,Taches!$J$6:$J$325,"Complétée") | M9: =COUNTIFS(Taches!$C$6:$C$325,$B9,Taches!$J$6:$J$325,"En cours")+COUNTIFS(Taches!$C$6:$C$325,$B9,Taches!$J$6:$J$325,"En revue") | N9: =COUNTIFS(Taches!$C$6:$C$325,$B9,Taches!$J$6:$J$325,"Bloquée") | O9: =COUNTIFS(Taches!$C$6:$C$325,$B9,Taches!$U$6:$U$325,"En retard") | P9: =IF(J9>=0.999,"Livrée",IF(AND(TODAY()>E9,J9<0.999),"En dépassement",IF(J9=0,IF(TODAY()>=D9,"À démarrer","Planifiée"),"En cours")))
B10: V5 | C10: VDR Intelligence : DealLens, Evidence Map, Issue Radar, Clean Team | D10: 46479 | E10: 46541 | F10: =E10-TODAY() | G10: =SUMIF(Taches!$C$6:$C$325,$B10,Taches!$M$6:$M$325) | H10: =G10/5 | I10: =SUMIF(Taches!$C$6:$C$325,$B10,Taches!$N$6:$N$325) | J10: =IF(G10=0,0,I10/G10) | K10: =COUNTIFS(Taches!$C$6:$C$325,$B10,Taches!$J$6:$J$325,"<>Annulé",Taches!$B$6:$B$325,"<>") | L10: =COUNTIFS(Taches!$C$6:$C$325,$B10,Taches!$J$6:$J$325,"Complétée") | M10: =COUNTIFS(Taches!$C$6:$C$325,$B10,Taches!$J$6:$J$325,"En cours")+COUNTIFS(Taches!$C$6:$C$325,$B10,Taches!$J$6:$J$325,"En revue") | N10: =COUNTIFS(Taches!$C$6:$C$325,$B10,Taches!$J$6:$J$325,"Bloquée") | O10: =COUNTIFS(Taches!$C$6:$C$325,$B10,Taches!$U$6:$U$325,"En retard") | P10: =IF(J10>=0.999,"Livrée",IF(AND(TODAY()>E10,J10<0.999),"En dépassement",IF(J10=0,IF(TODAY()>=D10,"À démarrer","Planifiée"),"En cours")))
B11: Total | G11: =SUM(G6:G10) | H11: =SUM(H6:H10) | I11: =SUM(I6:I10) | J11: =IF(G11=0,0,I11/G11) | K11: =SUM(K6:K10) | L11: =SUM(L6:L10) | M11: =SUM(M6:M10) | N11: =SUM(N6:N10) | O11: =SUM(O6:O10)

Sheet Gantt
B2: Planning hebdomadaire
B3: Barres calculées depuis les dates de l'onglet Taches. Bleu : prévu. Ambre : en cours. Vert : fait. Colonne surlignée : semaine courante.
I4: Semaine du (lundi)
B5: ID | C5: Tâche | D5: Version | E5: Module | F5: Début | G5: Fin | H5: Statut | I5: 46265 | J5: 46272 | K5: 46279 | L5: 46286 | M5: 46293 | N5: 46300 | O5: 46307 | P5: 46314 | Q5: 46321 | R5: 46328 | S5: 46335 | T5: 46342 | U5: 46349 | V5: 46356 | W5: 46363 | X5: 46370 | Y5: 46377 | Z5: 46384 | AA5: 46391 | AB5: 46398 | AC5: 46405 | AD5: 46412 | AE5: 46419 | AF5: 46426 | AG5: 46433 | AH5: 46440 | AI5: 46447 | AJ5: 46454 | AK5: 46461 | AL5: 46468 | AM5: 46475 | AN5: 46482 | AO5: 46489 | AP5: 46496 | AQ5: 46503 | AR5: 46510 | AS5: 46517 | AT5: 46524 | AU5: 46531 | AV5: 46538 | AW5: 46545
B6: =IF(Taches!B6="","",Taches!B6) | C6: =IF(Taches!B6="","",Taches!F6) | D6: =IF(Taches!B6="","",Taches!C6) | E6: =IF(Taches!B6="","",Taches!D6) | F6: =IF(Taches!P6="","",Taches!P6) | G6: =IF(Taches!Q6="","",Taches!Q6) | H6: =IF(Taches!B6="","",Taches!J6) | I6: =IF(OR($F6="",$G6=""),"",IF(AND(I$5<=$G6,I$5+6>=$F6),IF($H6="Complétée","F",IF(OR($H6="En cours",$H6="En revue"),"E",IF($H6="Bloquée","B","P"))),"")) | J6: =IF(OR($F6="",$G6=""),"",IF(AND(J$5<=$G6,J$5+6>=$F6),IF($H6="Complétée","F",IF(OR($H6="En cours",$H6="En revue"),"E",IF($H6="Bloquée","B","P"))),"")) | K6: =IF(OR($F6="",$G6=""),"",IF(AND(K$5<=$G6,K$5+6>=$F6),IF($H6="Complétée","F",IF(OR($H6="En cours",$H6="En revue"),"E",IF($H6="Bloquée","B","P"))),"")) | L6: =IF(OR($F6="",$G6=""),"",IF(AND(L$5<=$G6,L$5+6>=$F6),IF($H6="Complétée","F",IF(OR($H6="En cours",$H6="En revue"),"E",IF($H6="Bloquée","B","P"))),"")) | M6: =IF(OR($F6="",$G6=""),"",IF(AND(M$5<=$G6,M$5+6>=$F6),IF($H6="Complétée","F",IF(OR($H6="En cours",$H6="En revue"),"E",IF($H6="Bloquée","B","P"))),"")) | N6: =IF(OR($F6="",$G6=""),"",IF(AND(N$5<=$G6,N$5+6>=$F6),IF($H6="Complétée","F",IF(OR($H6="En cours",$H6="En revue"),"E",IF($H6="Bloquée","B","P"))),"")) | O6: =IF(OR($F6="",$G6=""),"",IF(AND(O$5<=$G6,O$5+6>=$F6),IF($H6="Complétée","F",IF(OR($H6="En cours",$H6="En revue"),"E",IF($H6="Bloquée","B","P"))),"")) | P6: =IF(OR($F6="",$G6=""),"",IF(AND(P$5<=$G6,P$5+6>=$F6),IF($H6="Complétée","F",IF(OR($H6="En cours",$H6="En revue"),"E",IF($H6="Bloquée","B","P"))),"")) | ... AW6: =IF(OR($F6="",$G6=""),"",IF(AND(AW$5<=$G6,AW$5+6>=$F6),IF($H6="Complétée","F",IF(OR($H6="En cours",$H6="En revue"),"E",IF($H6="Bloquée","B","P"))),""))
B7: =IF(Taches!B7="","",Taches!B7) | C7: =IF(Taches!B7="","",Taches!F7) | D7: =IF(Taches!B7="","",Taches!C7) | E7: =IF(Taches!B7="","",Taches!D7) | F7: =IF(Taches!P7="","",Taches!P7) | G7: =IF(Taches!Q7="","",Taches!Q7) | H7: =IF(Taches!B7="","",Taches!J7) | I7: =IF(OR($F7="",$G7=""),"",IF(AND(I$5<=$G7,I$5+6>=$F7),IF($H7="Complétée","F",IF(OR($H7="En cours",$H7="En revue"),"E",IF($H7="Bloquée","B","P"))),"")) | J7: =IF(OR($F7="",$G7=""),"",IF(AND(J$5<=$G7,J$5+6>=$F7),IF($H7="Complétée","F",IF(OR($H7="En cours",$H7="En revue"),"E",IF($H7="Bloquée","B","P"))),"")) | K7: =IF(OR($F7="",$G7=""),"",IF(AND(K$5<=$G7,K$5+6>=$F7),IF($H7="Complétée","F",IF(OR($H7="En cours",$H7="En revue"),"E",IF($H7="Bloquée","B","P"))),"")) | L7: =IF(OR($F7="",$G7=""),"",IF(AND(L$5<=$G7,L$5+6>=$F7),IF($H7="Complétée","F",IF(OR($H7="En cours",$H7="En revue"),"E",IF($H7="Bloquée","B","P"))),"")) | M7: =IF(OR($F7="",$G7=""),"",IF(AND(M$5<=$G7,M$5+6>=$F7),IF($H7="Complétée","F",IF(OR($H7="En cours",$H7="En revue"),"E",IF($H7="Bloquée","B","P"))),"")) | N7: =IF(OR($F7="",$G7=""),"",IF(AND(N$5<=$G7,N$5+6>=$F7),IF($H7="Complétée","F",IF(OR($H7="En cours",$H7="En revue"),"E",IF($H7="Bloquée","B","P"))),"")) | O7: =IF(OR($F7="",$G7=""),"",IF(AND(O$5<=$G7,O$5+6>=$F7),IF($H7="Complétée","F",IF(OR($H7="En cours",$H7="En revue"),"E",IF($H7="Bloquée","B","P"))),"")) | P7: =IF(OR($F7="",$G7=""),"",IF(AND(P$5<=$G7,P$5+6>=$F7),IF($H7="Complétée","F",IF(OR($H7="En cours",$H7="En revue"),"E",IF($H7="Bloquée","B","P"))),"")) | ... AW7: =IF(OR($F7="",$G7=""),"",IF(AND(AW$5<=$G7,AW$5+6>=$F7),IF($H7="Complétée","F",IF(OR($H7="En cours",$H7="En revue"),"E",IF($H7="Bloquée","B","P"))),""))
B8: =IF(Taches!B8="","",Taches!B8) | C8: =IF(Taches!B8="","",Taches!F8) | D8: =IF(Taches!B8="","",Taches!C8) | E8: =IF(Taches!B8="","",Taches!D8) | F8: =IF(Taches!P8="","",Taches!P8) | G8: =IF(Taches!Q8="","",Taches!Q8) | H8: =IF(Taches!B8="","",Taches!J8) | I8: =IF(OR($F8="",$G8=""),"",IF(AND(I$5<=$G8,I$5+6>=$F8),IF($H8="Complétée","F",IF(OR($H8="En cours",$H8="En revue"),"E",IF($H8="Bloquée","B","P"))),"")) | J8: =IF(OR($F8="",$G8=""),"",IF(AND(J$5<=$G8,J$5+6>=$F8),IF($H8="Complétée","F",IF(OR($H8="En cours",$H8="En revue"),"E",IF($H8="Bloquée","B","P"))),"")) | K8: =IF(OR($F8="",$G8=""),"",IF(AND(K$5<=$G8,K$5+6>=$F8),IF($H8="Complétée","F",IF(OR($H8="En cours",$H8="En revue"),"E",IF($H8="Bloquée","B","P"))),"")) | L8: =IF(OR($F8="",$G8=""),"",IF(AND(L$5<=$G8,L$5+6>=$F8),IF($H8="Complétée","F",IF(OR($H8="En cours",$H8="En revue"),"E",IF($H8="Bloquée","B","P"))),"")) | M8: =IF(OR($F8="",$G8=""),"",IF(AND(M$5<=$G8,M$5+6>=$F8),IF($H8="Complétée","F",IF(OR($H8="En cours",$H8="En revue"),"E",IF($H8="Bloquée","B","P"))),"")) | N8: =IF(OR($F8="",$G8=""),"",IF(AND(N$5<=$G8,N$5+6>=$F8),IF($H8="Complétée","F",IF(OR($H8="En cours",$H8="En revue"),"E",IF($H8="Bloquée","B","P"))),"")) | O8: =IF(OR($F8="",$G8=""),"",IF(AND(O$5<=$G8,O$5+6>=$F8),IF($H8="Complétée","F",IF(OR($H8="En cours",$H8="En revue"),"E",IF($H8="Bloquée","B","P"))),"")) | P8: =IF(OR($F8="",$G8=""),"",IF(AND(P$5<=$G8,P$5+6>=$F8),IF($H8="Complétée","F",IF(OR($H8="En cours",$H8="En revue"),"E",IF($H8="Bloquée","B","P"))),"")) | ... AW8: =IF(OR($F8="",$G8=""),"",IF(AND(AW$5<=$G8,AW$5+6>=$F8),IF($H8="Complétée","F",IF(OR($H8="En cours",$H8="En revue"),"E",IF($H8="Bloquée","B","P"))),""))
B9: =IF(Taches!B9="","",Taches!B9) | C9: =IF(Taches!B9="","",Taches!F9) | D9: =IF(Taches!B9="","",Taches!C9) | E9: =IF(Taches!B9="","",Taches!D9) | F9: =IF(Taches!P9="","",Taches!P9) | G9: =IF(Taches!Q9="","",Taches!Q9) | H9: =IF(Taches!B9="","",Taches!J9) | I9: =IF(OR($F9="",$G9=""),"",IF(AND(I$5<=$G9,I$5+6>=$F9),IF($H9="Complétée","F",IF(OR($H9="En cours",$H9="En revue"),"E",IF($H9="Bloquée","B","P"))),"")) | J9: =IF(OR($F9="",$G9=""),"",IF(AND(J$5<=$G9,J$5+6>=$F9),IF($H9="Complétée","F",IF(OR($H9="En cours",$H9="En revue"),"E",IF($H9="Bloquée","B","P"))),"")) | K9: =IF(OR($F9="",$G9=""),"",IF(AND(K$5<=$G9,K$5+6>=$F9),IF($H9="Complétée","F",IF(OR($H9="En cours",$H9="En revue"),"E",IF($H9="Bloquée","B","P"))),"")) | L9: =IF(OR($F9="",$G9=""),"",IF(AND(L$5<=$G9,L$5+6>=$F9),IF($H9="Complétée","F",IF(OR($H9="En cours",$H9="En revue"),"E",IF($H9="Bloquée","B","P"))),"")) | M9: =IF(OR($F9="",$G9=""),"",IF(AND(M$5<=$G9,M$5+6>=$F9),IF($H9="Complétée","F",IF(OR($H9="En cours",$H9="En revue"),"E",IF($H9="Bloquée","B","P"))),"")) | N9: =IF(OR($F9="",$G9=""),"",IF(AND(N$5<=$G9,N$5+6>=$F9),IF($H9="Complétée","F",IF(OR($H9="En cours",$H9="En revue"),"E",IF($H9="Bloquée","B","P"))),"")) | O9: =IF(OR($F9="",$G9=""),"",IF(AND(O$5<=$G9,O$5+6>=$F9),IF($H9="Complétée","F",IF(OR($H9="En cours",$H9="En revue"),"E",IF($H9="Bloquée","B","P"))),"")) | P9: =IF(OR($F9="",$G9=""),"",IF(AND(P$5<=$G9,P$5+6>=$F9),IF($H9="Complétée","F",IF(OR($H9="En cours",$H9="En revue"),"E",IF($H9="Bloquée","B","P"))),"")) | ... AW9: =IF(OR($F9="",$G9=""),"",IF(AND(AW$5<=$G9,AW$5+6>=$F9),IF($H9="Complétée","F",IF(OR($H9="En cours",$H9="En revue"),"E",IF($H9="Bloquée","B","P"))),""))
B10: =IF(Taches!B10="","",Taches!B10) | C10: =IF(Taches!B10="","",Taches!F10) | D10: =IF(Taches!B10="","",Taches!C10) | E10: =IF(Taches!B10="","",Taches!D10) | F10: =IF(Taches!P10="","",Taches!P10) | G10: =IF(Taches!Q10="","",Taches!Q10) | H10: =IF(Taches!B10="","",Taches!J10) | I10: =IF(OR($F10="",$G10=""),"",IF(AND(I$5<=$G10,I$5+6>=$F10),IF($H10="Complétée","F",IF(OR($H10="En cours",$H10="En revue"),"E",IF($H10="Bloquée","B","P"))),"")) | J10: =IF(OR($F10="",$G10=""),"",IF(AND(J$5<=$G10,J$5+6>=$F10),IF($H10="Complétée","F",IF(OR($H10="En cours",$H10="En revue"),"E",IF($H10="Bloquée","B","P"))),"")) | K10: =IF(OR($F10="",$G10=""),"",IF(AND(K$5<=$G10,K$5+6>=$F10),IF($H10="Complétée","F",IF(OR($H10="En cours",$H10="En revue"),"E",IF($H10="Bloquée","B","P"))),"")) | L10: =IF(OR($F10="",$G10=""),"",IF(AND(L$5<=$G10,L$5+6>=$F10),IF($H10="Complétée","F",IF(OR($H10="En cours",$H10="En revue"),"E",IF($H10="Bloquée","B","P"))),"")) | M10: =IF(OR($F10="",$G10=""),"",IF(AND(M$5<=$G10,M$5+6>=$F10),IF($H10="Complétée","F",IF(OR($H10="En cours",$H10="En revue"),"E",IF($H10="Bloquée","B","P"))),"")) | N10: =IF(OR($F10="",$G10=""),"",IF(AND(N$5<=$G10,N$5+6>=$F10),IF($H10="Complétée","F",IF(OR($H10="En cours",$H10="En revue"),"E",IF($H10="Bloquée","B","P"))),"")) | O10: =IF(OR($F10="",$G10=""),"",IF(AND(O$5<=$G10,O$5+6>=$F10),IF($H10="Complétée","F",IF(OR($H10="En cours",$H10="En revue"),"E",IF($H10="Bloquée","B","P"))),"")) | P10: =IF(OR($F10="",$G10=""),"",IF(AND(P$5<=$G10,P$5+6>=$F10),IF($H10="Complétée","F",IF(OR($H10="En cours",$H10="En revue"),"E",IF($H10="Bloquée","B","P"))),"")) | ... AW10: =IF(OR($F10="",$G10=""),"",IF(AND(AW$5<=$G10,AW$5+6>=$F10),IF($H10="Complétée","F",IF(OR($H10="En cours",$H10="En revue"),"E",IF($H10="Bloquée","B","P"))),""))
B11: =IF(Taches!B11="","",Taches!B11) | C11: =IF(Taches!B11="","",Taches!F11) | D11: =IF(Taches!B11="","",Taches!C11) | E11: =IF(Taches!B11="","",Taches!D11) | F11: =IF(Taches!P11="","",Taches!P11) | G11: =IF(Taches!Q11="","",Taches!Q11) | H11: =IF(Taches!B11="","",Taches!J11) | I11: =IF(OR($F11="",$G11=""),"",IF(AND(I$5<=$G11,I$5+6>=$F11),IF($H11="Complétée","F",IF(OR($H11="En cours",$H11="En revue"),"E",IF($H11="Bloquée","B","P"))),"")) | J11: =IF(OR($F11="",$G11=""),"",IF(AND(J$5<=$G11,J$5+6>=$F11),IF($H11="Complétée","F",IF(OR($H11="En cours",$H11="En revue"),"E",IF($H11="Bloquée","B","P"))),"")) | K11: =IF(OR($F11="",$G11=""),"",IF(AND(K$5<=$G11,K$5+6>=$F11),IF($H11="Complétée","F",IF(OR($H11="En cours",$H11="En revue"),"E",IF($H11="Bloquée","B","P"))),"")) | L11: =IF(OR($F11="",$G11=""),"",IF(AND(L$5<=$G11,L$5+6>=$F11),IF($H11="Complétée","F",IF(OR($H11="En cours",$H11="En revue"),"E",IF($H11="Bloquée","B","P"))),"")) | M11: =IF(OR($F11="",$G11=""),"",IF(AND(M$5<=$G11,M$5+6>=$F11),IF($H11="Complétée","F",IF(OR($H11="En cours",$H11="En revue"),"E",IF($H11="Bloquée","B","P"))),"")) | N11: =IF(OR($F11="",$G11=""),"",IF(AND(N$5<=$G11,N$5+6>=$F11),IF($H11="Complétée","F",IF(OR($H11="En cours",$H11="En revue"),"E",IF($H11="Bloquée","B","P"))),"")) | O11: =IF(OR($F11="",$G11=""),"",IF(AND(O$5<=$G11,O$5+6>=$F11),IF($H11="Complétée","F",IF(OR($H11="En cours",$H11="En revue"),"E",IF($H11="Bloquée","B","P"))),"")) | P11: =IF(OR($F11="",$G11=""),"",IF(AND(P$5<=$G11,P$5+6>=$F11),IF($H11="Complétée","F",IF(OR($H11="En cours",$H11="En revue"),"E",IF($H11="Bloquée","B","P"))),"")) | ... AW11: =IF(OR($F11="",$G11=""),"",IF(AND(AW$5<=$G11,AW$5+6>=$F11),IF($H11="Complétée","F",IF(OR($H11="En cours",$H11="En revue"),"E",IF($H11="Bloquée","B","P"))),""))
B12: =IF(Taches!B12="","",Taches!B12) | C12: =IF(Taches!B12="","",Taches!F12) | D12: =IF(Taches!B12="","",Taches!C12) | E12: =IF(Taches!B12="","",Taches!D12) | F12: =IF(Taches!P12="","",Taches!P12) | G12: =IF(Taches!Q12="","",Taches!Q12) | H12: =IF(Taches!B12="","",Taches!J12) | I12: =IF(OR($F12="",$G12=""),"",IF(AND(I$5<=$G12,I$5+6>=$F12),IF($H12="Complétée","F",IF(OR($H12="En cours",$H12="En revue"),"E",IF($H12="Bloquée","B","P"))),"")) | J12: =IF(OR($F12="",$G12=""),"",IF(AND(J$5<=$G12,J$5+6>=$F12),IF($H12="Complétée","F",IF(OR($H12="En cours",$H12="En revue"),"E",IF($H12="Bloquée","B","P"))),"")) | K12: =IF(OR($F12="",$G12=""),"",IF(AND(K$5<=$G12,K$5+6>=$F12),IF($H12="Complétée","F",IF(OR($H12="En cours",$H12="En revue"),"E",IF($H12="Bloquée","B","P"))),"")) | L12: =IF(OR($F12="",$G12=""),"",IF(AND(L$5<=$G12,L$5+6>=$F12),IF($H12="Complétée","F",IF(OR($H12="En cours",$H12="En revue"),"E",IF($H12="Bloquée","B","P"))),"")) | M12: =IF(OR($F12="",$G12=""),"",IF(AND(M$5<=$G12,M$5+6>=$F12),IF($H12="Complétée","F",IF(OR($H12="En cours",$H12="En revue"),"E",IF($H12="Bloquée","B","P"))),"")) | N12: =IF(OR($F12="",$G12=""),"",IF(AND(N$5<=$G12,N$5+6>=$F12),IF($H12="Complétée","F",IF(OR($H12="En cours",$H12="En revue"),"E",IF($H12="Bloquée","B","P"))),"")) | O12: =IF(OR($F12="",$G12=""),"",IF(AND(O$5<=$G12,O$5+6>=$F12),IF($H12="Complétée","F",IF(OR($H12="En cours",$H12="En revue"),"E",IF($H12="Bloquée","B","P"))),"")) | P12: =IF(OR($F12="",$G12=""),"",IF(AND(P$5<=$G12,P$5+6>=$F12),IF($H12="Complétée","F",IF(OR($H12="En cours",$H12="En revue"),"E",IF($H12="Bloquée","B","P"))),"")) | ... AW12: =IF(OR($F12="",$G12=""),"",IF(AND(AW$5<=$G12,AW$5+6>=$F12),IF($H12="Complétée","F",IF(OR($H12="En cours",$H12="En revue"),"E",IF($H12="Bloquée","B","P"))),""))
B13: =IF(Taches!B13="","",Taches!B13) | C13: =IF(Taches!B13="","",Taches!F13) | D13: =IF(Taches!B13="","",Taches!C13) | E13: =IF(Taches!B13="","",Taches!D13) | F13: =IF(Taches!P13="","",Taches!P13) | G13: =IF(Taches!Q13="","",Taches!Q13) | H13: =IF(Taches!B13="","",Taches!J13) | I13: =IF(OR($F13="",$G13=""),"",IF(AND(I$5<=$G13,I$5+6>=$F13),IF($H13="Complétée","F",IF(OR($H13="En cours",$H13="En revue"),"E",IF($H13="Bloquée","B","P"))),"")) | J13: =IF(OR($F13="",$G13=""),"",IF(AND(J$5<=$G13,J$5+6>=$F13),IF($H13="Complétée","F",IF(OR($H13="En cours",$H13="En revue"),"E",IF($H13="Bloquée","B","P"))),"")) | K13: =IF(OR($F13="",$G13=""),"",IF(AND(K$5<=$G13,K$5+6>=$F13),IF($H13="Complétée","F",IF(OR($H13="En cours",$H13="En revue"),"E",IF($H13="Bloquée","B","P"))),"")) | L13: =IF(OR($F13="",$G13=""),"",IF(AND(L$5<=$G13,L$5+6>=$F13),IF($H13="Complétée","F",IF(OR($H13="En cours",$H13="En revue"),"E",IF($H13="Bloquée","B","P"))),"")) | M13: =IF(OR($F13="",$G13=""),"",IF(AND(M$5<=$G13,M$5+6>=$F13),IF($H13="Complétée","F",IF(OR($H13="En cours",$H13="En revue"),"E",IF($H13="Bloquée","B","P"))),"")) | N13: =IF(OR($F13="",$G13=""),"",IF(AND(N$5<=$G13,N$5+6>=$F13),IF($H13="Complétée","F",IF(OR($H13="En cours",$H13="En revue"),"E",IF($H13="Bloquée","B","P"))),"")) | O13: =IF(OR($F13="",$G13=""),"",IF(AND(O$5<=$G13,O$5+6>=$F13),IF($H13="Complétée","F",IF(OR($H13="En cours",$H13="En revue"),"E",IF($H13="Bloquée","B","P"))),"")) | P13: =IF(OR($F13="",$G13=""),"",IF(AND(P$5<=$G13,P$5+6>=$F13),IF($H13="Complétée","F",IF(OR($H13="En cours",$H13="En revue"),"E",IF($H13="Bloquée","B","P"))),"")) | ... AW13: =IF(OR($F13="",$G13=""),"",IF(AND(AW$5<=$G13,AW$5+6>=$F13),IF($H13="Complétée","F",IF(OR($H13="En cours",$H13="En revue"),"E",IF($H13="Bloquée","B","P"))),""))
B14: =IF(Taches!B14="","",Taches!B14) | C14: =IF(Taches!B14="","",Taches!F14) | D14: =IF(Taches!B14="","",Taches!C14) | E14: =IF(Taches!B14="","",Taches!D14) | F14: =IF(Taches!P14="","",Taches!P14) | G14: =IF(Taches!Q14="","",Taches!Q14) | H14: =IF(Taches!B14="","",Taches!J14) | I14: =IF(OR($F14="",$G14=""),"",IF(AND(I$5<=$G14,I$5+6>=$F14),IF($H14="Complétée","F",IF(OR($H14="En cours",$H14="En revue"),"E",IF($H14="Bloquée","B","P"))),"")) | J14: =IF(OR($F14="",$G14=""),"",IF(AND(J$5<=$G14,J$5+6>=$F14),IF($H14="Complétée","F",IF(OR($H14="En cours",$H14="En revue"),"E",IF($H14="Bloquée","B","P"))),"")) | K14: =IF(OR($F14="",$G14=""),"",IF(AND(K$5<=$G14,K$5+6>=$F14),IF($H14="Complétée","F",IF(OR($H14="En cours",$H14="En revue"),"E",IF($H14="Bloquée","B","P"))),"")) | L14: =IF(OR($F14="",$G14=""),"",IF(AND(L$5<=$G14,L$5+6>=$F14),IF($H14="Complétée","F",IF(OR($H14="En cours",$H14="En revue"),"E",IF($H14="Bloquée","B","P"))),"")) | M14: =IF(OR($F14="",$G14=""),"",IF(AND(M$5<=$G14,M$5+6>=$F14),IF($H14="Complétée","F",IF(OR($H14="En cours",$H14="En revue"),"E",IF($H14="Bloquée","B","P"))),"")) | N14: =IF(OR($F14="",$G14=""),"",IF(AND(N$5<=$G14,N$5+6>=$F14),IF($H14="Complétée","F",IF(OR($H14="En cours",$H14="En revue"),"E",IF($H14="Bloquée","B","P"))),"")) | O14: =IF(OR($F14="",$G14=""),"",IF(AND(O$5<=$G14,O$5+6>=$F14),IF($H14="Complétée","F",IF(OR($H14="En cours",$H14="En revue"),"E",IF($H14="Bloquée","B","P"))),"")) | P14: =IF(OR($F14="",$G14=""),"",IF(AND(P$5<=$G14,P$5+6>=$F14),IF($H14="Complétée","F",IF(OR($H14="En cours",$H14="En revue"),"E",IF($H14="Bloquée","B","P"))),"")) | ... AW14: =IF(OR($F14="",$G14=""),"",IF(AND(AW$5<=$G14,AW$5+6>=$F14),IF($H14="Complétée","F",IF(OR($H14="En cours",$H14="En revue"),"E",IF($H14="Bloquée","B","P"))),""))
B15: =IF(Taches!B15="","",Taches!B15) | C15: =IF(Taches!B15="","",Taches!F15) | D15: =IF(Taches!B15="","",Taches!C15) | E15: =IF(Taches!B15="","",Taches!D15) | F15: =IF(Taches!P15="","",Taches!P15) | G15: =IF(Taches!Q15="","",Taches!Q15) | H15: =IF(Taches!B15="","",Taches!J15) | I15: =IF(OR($F15="",$G15=""),"",IF(AND(I$5<=$G15,I$5+6>=$F15),IF($H15="Complétée","F",IF(OR($H15="En cours",$H15="En revue"),"E",IF($H15="Bloquée","B","P"))),"")) | J15: =IF(OR($F15="",$G15=""),"",IF(AND(J$5<=$G15,J$5+6>=$F15),IF($H15="Complétée","F",IF(OR($H15="En cours",$H15="En revue"),"E",IF($H15="Bloquée","B","P"))),"")) | K15: =IF(OR($F15="",$G15=""),"",IF(AND(K$5<=$G15,K$5+6>=$F15),IF($H15="Complétée","F",IF(OR($H15="En cours",$H15="En revue"),"E",IF($H15="Bloquée","B","P"))),"")) | L15: =IF(OR($F15="",$G15=""),"",IF(AND(L$5<=$G15,L$5+6>=$F15),IF($H15="Complétée","F",IF(OR($H15="En cours",$H15="En revue"),"E",IF($H15="Bloquée","B","P"))),"")) | M15: =IF(OR($F15="",$G15=""),"",IF(AND(M$5<=$G15,M$5+6>=$F15),IF($H15="Complétée","F",IF(OR($H15="En cours",$H15="En revue"),"E",IF($H15="Bloquée","B","P"))),"")) | N15: =IF(OR($F15="",$G15=""),"",IF(AND(N$5<=$G15,N$5+6>=$F15),IF($H15="Complétée","F",IF(OR($H15="En cours",$H15="En revue"),"E",IF($H15="Bloquée","B","P"))),"")) | O15: =IF(OR($F15="",$G15=""),"",IF(AND(O$5<=$G15,O$5+6>=$F15),IF($H15="Complétée","F",IF(OR($H15="En cours",$H15="En revue"),"E",IF($H15="Bloquée","B","P"))),"")) | P15: =IF(OR($F15="",$G15=""),"",IF(AND(P$5<=$G15,P$5+6>=$F15),IF($H15="Complétée","F",IF(OR($H15="En cours",$H15="En revue"),"E",IF($H15="Bloquée","B","P"))),"")) | ... AW15: =IF(OR($F15="",$G15=""),"",IF(AND(AW$5<=$G15,AW$5+6>=$F15),IF($H15="Complétée","F",IF(OR($H15="En cours",$H15="En revue"),"E",IF($H15="Bloquée","B","P"))),""))
B16: =IF(Taches!B16="","",Taches!B16) | C16: =IF(Taches!B16="","",Taches!F16) | D16: =IF(Taches!B16="","",Taches!C16) | E16: =IF(Taches!B16="","",Taches!D16) | F16: =IF(Taches!P16="","",Taches!P16) | G16: =IF(Taches!Q16="","",Taches!Q16) | H16: =IF(Taches!B16="","",Taches!J16) | I16: =IF(OR($F16="",$G16=""),"",IF(AND(I$5<=$G16,I$5+6>=$F16),IF($H16="Complétée","F",IF(OR($H16="En cours",$H16="En revue"),"E",IF($H16="Bloquée","B","P"))),"")) | J16: =IF(OR($F16="",$G16=""),"",IF(AND(J$5<=$G16,J$5+6>=$F16),IF($H16="Complétée","F",IF(OR($H16="En cours",$H16="En revue"),"E",IF($H16="Bloquée","B","P"))),"")) | K16: =IF(OR($F16="",$G16=""),"",IF(AND(K$5<=$G16,K$5+6>=$F16),IF($H16="Complétée","F",IF(OR($H16="En cours",$H16="En revue"),"E",IF($H16="Bloquée","B","P"))),"")) | L16: =IF(OR($F16="",$G16=""),"",IF(AND(L$5<=$G16,L$5+6>=$F16),IF($H16="Complétée","F",IF(OR($H16="En cours",$H16="En revue"),"E",IF($H16="Bloquée","B","P"))),"")) | M16: =IF(OR($F16="",$G16=""),"",IF(AND(M$5<=$G16,M$5+6>=$F16),IF($H16="Complétée","F",IF(OR($H16="En cours",$H16="En revue"),"E",IF($H16="Bloquée","B","P"))),"")) | N16: =IF(OR($F16="",$G16=""),"",IF(AND(N$5<=$G16,N$5+6>=$F16),IF($H16="Complétée","F",IF(OR($H16="En cours",$H16="En revue"),"E",IF($H16="Bloquée","B","P"))),"")) | O16: =IF(OR($F16="",$G16=""),"",IF(AND(O$5<=$G16,O$5+6>=$F16),IF($H16="Complétée","F",IF(OR($H16="En cours",$H16="En revue"),"E",IF($H16="Bloquée","B","P"))),"")) | P16: =IF(OR($F16="",$G16=""),"",IF(AND(P$5<=$G16,P$5+6>=$F16),IF($H16="Complétée","F",IF(OR($H16="En cours",$H16="En revue"),"E",IF($H16="Bloquée","B","P"))),"")) | ... AW16: =IF(OR($F16="",$G16=""),"",IF(AND(AW$5<=$G16,AW$5+6>=$F16),IF($H16="Complétée","F",IF(OR($H16="En cours",$H16="En revue"),"E",IF($H16="Bloquée","B","P"))),""))
B17: =IF(Taches!B17="","",Taches!B17) | C17: =IF(Taches!B17="","",Taches!F17) | D17: =IF(Taches!B17="","",Taches!C17) | E17: =IF(Taches!B17="","",Taches!D17) | F17: =IF(Taches!P17="","",Taches!P17) | G17: =IF(Taches!Q17="","",Taches!Q17) | H17: =IF(Taches!B17="","",Taches!J17) | I17: =IF(OR($F17="",$G17=""),"",IF(AND(I$5<=$G17,I$5+6>=$F17),IF($H17="Complétée","F",IF(OR($H17="En cours",$H17="En revue"),"E",IF($H17="Bloquée","B","P"))),"")) | J17: =IF(OR($F17="",$G17=""),"",IF(AND(J$5<=$G17,J$5+6>=$F17),IF($H17="Complétée","F",IF(OR($H17="En cours",$H17="En revue"),"E",IF($H17="Bloquée","B","P"))),"")) | K17: =IF(OR($F17="",$G17=""),"",IF(AND(K$5<=$G17,K$5+6>=$F17),IF($H17="Complétée","F",IF(OR($H17="En cours",$H17="En revue"),"E",IF($H17="Bloquée","B","P"))),"")) | L17: =IF(OR($F17="",$G17=""),"",IF(AND(L$5<=$G17,L$5+6>=$F17),IF($H17="Complétée","F",IF(OR($H17="En cours",$H17="En revue"),"E",IF($H17="Bloquée","B","P"))),"")) | M17: =IF(OR($F17="",$G17=""),"",IF(AND(M$5<=$G17,M$5+6>=$F17),IF($H17="Complétée","F",IF(OR($H17="En cours",$H17="En revue"),"E",IF($H17="Bloquée","B","P"))),"")) | N17: =IF(OR($F17="",$G17=""),"",IF(AND(N$5<=$G17,N$5+6>=$F17),IF($H17="Complétée","F",IF(OR($H17="En cours",$H17="En revue"),"E",IF($H17="Bloquée","B","P"))),"")) | O17: =IF(OR($F17="",$G17=""),"",IF(AND(O$5<=$G17,O$5+6>=$F17),IF($H17="Complétée","F",IF(OR($H17="En cours",$H17="En revue"),"E",IF($H17="Bloquée","B","P"))),"")) | P17: =IF(OR($F17="",$G17=""),"",IF(AND(P$5<=$G17,P$5+6>=$F17),IF($H17="Complétée","F",IF(OR($H17="En cours",$H17="En revue"),"E",IF($H17="Bloquée","B","P"))),"")) | ... AW17: =IF(OR($F17="",$G17=""),"",IF(AND(AW$5<=$G17,AW$5+6>=$F17),IF($H17="Complétée","F",IF(OR($H17="En cours",$H17="En revue"),"E",IF($H17="Bloquée","B","P"))),""))
... B325: =IF(Taches!B325="","",Taches!B325) | C325: =IF(Taches!B325="","",Taches!F325) | D325: =IF(Taches!B325="","",Taches!C325) | E325: =IF(Taches!B325="","",Taches!D325) | F325: =IF(Taches!P325="","",Taches!P325) | G325: =IF(Taches!Q325="","",Taches!Q325) | H325: =IF(Taches!B325="","",Taches!J325) | I325: =IF(OR($F325="",$G325=""),"",IF(AND(I$5<=$G325,I$5+6>=$F325),IF($H325="Complétée","F",IF(OR($H325="En cours",$H325="En revue"),"E",IF($H325="Bloquée","B","P"))),"")) | J325: =IF(OR($F325="",$G325=""),"",IF(AND(J$5<=$G325,J$5+6>=$F325),IF($H325="Complétée","F",IF(OR($H325="En cours",$H325="En revue"),"E",IF($H325="Bloquée","B","P"))),"")) | K325: =IF(OR($F325="",$G325=""),"",IF(AND(K$5<=$G325,K$5+6>=$F325),IF($H325="Complétée","F",IF(OR($H325="En cours",$H325="En revue"),"E",IF($H325="Bloquée","B","P"))),"")) | L325: =IF(OR($F325="",$G325=""),"",IF(AND(L$5<=$G325,L$5+6>=$F325),IF($H325="Complétée","F",IF(OR($H325="En cours",$H325="En revue"),"E",IF($H325="Bloquée","B","P"))),"")) | M325: =IF(OR($F325="",$G325=""),"",IF(AND(M$5<=$G325,M$5+6>=$F325),IF($H325="Complétée","F",IF(OR($H325="En cours",$H325="En revue"),"E",IF($H325="Bloquée","B","P"))),"")) | N325: =IF(OR($F325="",$G325=""),"",IF(AND(N$5<=$G325,N$5+6>=$F325),IF($H325="Complétée","F",IF(OR($H325="En cours",$H325="En revue"),"E",IF($H325="Bloquée","B","P"))),"")) | O325: =IF(OR($F325="",$G325=""),"",IF(AND(O$5<=$G325,O$5+6>=$F325),IF($H325="Complétée","F",IF(OR($H325="En cours",$H325="En revue"),"E",IF($H325="Bloquée","B","P"))),"")) | P325: =IF(OR($F325="",$G325=""),"",IF(AND(P$5<=$G325,P$5+6>=$F325),IF($H325="Complétée","F",IF(OR($H325="En cours",$H325="En revue"),"E",IF($H325="Bloquée","B","P"))),"")) | ... AW325: =IF(OR($F325="",$G325=""),"",IF(AND(AW$5<=$G325,AW$5+6>=$F325),IF($H325="Complétée","F",IF(OR($H325="En cours",$H325="En revue"),"E",IF($H325="Bloquée","B","P"))),""))

Sheet Jalons
B2: Jalons
B3: Dates cibles et statut à saisir ; jours restants, avancement de la version et alerte de dépassement sont calculés.
B5: ID | C5: Jalon | D5: Version | E5: Date cible | F5: Statut | G5: Jours restants | H5: Avancement version | I5: Alerte | J5: Prochain (calcul) | K5: Commentaire
B6: J01 | C6: Confirmation de l'équipe de développement par M. Bruno | D6: V1 | E6: 46279 | F6: À venir | G6: =IF(F6="Atteint","",E6-TODAY()) | H6: =IFERROR(VLOOKUP($D6,Versions!$B$6:$P$10,9,FALSE),0) | I6: =IF(AND(F6<>"Atteint",F6<>"Abandonné",TODAY()>E6),"Dépassé",IF(AND(F6<>"Atteint",F6<>"Abandonné",E6-TODAY()<=7),"Cette semaine","")) | J6: =IF(AND(F6<>"Atteint",F6<>"Abandonné",E6>=TODAY()),E6,"") | K6: Conditionne la tenue du périmètre V1
B7: J02 | C7: Réponse sur la disponibilité d'une API CFE / RCCM | D7: V1 | E7: 46281 | F7: À venir | G7: =IF(F7="Atteint","",E7-TODAY()) | H7: =IFERROR(VLOOKUP($D7,Versions!$B$6:$P$10,9,FALSE),0) | I7: =IF(AND(F7<>"Atteint",F7<>"Abandonné",TODAY()>E7),"Dépassé",IF(AND(F7<>"Atteint",F7<>"Abandonné",E7-TODAY()<=7),"Cette semaine","")) | J7: =IF(AND(F7<>"Atteint",F7<>"Abandonné",E7>=TODAY()),E7,"") | K7: Sinon saisie manuelle supervisée
B8: J03 | C8: Gel du périmètre V1 | D8: V1 | E8: 46283 | F8: À venir | G8: =IF(F8="Atteint","",E8-TODAY()) | H8: =IFERROR(VLOOKUP($D8,Versions!$B$6:$P$10,9,FALSE),0) | I8: =IF(AND(F8<>"Atteint",F8<>"Abandonné",TODAY()>E8),"Dépassé",IF(AND(F8<>"Atteint",F8<>"Abandonné",E8-TODAY()<=7),"Cette semaine","")) | J8: =IF(AND(F8<>"Atteint",F8<>"Abandonné",E8>=TODAY()),E8,"") | K8: Plus aucun ajout après cette date
B9: J04 | C9: Designer UI/UX confirmé | D9: V1 | E9: 46283 | F9: À venir | G9: =IF(F9="Atteint","",E9-TODAY()) | H9: =IFERROR(VLOOKUP($D9,Versions!$B$6:$P$10,9,FALSE),0) | I9: =IF(AND(F9<>"Atteint",F9<>"Abandonné",TODAY()>E9),"Dépassé",IF(AND(F9<>"Atteint",F9<>"Abandonné",E9-TODAY()<=7),"Cette semaine","")) | J9: =IF(AND(F9<>"Atteint",F9<>"Abandonné",E9>=TODAY()),E9,"") | K9: Proposition Bouley à confirmer
B10: J05 | C10: Recette interne V1 terminée | D10: V1 | E10: 46309 | F10: À venir | G10: =IF(F10="Atteint","",E10-TODAY()) | H10: =IFERROR(VLOOKUP($D10,Versions!$B$6:$P$10,9,FALSE),0) | I10: =IF(AND(F10<>"Atteint",F10<>"Abandonné",TODAY()>E10),"Dépassé",IF(AND(F10<>"Atteint",F10<>"Abandonné",E10-TODAY()<=7),"Cette semaine","")) | J10: =IF(AND(F10<>"Atteint",F10<>"Abandonné",E10>=TODAY()),E10,"") | K10: Zéro anomalie bloquante ; QA du 13 au 15/10
B11: J06 | C11: Fin de développement V1 (hors QA) | D11: V1 | E11: 46307 | F11: À venir | G11: =IF(F11="Atteint","",E11-TODAY()) | H11: =IFERROR(VLOOKUP($D11,Versions!$B$6:$P$10,9,FALSE),0) | I11: =IF(AND(F11<>"Atteint",F11<>"Abandonné",TODAY()>E11),"Dépassé",IF(AND(F11<>"Atteint",F11<>"Abandonné",E11-TODAY()<=7),"Cette semaine","")) | J11: =IF(AND(F11<>"Atteint",F11<>"Abandonné",E11>=TODAY()),E11,"") | K11: Le développement s'arrête, la QA prend le relais du 13 au 15/10
B12: J07 | C12: Démonstration V1 à M. Bruno et à la CCI-Togo | D12: V1 | E12: 46310 | F12: À venir | G12: =IF(F12="Atteint","",E12-TODAY()) | H12: =IFERROR(VLOOKUP($D12,Versions!$B$6:$P$10,9,FALSE),0) | I12: =IF(AND(F12<>"Atteint",F12<>"Abandonné",TODAY()>E12),"Dépassé",IF(AND(F12<>"Atteint",F12<>"Abandonné",E12-TODAY()<=7),"Cette semaine","")) | J12: =IF(AND(F12<>"Atteint",F12<>"Abandonné",E12>=TODAY()),E12,"") | K12: Échéance ferme
B13: J08 | C13: Contrat prestataire de signature qualifiée (PSC) signé | D13: V2 | E13: 46325 | F13: À venir | G13: =IF(F13="Atteint","",E13-TODAY()) | H13: =IFERROR(VLOOKUP($D13,Versions!$B$6:$P$10,9,FALSE),0) | I13: =IF(AND(F13<>"Atteint",F13<>"Abandonné",TODAY()>E13),"Dépassé",IF(AND(F13<>"Atteint",F13<>"Abandonné",E13-TODAY()<=7),"Cette semaine","")) | J13: =IF(AND(F13<>"Atteint",F13<>"Abandonné",E13>=TODAY()),E13,"") | K13: Bloquant pour l'intégration NDA
B14: J09 | C14: Livraison V2 | D14: V2 | E14: 46366 | F14: À venir | G14: =IF(F14="Atteint","",E14-TODAY()) | H14: =IFERROR(VLOOKUP($D14,Versions!$B$6:$P$10,9,FALSE),0) | I14: =IF(AND(F14<>"Atteint",F14<>"Abandonné",TODAY()>E14),"Dépassé",IF(AND(F14<>"Atteint",F14<>"Abandonné",E14-TODAY()<=7),"Cette semaine","")) | J14: =IF(AND(F14<>"Atteint",F14<>"Abandonné",E14>=TODAY()),E14,"")
B15: J10 | C15: Avis juridique écrit sur le RPS et le barème de frais | D15: V3 | E15: 46402 | F15: À venir | G15: =IF(F15="Atteint","",E15-TODAY()) | H15: =IFERROR(VLOOKUP($D15,Versions!$B$6:$P$10,9,FALSE),0) | I15: =IF(AND(F15<>"Atteint",F15<>"Abandonné",TODAY()>E15),"Dépassé",IF(AND(F15<>"Atteint",F15<>"Abandonné",E15-TODAY()<=7),"Cette semaine","")) | J15: =IF(AND(F15<>"Atteint",F15<>"Abandonné",E15>=TODAY()),E15,"") | K15: Conditionne l'activation du barème
B16: J11 | C16: Pentest indépendant réalisé et remédié | D16: V3 | E16: 46428 | F16: À venir | G16: =IF(F16="Atteint","",E16-TODAY()) | H16: =IFERROR(VLOOKUP($D16,Versions!$B$6:$P$10,9,FALSE),0) | I16: =IF(AND(F16<>"Atteint",F16<>"Abandonné",TODAY()>E16),"Dépassé",IF(AND(F16<>"Atteint",F16<>"Abandonné",E16-TODAY()<=7),"Cette semaine","")) | J16: =IF(AND(F16<>"Atteint",F16<>"Abandonné",E16>=TODAY()),E16,"") | K16: Porte G10
B17: J12 | C17: Portes de conformité G1 à G10 fermées | D17: V3 | E17: 46430 | F17: À venir | G17: =IF(F17="Atteint","",E17-TODAY()) | H17: =IFERROR(VLOOKUP($D17,Versions!$B$6:$P$10,9,FALSE),0) | I17: =IF(AND(F17<>"Atteint",F17<>"Abandonné",TODAY()>E17),"Dépassé",IF(AND(F17<>"Atteint",F17<>"Abandonné",E17-TODAY()<=7),"Cette semaine","")) | J17: =IF(AND(F17<>"Atteint",F17<>"Abandonné",E17>=TODAY()),E17,"") | K17: Condition de lancement commercial
B18: J13 | C18: Livraison V3 | D18: V3 | E18: 46436 | F18: À venir | G18: =IF(F18="Atteint","",E18-TODAY()) | H18: =IFERROR(VLOOKUP($D18,Versions!$B$6:$P$10,9,FALSE),0) | I18: =IF(AND(F18<>"Atteint",F18<>"Abandonné",TODAY()>E18),"Dépassé",IF(AND(F18<>"Atteint",F18<>"Abandonné",E18-TODAY()<=7),"Cette semaine","")) | J18: =IF(AND(F18<>"Atteint",F18<>"Abandonné",E18>=TODAY()),E18,"")
B19: J14 | C19: Cadrage de l'intégration Remo.co validé | D19: V1 | E19: 46283 | F19: À venir | G19: =IF(F19="Atteint","",E19-TODAY()) | H19: =IFERROR(VLOOKUP($D19,Versions!$B$6:$P$10,9,FALSE),0) | I19: =IF(AND(F19<>"Atteint",F19<>"Abandonné",TODAY()>E19),"Dépassé",IF(AND(F19<>"Atteint",F19<>"Abandonné",E19-TODAY()<=7),"Cette semaine","")) | J19: =IF(AND(F19<>"Atteint",F19<>"Abandonné",E19>=TODAY()),E19,"") | K19: Bloque le connecteur Remo
B20: J15 | C20: Livraison V4 | D20: V4 | E20: 46478 | F20: À venir | G20: =IF(F20="Atteint","",E20-TODAY()) | H20: =IFERROR(VLOOKUP($D20,Versions!$B$6:$P$10,9,FALSE),0) | I20: =IF(AND(F20<>"Atteint",F20<>"Abandonné",TODAY()>E20),"Dépassé",IF(AND(F20<>"Atteint",F20<>"Abandonné",E20-TODAY()<=7),"Cette semaine","")) | J20: =IF(AND(F20<>"Atteint",F20<>"Abandonné",E20>=TODAY()),E20,"")
B21: J16 | C21: Contrat fournisseur IA signé | D21: V5 | E21: 46486 | F21: À venir | G21: =IF(F21="Atteint","",E21-TODAY()) | H21: =IFERROR(VLOOKUP($D21,Versions!$B$6:$P$10,9,FALSE),0) | I21: =IF(AND(F21<>"Atteint",F21<>"Abandonné",TODAY()>E21),"Dépassé",IF(AND(F21<>"Atteint",F21<>"Abandonné",E21-TODAY()<=7),"Cette semaine","")) | J21: =IF(AND(F21<>"Atteint",F21<>"Abandonné",E21>=TODAY()),E21,"") | K21: Bloquant pour DealLens
B22: J17 | C22: Livraison V5 | D22: V5 | E22: 46541 | F22: À venir | G22: =IF(F22="Atteint","",E22-TODAY()) | H22: =IFERROR(VLOOKUP($D22,Versions!$B$6:$P$10,9,FALSE),0) | I22: =IF(AND(F22<>"Atteint",F22<>"Abandonné",TODAY()>E22),"Dépassé",IF(AND(F22<>"Atteint",F22<>"Abandonné",E22-TODAY()<=7),"Cette semaine","")) | J22: =IF(AND(F22<>"Atteint",F22<>"Abandonné",E22>=TODAY()),E22,"")

Sheet Risques
B2: Registre des risques
B3: Score = probabilité x impact (1 à 5). Niveau et alerte calculés. Statut et mitigation à tenir à jour.
B5: ID | C5: Risque | D5: Catégorie | E5: Probabilité (1-5) | F5: Impact (1-5) | G5: Score | H5: Niveau | I5: Version | J5: Responsable | K5: Mitigation | L5: Statut
B6: R01 | C6: Équipe de développement non confirmée ou sous-dimensionnée | D6: Organisation | E6: 4 | F6: 5 | G6: =E6*F6 | H6: =IF(G6>=15,"Critique",IF(G6>=8,"Élevé",IF(G6>=4,"Moyen","Faible"))) | I6: V1 | J6: Chef de projet | K6: Décision de M. Bruno avant J01 ; sinon retrait de la démo RPS puis du matching automatisé | L6: Ouvert
B7: R02 | C7: Aucune API CFE / RCCM disponible | D7: Dépendance externe | E7: 3 | F7: 4 | G7: =E7*F7 | H7: =IF(G7>=15,"Critique",IF(G7>=8,"Élevé",IF(G7>=4,"Moyen","Faible"))) | I7: V1 | J7: Chef de projet | K7: Adaptateur à double mode : API ou saisie manuelle supervisée | L7: Ouvert
B8: R03 | C8: Designer UI/UX non disponible de bout en bout | D8: Organisation | E8: 3 | F8: 3 | G8: =E8*F8 | H8: =IF(G8>=15,"Critique",IF(G8>=8,"Élevé",IF(G8>=4,"Moyen","Faible"))) | I8: V1 | J8: M. Bruno | K8: Confirmer la proposition Bouley avant J04 | L8: Ouvert
B9: R04 | C9: Périmètre V1 qui s'élargit pendant le mois | D9: Périmètre | E9: 4 | F9: 4 | G9: =E9*F9 | H9: =IF(G9>=15,"Critique",IF(G9>=8,"Élevé",IF(G9>=4,"Moyen","Faible"))) | I9: V1 | J9: Chef de projet | K9: Gel du périmètre à J03, toute demande passe par l'onglet Decisions | L9: Ouvert
B10: R05 | C10: Démonstration perçue comme un produit fini (sur-promesse) | D10: Communication | E10: 3 | F10: 4 | G10: =E10*F10 | H10: =IF(G10>=15,"Critique",IF(G10>=8,"Élevé",IF(G10>=4,"Moyen","Faible"))) | I10: V1 | J10: M. Bruno | K10: Note de cadrage V1, étiquette 'démonstration synthétique' sur chaque écran | L10: Ouvert
B11: R06 | C11: Prestataire de signature qualifiée non contractualisé à temps | D11: Dépendance externe | E11: 3 | F11: 4 | G11: =E11*F11 | H11: =IF(G11>=15,"Critique",IF(G11>=8,"Élevé",IF(G11>=4,"Moyen","Faible"))) | I11: V2 | J11: M. Bruno | K11: Lancer la consultation des PSC accrédités dès la fin de V1 | L11: Ouvert
B12: R07 | C12: Retard des portes de conformité (IPDCP, DPO, pentest) | D12: Réglementaire | E12: 3 | F12: 5 | G12: =E12*F12 | H12: =IF(G12>=15,"Critique",IF(G12>=8,"Élevé",IF(G12>=4,"Moyen","Faible"))) | I12: V3 | J12: Conseil juridique / DPO | K12: Démarrer les démarches IPDCP pendant V2 | L12: Ouvert
B13: R08 | C13: Partenaire fiscal non identifié | D13: Dépendance externe | E13: 3 | F13: 2 | G13: =E13*F13 | H13: =IF(G13>=15,"Critique",IF(G13>=8,"Élevé",IF(G13>=4,"Moyen","Faible"))) | I13: V3 | J13: M. Bruno | K13: Confirmer TaxeFacile ou qualifier une alternative avant V3 | L13: Ouvert
B14: R09 | C14: Périmètre de l'intégration Remo.co plus large que prévu | D14: Technique | E14: 2 | F14: 3 | G14: =E14*F14 | H14: =IF(G14>=15,"Critique",IF(G14>=8,"Élevé",IF(G14>=4,"Moyen","Faible"))) | I14: V4 | J14: Chef de projet | K14: Cadrage écrit avant chiffrage définitif (J14) | L14: Ouvert
B15: R10 | C15: Fournisseur IA sans clauses de confidentialité acceptables | D15: Dépendance externe | E15: 3 | F15: 5 | G15: =E15*F15 | H15: =IF(G15>=15,"Critique",IF(G15>=8,"Élevé",IF(G15>=4,"Moyen","Faible"))) | I15: V5 | J15: Conseil juridique | K15: Consultation dès V3, clauses de non-réutilisation des données | L15: Ouvert
B16: R11 | C16: Fuite de divulgation T0 / T1 sur un dossier titres en production | D16: Sécurité | E16: 2 | F16: 5 | G16: =E16*F16 | H16: =IF(G16>=15,"Critique",IF(G16>=8,"Élevé",IF(G16>=4,"Moyen","Faible"))) | I16: V2 | J16: Équipe de développement | K16: Allow-list serveur, tests DISCLOSURE_LEAK sur les 12 cas de référence | L16: Surveillé
B17: R12 | C17: Sur-ingénierie par rapport au plafond du pilote (2 000 comptes) | D17: Technique | E17: 2 | F17: 2 | G17: =E17*F17 | H17: =IF(G17>=15,"Critique",IF(G17>=8,"Élevé",IF(G17>=4,"Moyen","Faible"))) | I17: V2 | J17: Chef de projet | K17: Revue d'architecture à chaque version contre le plafond de capacité | L17: Surveillé
B18: R13 | C18: Pentest indépendant reporté en V3 : la démonstration V1 tourne sans audit externe | D18: Sécurité | E18: 3 | F18: 4 | G18: =E18*F18 | H18: =IF(G18>=15,"Critique",IF(G18>=8,"Élevé",IF(G18>=4,"Moyen","Faible"))) | I18: V1 | J18: Chef de projet | K18: Revue de sécurité interne et scan de dépendances en V1 (lot Sécurité) ; aucun environnement accessible publiquement avant V3 ; commander le pentest dès V2 | L18: Ouvert

Sheet Securite
B2: Registre de sécurité
B3: Chaque constat, son traitement, sa version cible et la tâche qui le porte. Le statut de la tâche est lu automatiquement dans l'onglet Taches.
B5: ID | C5: Constat | D5: Risque si non traité | E5: Traitement et justification du calendrier | F5: Version cible | G5: Tâche liée (onglet Taches) | H5: Statut de la tâche | I5: Avancement | J5: Commentaire
B6: S01 | C6: L'API se connecte avec le rôle propriétaire de la base : les politiques RLS existent mais ne s'exercent pas | D6: Un défaut d'autorisation applicatif expose les dossiers d'un autre cédant | E6: Rôle dealpme_api sans contournement, contexte par transaction, test négatif | F6: V1 | G6: RLS effective : rôle applicatif sans contournement, contexte app.organisation_id et app.roles par transaction | H6: =IF($G6="","Sans tâche",IFERROR(INDEX(Taches!$J$6:$J$325,MATCH($G6,Taches!$F$6:$F$325,0)),"À planifier")) | I6: =IF($G6="","",IFERROR(INDEX(Taches!$L$6:$L$325,MATCH($G6,Taches!$F$6:$F$325,0)),0))
B7: S02 | C7: Aucune limitation de débit ni verrouillage après échecs de connexion | D7: Force brute sur /auth/login et sur les codes OTP | E7: Limitation par IP et par compte, verrouillage progressif, journal des échecs | F7: V1 | G7: Anti-force-brute : limitation de débit par IP et par compte, verrouillage progressif, journal des échecs | H7: =IF($G7="","Sans tâche",IFERROR(INDEX(Taches!$J$6:$J$325,MATCH($G7,Taches!$F$6:$F$325,0)),"À planifier")) | I7: =IF($G7="","",IFERROR(INDEX(Taches!$L$6:$L$325,MATCH($G7,Taches!$F$6:$F$325,0)),0))
B8: S03 | C8: Pas de vérification email ni de second facteur effectif | D8: Usurpation d'un compte officier ou administrateur | E8: Vérification email, MFA obligatoire pour les officiers CCI-Togo et les administrateurs | F8: V1 | G8: Vérification email, MFA obligatoire pour les officiers CCI-Togo et les administrateurs, liaison OTP | H8: =IF($G8="","Sans tâche",IFERROR(INDEX(Taches!$J$6:$J$325,MATCH($G8,Taches!$F$6:$F$325,0)),"À planifier")) | I8: =IF($G8="","",IFERROR(INDEX(Taches!$L$6:$L$325,MATCH($G8,Taches!$F$6:$F$325,0)),0))
B9: S04 | C9: Champs CONFIDENTIAL_DEAL (prix, valorisation) en clair en base | D9: Un dump de la base révèle les conditions des cessions | E9: Chiffrement applicatif, clé hors base, rotation documentée | F9: V1 | G9: Chiffrement applicatif des champs CONFIDENTIAL_DEAL, clé gérée hors base, rotation documentée | H9: =IF($G9="","Sans tâche",IFERROR(INDEX(Taches!$J$6:$J$325,MATCH($G9,Taches!$F$6:$F$325,0)),"À planifier")) | I9: =IF($G9="","",IFERROR(INDEX(Taches!$L$6:$L$325,MATCH($G9,Taches!$F$6:$F$325,0)),0))
B10: S05 | C10: Pas d'en-têtes de sécurité HTTP, pas de CORS explicite | D10: Injection de contenu, appels depuis des origines inconnues | E10: CSP, HSTS, CORS strict, cookies sécurisés, taille maximale des requêtes | F10: V1 | G10: En-têtes de sécurité HTTP, CORS strict, cookies sécurisés, taille maximale des corps de requête | H10: =IF($G10="","Sans tâche",IFERROR(INDEX(Taches!$J$6:$J$325,MATCH($G10,Taches!$F$6:$F$325,0)),"À planifier")) | I10: =IF($G10="","",IFERROR(INDEX(Taches!$L$6:$L$325,MATCH($G10,Taches!$F$6:$F$325,0)),0))
B11: S06 | C11: Idempotence en mémoire ; signatures de webhooks non vérifiées (faux connecteurs) | D11: Double effet sur rejeu ; webhook forgé accepté | E11: Idempotence en base, HMAC vérifié sur chaque webhook, test de rejeu | F11: V1 | G11: Idempotence persistée en base et vérification de signature HMAC sur tous les webhooks | H11: =IF($G11="","Sans tâche",IFERROR(INDEX(Taches!$J$6:$J$325,MATCH($G11,Taches!$F$6:$F$325,0)),"À planifier")) | I11: =IF($G11="","",IFERROR(INDEX(Taches!$L$6:$L$325,MATCH($G11,Taches!$F$6:$F$325,0)),0))
B12: S07 | C12: Mot de passe commun du jeu de démonstration | D12: Accès trivial si le jeu est chargé sur un environnement accessible | E12: Mots de passe uniques, chargement refusé hors développement | F12: V1 | G12: Mots de passe de démonstration uniques par compte, jeu de démonstration interdit hors environnement local | H12: =IF($G12="","Sans tâche",IFERROR(INDEX(Taches!$J$6:$J$325,MATCH($G12,Taches!$F$6:$F$325,0)),"À planifier")) | I12: =IF($G12="","",IFERROR(INDEX(Taches!$L$6:$L$325,MATCH($G12,Taches!$F$6:$F$325,0)),0))
B13: S08 | C13: Aucun scan de dépendances exécuté | D13: Vulnérabilité connue embarquée sans alerte | E13: Scan bloquant en CI sur vulnérabilité critique, revue interne selon la liste de contrôle v0 | F13: V1 | G13: Revue de sécurité interne (liste de contrôle v0 : paliers, URL pré-signées, compteur RPS) et scan de dépendances bloquant en CI | H13: =IF($G13="","Sans tâche",IFERROR(INDEX(Taches!$J$6:$J$325,MATCH($G13,Taches!$F$6:$F$325,0)),"À planifier")) | I13: =IF($G13="","",IFERROR(INDEX(Taches!$L$6:$L$325,MATCH($G13,Taches!$F$6:$F$325,0)),0))
B14: S09 | C14: Aucun pentest indépendant | D14: Failles non détectées par l'équipe elle-même | E14: Reporté en V3 (porte G10) : exige un prestataire externe et un périmètre stabilisé ; mitigation V1 = revue interne S08, aucun environnement public avant V3 ; commander le pentest dès V2 | F14: V3 | G14: Pentest indépendant et remédiation des constats critiques et élevés (G10) | H14: =IF($G14="","Sans tâche",IFERROR(INDEX(Taches!$J$6:$J$325,MATCH($G14,Taches!$F$6:$F$325,0)),"À planifier")) | I14: =IF($G14="","",IFERROR(INDEX(Taches!$L$6:$L$325,MATCH($G14,Taches!$F$6:$F$325,0)),0))
B15: S10 | C15: Documents servis sans rendu serveur ni filigrane (data room absente en V1) | D15: Fuite de documents confidentiels | E15: Reporté en V2 avec la data room : rendu serveur, filigrane, URL pré-signées courtes, révocation en moins de 60 s ; V1 ne stocke aucun document de data room | F15: V2 | G15: Visualiseur rendu serveur, page à page, chargement progressif (3G) | H15: =IF($G15="","Sans tâche",IFERROR(INDEX(Taches!$J$6:$J$325,MATCH($G15,Taches!$F$6:$F$325,0)),"À planifier")) | I15: =IF($G15="","",IFERROR(INDEX(Taches!$L$6:$L$325,MATCH($G15,Taches!$F$6:$F$325,0)),0))
B16: S11 | C16: Preuve de signature non qualifiée (pas de NDA en V1) | D16: NDA non opposable | E16: Reporté en V2 : prestataire PSC accrédité ARCEP, archivage PSAE ; V1 n'exécute aucun NDA | F16: V2 | G16: Intégration API de signature qualifiée, webhooks à signature vérifiée | H16: =IF($G16="","Sans tâche",IFERROR(INDEX(Taches!$J$6:$J$325,MATCH($G16,Taches!$F$6:$F$325,0)),"À planifier")) | I16: =IF($G16="","",IFERROR(INDEX(Taches!$L$6:$L$325,MATCH($G16,Taches!$F$6:$F$325,0)),0))
B17: S12 | C17: Accès administrateur non tracé par mode break-glass | D17: Accès silencieux à des dossiers confidentiels | E17: Reporté en V3 avec le module support ; V1 : journal d'audit persisté sur toute action sensible, aucun endpoint d'accès aux données confidentielles pour l'administrateur | F17: V3 | G17: Mode 'break-glass' journalisé pour l'administration | H17: =IF($G17="","Sans tâche",IFERROR(INDEX(Taches!$J$6:$J$325,MATCH($G17,Taches!$F$6:$F$325,0)),"À planifier")) | I17: =IF($G17="","",IFERROR(INDEX(Taches!$L$6:$L$325,MATCH($G17,Taches!$F$6:$F$325,0)),0))
B18: S13 | C18: Vérification d'identité documentaire sans biométrie | D18: Usurpation d'identité au-delà de ce que le document capture | E18: Voulu par le v0 : biométrie interdite sans autorisation IPDCP (drapeau FEATURE_BIOMETRIC_KYC fermé) ; revue humaine et recoupement RCCM en V1 | F18: P2 | H18: =IF($G18="","Sans tâche",IFERROR(INDEX(Taches!$J$6:$J$325,MATCH($G18,Taches!$F$6:$F$325,0)),"À planifier")) | I18: =IF($G18="","",IFERROR(INDEX(Taches!$L$6:$L$325,MATCH($G18,Taches!$F$6:$F$325,0)),0))
B19: S14 | C19: Portes de conformité G1 à G10 non fermées (IPDCP, DPO, avis juridiques) | D19: Lancement commercial juridiquement exposé | E19: Reporté en V3 : condition explicite de lancement ; V1 est une démonstration à données synthétiques, jamais un service public | F19: V3 | G19: Déclaration IPDCP et autorisation de transfert transfrontalier (G1, G2) | H19: =IF($G19="","Sans tâche",IFERROR(INDEX(Taches!$J$6:$J$325,MATCH($G19,Taches!$F$6:$F$325,0)),"À planifier")) | I19: =IF($G19="","",IFERROR(INDEX(Taches!$L$6:$L$325,MATCH($G19,Taches!$F$6:$F$325,0)),0))
B21: Règle | C21: Aucune tâche ne passe en Complétée sans son test négatif. Tout report de sécurité doit figurer ici avec sa justification, sa mitigation intermédiaire et sa version cible ; un report sans mitigation est refusé.

Sheet Decisions
B2: Journal des décisions et arbitrages
B3: Toute demande de changement de périmètre passe par ce journal. Statut à mettre à jour au fil des réponses.
B5: ID | C5: Date | D5: Sujet | E5: Décision ou question | F5: Statut | G5: Décideur | H5: Impact | I5: Prochaine action | J5: Échéance
B6: D01 | C6: 09/09/2026 | D6: Périmètre cible | E6: Le cahier des charges v0 approuvé et le Référentiel P04-P25 sont retenus comme cible finale ; le blueprint v5 n'est pas retenu. | F6: Tranché | G6: M. Bruno | H6: Cadre toute la feuille de route
B7: D02 | C7: 09/09/2026 | D7: Deal-Connect / Guichet Diaspora | E7: Remo.co retenu comme connecteur externe pour les salons et rendez-vous virtuels. | F7: Tranché | G7: M. Bruno | H7: Intégration dès V1 ; périmètre d'intégration à cadrer | I7: Cadrage écrit sur la documentation API Remo | J7: 18/09/2026
B8: D04 | C8: 10/09/2026 | D8: Lot Sécurité en V1 | E8: Huit constats de sécurité traités avant la présentation (RLS effective, anti-force-brute, MFA, chiffrement applicatif, en-têtes, idempotence et signatures, revue interne, mots de passe de démonstration). Le pentest indépendant reste en V3 (porte G10). | F8: Tranché | G8: Chef de projet | H8: +19 j/p sur V1 (total 236) ; voir l'onglet Securite | I8: Commencer par la RLS effective | J8: 18/09/2026
B9: D03 | C9: 09/09/2026 | D9: Démonstration RPS en V1 | E9: V1 inclut une démonstration maquettée du blocage de publication d'une cession de titres ; le circuit réel reste en V2. | F9: Tranché | G9: Chef de projet | H9: +20 j/p sur V1
B10: A01 | C10: 09/09/2026 | D10: Équipe de développement | E10: Taille et séniorité de l'équipe disponible dès maintenant ? | F10: Ouvert | G10: M. Bruno | H10: Détermine si V1 tient en 5 semaines ou nécessite des coupes | I10: Réponse attendue avant J01 | J10: 14/09/2026
B11: A02 | C11: 09/09/2026 | D11: API CFE / RCCM | E11: Une API existe-t-elle, ou faut-il un échange de fichier supervisé ? | F11: Ouvert | G11: CCI-Togo | H11: Bloque le lot Espace CCI-Togo | I11: Vérifier avant le démarrage du lot | J11: 16/09/2026
B12: A03 | C12: 09/09/2026 | D12: Designer UI/UX | E12: Confirmation d'un designer de bout en bout (proposition Bouley) ? | F12: Ouvert | G12: M. Bruno | H12: Sans lui, la charge frontend absorbe la conception | I12: Décision avant J04 | J12: 18/09/2026
B13: A04 | C13: 09/09/2026 | D13: Statut Deal-Experts (P13) | E13: Processus contractuel déjà opposable, ou cible future ? | F13: Ouvert | G13: CCI-Togo | H13: Change le dimensionnement du module EXP et sa version | I13: Clarifier avec la CCI-Togo avant V4 | J13: 31/01/2027
B14: A05 | C14: 09/09/2026 | D14: Numérotation P01-P03 | E14: Processus manquants ou numérotation volontaire à partir de P04 ? | F14: Ouvert | G14: CCI-Togo | H14: Faible impact sur le plan | I14: Confirmer avec le juridique
B15: A06 | C15: 09/09/2026 | D15: Partenaire fiscal | E15: 'TaxeFacile' est-il le partenaire réel, ou faut-il en qualifier un ? | F15: Ouvert | G15: M. Bruno | H15: Impacte le lot Conformité fiscale de V3 | I15: Qualifier avant V3 | J15: 30/11/2026
B16: A07 | C16: 09/09/2026 | D16: Charte du COPIL | E16: Composition, cadence exacte, règles de vote ? | F16: Ouvert | G16: CCI-Togo | H16: Gouvernance inter-version | I16: Récupérer l'annexe de la Convention
B17: A08 | C17: 09/09/2026 | D17: Fournisseur IA (DealLens) | E17: Quel fournisseur, avec quelles clauses de confidentialité ? | F17: Ouvert | G17: Conseil juridique | H17: Bloque tout le lot V5 | I17: Lancer la consultation dès V3 | J17: 09/04/2027

Sheet Processus
B2: Référentiel de processus P04 à P25
B3: Chaque processus contractuel est rattaché à son module principal ; l'avancement est hérité du module.
B5: Code | C5: Bloc | D5: Processus | E5: Propriétaire (référentiel) | F5: Module principal | G5: Version cible | H5: Avancement module | I5: État module
B6: P04 | C6: A. Préparer la transmission | D6: Pass Transmission : constitution et qualification du dossier cédant | E6: Responsable Opérations DealPME | F6: MKT | G6: =IFERROR(VLOOKUP($F6,Modules!$B$6:$Q$25,5,FALSE),"") | H6: =IFERROR(VLOOKUP($F6,Modules!$B$6:$Q$25,8,FALSE),0) | I6: =IFERROR(VLOOKUP($F6,Modules!$B$6:$Q$25,14,FALSE),"")
B7: P05 | C7: A. Préparer la transmission | D7: Évaluation financière sommaire et non opposable | E7: Responsable Produit DealPME | F7: MKT | G7: =IFERROR(VLOOKUP($F7,Modules!$B$6:$Q$25,5,FALSE),"") | H7: =IFERROR(VLOOKUP($F7,Modules!$B$6:$Q$25,8,FALSE),0) | I7: =IFERROR(VLOOKUP($F7,Modules!$B$6:$Q$25,14,FALSE),"")
B8: P06 | C8: A. Préparer la transmission | D8: Deal-Ready : diagnostic, remédiation et certification CCI-Togo | E8: Responsable Institutionnel CCI-Togo | F8: CCI | G8: =IFERROR(VLOOKUP($F8,Modules!$B$6:$Q$25,5,FALSE),"") | H8: =IFERROR(VLOOKUP($F8,Modules!$B$6:$Q$25,8,FALSE),0) | I8: =IFERROR(VLOOKUP($F8,Modules!$B$6:$Q$25,14,FALSE),"")
B9: P07 | C9: A. Préparer la transmission | D9: Qualification du mode de transmission et régime de confidentialité | E9: Responsable Conformité DealPME | F9: RPS | G9: =IFERROR(VLOOKUP($F9,Modules!$B$6:$Q$25,5,FALSE),"") | H9: =IFERROR(VLOOKUP($F9,Modules!$B$6:$Q$25,8,FALSE),0) | I9: =IFERROR(VLOOKUP($F9,Modules!$B$6:$Q$25,14,FALSE),"")
B10: P08 | C10: B. Qualifier et connecter | D10: Qualification du repreneur / investisseur | E10: Responsable Conformité DealPME | F10: IDN | G10: =IFERROR(VLOOKUP($F10,Modules!$B$6:$Q$25,5,FALSE),"") | H10: =IFERROR(VLOOKUP($F10,Modules!$B$6:$Q$25,8,FALSE),0) | I10: =IFERROR(VLOOKUP($F10,Modules!$B$6:$Q$25,14,FALSE),"")
B11: P09 | C11: B. Qualifier et connecter | D11: Recherche, matching et manifestation d'intérêt | E11: Responsable Produit DealPME | F11: MKT | G11: =IFERROR(VLOOKUP($F11,Modules!$B$6:$Q$25,5,FALSE),"") | H11: =IFERROR(VLOOKUP($F11,Modules!$B$6:$Q$25,8,FALSE),0) | I11: =IFERROR(VLOOKUP($F11,Modules!$B$6:$Q$25,14,FALSE),"")
B12: P10 | C12: B. Qualifier et connecter | D12: Admission et divulgation contrôlée | E12: Responsable Conformité DealPME | F12: RPS | G12: =IFERROR(VLOOKUP($F12,Modules!$B$6:$Q$25,5,FALSE),"") | H12: =IFERROR(VLOOKUP($F12,Modules!$B$6:$Q$25,8,FALSE),0) | I12: =IFERROR(VLOOKUP($F12,Modules!$B$6:$Q$25,14,FALSE),"")
B13: P11 | C13: B. Qualifier et connecter | D13: NDA, signature et constitution de la preuve | E13: Responsable Juridique et Conformité DealPME | F13: SIG | G13: =IFERROR(VLOOKUP($F13,Modules!$B$6:$Q$25,5,FALSE),"") | H13: =IFERROR(VLOOKUP($F13,Modules!$B$6:$Q$25,8,FALSE),0) | I13: =IFERROR(VLOOKUP($F13,Modules!$B$6:$Q$25,14,FALSE),"")
B14: P12 | C14: B. Qualifier et connecter | D14: VDR, autorisation d'accès et questions-réponses | E14: Responsable Produit et Sécurité DealPME | F14: VDR | G14: =IFERROR(VLOOKUP($F14,Modules!$B$6:$Q$25,5,FALSE),"") | H14: =IFERROR(VLOOKUP($F14,Modules!$B$6:$Q$25,8,FALSE),0) | I14: =IFERROR(VLOOKUP($F14,Modules!$B$6:$Q$25,14,FALSE),"")
B15: P13 | C15: B. Qualifier et connecter | D15: Mobilisation et gestion d'un expert indépendant | E15: Responsable Marketplace Services DealPME | F15: EXP | G15: =IFERROR(VLOOKUP($F15,Modules!$B$6:$Q$25,5,FALSE),"") | H15: =IFERROR(VLOOKUP($F15,Modules!$B$6:$Q$25,8,FALSE),0) | I15: =IFERROR(VLOOKUP($F15,Modules!$B$6:$Q$25,14,FALSE),"")
B16: P14 | C16: C. Négocier et réaliser | D16: Offre, contre-offre, LOI et documentation | E16: Responsable Transaction Workflow DealPME | F16: NEG | G16: =IFERROR(VLOOKUP($F16,Modules!$B$6:$Q$25,5,FALSE),"") | H16: =IFERROR(VLOOKUP($F16,Modules!$B$6:$Q$25,8,FALSE),0) | I16: =IFERROR(VLOOKUP($F16,Modules!$B$6:$Q$25,14,FALSE),"")
B17: P15 | C17: C. Négocier et réaliser | D17: Audit d'acquisition et résolution des points ouverts | E17: Responsable Transaction Workflow DealPME | F17: NEG | G17: =IFERROR(VLOOKUP($F17,Modules!$B$6:$Q$25,5,FALSE),"") | H17: =IFERROR(VLOOKUP($F17,Modules!$B$6:$Q$25,8,FALSE),0) | I17: =IFERROR(VLOOKUP($F17,Modules!$B$6:$Q$25,14,FALSE),"")
... B27: P25 | C27: E. Gouverner et opérer | D27: Exploitation, sécurité, incidents, continuité et SLA | E27: Responsable Technique DealPME | F27: OPS | G27: =IFERROR(VLOOKUP($F27,Modules!$B$6:$Q$25,5,FALSE),"") | H27: =IFERROR(VLOOKUP($F27,Modules!$B$6:$Q$25,8,FALSE),0) | I27: =IFERROR(VLOOKUP($F27,Modules!$B$6:$Q$25,14,FALSE),"")

Sheet Acteurs
B2: Acteurs et responsabilités (RACI)
B3: R = réalise, A = approuve (un seul par module), C = consulté, I = informé. Dérivé du Référentiel de processus.
B5: Rôle | C5: Organisation | D5: Personne / entité | E5: Responsabilités
B6: Chef de projet / architecte | C6: DealPME | D6: Abdou-Raouf | E6: Pilotage, architecture, arbitrages techniques, tenue de ce classeur
B7: Équipe de développement | C7: DealPME | D7: À confirmer | E7: Réalisation, tests, documentation
B8: Propriétaire produit | C8: DealPME | D8: M. Bruno H. | E8: Priorisation, validation des livrables, décisions de périmètre
B9: Référent institutionnel | C9: CCI-Togo | D9: À désigner | E9: Confirmation d'adhésion, certification Deal-Ready, promotion, COPIL
B10: Designer UI/UX | C10: Externe | D10: À confirmer (proposition Bouley) | E10: Conception des écrans, revue visuelle
B11: Conseil juridique / DPO | C11: Externe | D11: À désigner | E11: Avis RPS, revue des modèles, IPDCP, nomination DPO
B12: Prestataires techniques | C12: Externe | D12: PSC signature, mobile money, PSAE, Remo.co, fournisseur IA | E12: Intégrations sous contrat
B13: Experts indépendants | C13: Externe | D13: Registre à constituer | E13: Diagnostics Deal-Ready, missions d'expertise
B16: Matrice RACI par module
B17: Module | C17: Chef de projet | D17: Équipe dev | E17: Propriétaire produit | F17: CCI-Togo | G17: Designer UI/UX | H17: Juridique / DPO | I17: Prestataires | J17: Experts
B18: FOND Fondations : modèle de données et bifurcation actif / titre | C18: A | D18: R | E18: C | F18: I | H18: C
B19: TRV Transverse technique : infra, CI, design system, QA | C19: A | D19: R | E19: I | G19: C | I19: C
B20: IDN Identité, abonnement et facturation | C20: A | D20: R | E20: C | F20: I | G20: C | H20: C | I20: C
B21: GOV Console institutionnelle CCI-Togo et gouvernance | C21: C | D21: R | E21: C | F21: A | H21: C
B22: CCI Deal-Ready : certification CCI-Togo | C22: C | D22: R | E22: C | F22: A | H22: C | J22: C
B23: MKT Pass Transmission : dossier cédant, marketplace, évaluation indicative | C23: A | D23: R | E23: C | F23: I | G23: C | H23: C
B24: RPS Regulatory Perimeter Service : divulgation T0/T1/T2 | C24: C | D24: R | E24: C | F24: I | H24: A
B25: SIG Signature électronique et preuve | C25: A | D25: R | E25: C | F25: I | H25: C | I25: R
B26: VDR Data room et questions-réponses | C26: A | D26: R | E26: C | F26: I | G26: C | H26: C
B27: NEG Négociation : offre, LOI, audit d'acquisition | C27: A | D27: R | E27: C | F27: I | G27: C | H27: C
B28: REA Réalisation et traçabilité de la transmission | C28: A | D28: R | E28: C | F28: C | H28: C
B29: LEG LegalTech OHADA et conformité fiscale | C29: C | D29: R | E29: C | F29: I | H29: A | I29: R
B30: FIN Finance : frais, rétrocession CCI, reporting | C30: C | D30: R | E30: A | F30: C | H30: C
B31: SUP Support et accès privilégiés | C31: A | D31: R | E31: C | F31: I | H31: C
B32: OPS Exploitation, sécurité, continuité (SLA 99,5 %) | C32: A | D32: R | E32: I | F32: C | H32: C | I32: C
B33: REB Alerte & Rebond : entreprises en difficulté | C33: A | D33: R | E33: C | F33: C | H33: C | J33: C
B34: CNX Deal-Connect : événements B2B (Remo.co) | C34: C | D34: R | E34: C | F34: A | G34: C | I34: R
B35: DIA Guichet Diaspora et investissement | C35: A | D35: R | E35: C | F35: C | G35: C | H35: C | I35: R
B36: EXP Deal-Experts : mobilisation d'expert indépendant | C36: A | D36: R | E36: C | F36: C | H36: C | J36: R
B37: VDR-IA VDR Intelligence : DealLens et surfaces de diligence | C37: A | D37: R | E37: C | F37: I | G37: C | H37: C | I37: R

Sheet Parametres
B2: Paramètres et listes
B3: Listes déroulantes et règles de calcul de l'avancement. Modifier ici pour changer les valeurs proposées.
B5: Statut | C5: Avancement par défaut | D5: Compte dans la charge | F5: Priorité | H5: Version | J5: Module (code) | L5: Oui / Non | N5: Statut jalon | P5: Statut risque | R5: Statut décision
B6: À faire | C6: 0 | D6: Oui | F6: Haute | H6: V1 | J6: FOND | L6: Oui | N6: À venir | P6: Ouvert | R6: Ouvert
B7: En cours | C7: 0.25 | D7: Oui | F7: Moyenne | H7: V2 | J7: TRV | L7: Non | N7: En risque | P7: Surveillé | R7: En discussion
B8: En revue | C8: 0.9 | D8: Oui | F8: Basse | H8: V3 | J8: IDN | N8: Atteint | P8: Clos | R8: Tranché
B9: Bloquée | C9: 0.25 | D9: Oui | H9: V4 | J9: GOV | N9: Abandonné
B10: Complétée | C10: 1 | D10: Oui | H10: V5 | J10: CCI
B11: Backlog | C11: 0 | D11: Oui | J11: MKT
B12: Abandonnée | C12: 0 | D12: Non | J12: RPS
J13: SIG
J14: VDR
B15: Règle d'avancement d'une tâche | J15: NEG
B16: Si le statut est 'Complétée' : 100 %. Si un pourcentage est saisi dans la colonne '% saisi' de l'onglet Taches, il est utilisé. Sinon, l'avancement par défaut du statut ci-dessus s'applique.
B17: Une tâche 'Abandonnée' sort des totaux de charge. La charge réalisée = charge retenue x avancement. Les modules, versions, processus et le tableau de bord sont calculés à partir de ces deux colonnes.
J18: FIN
J19: SUP
J20: OPS
J21: REB
J22: CNX
J23: DIA
J24: EXP
J25: VDR-IA
